Workbook

Sheet NEW MODEL BY SES
A1: SERVICE ENABLING SYSTEM CATEGORIZATION MODEL 2024 HUNGARY | C1: Based on a file of slovnaft. | E1: EMPLOYEES | H1: GASTRO | K1: TOTAL NON-FUEL | N1: TOTAL FUEL | Q1: CAR WASH | T1: Points
C2: 1. step | E2: No. of Emp. | F2: No.of SeS | H2: Revenue (Ft) | I2: No. FC FULL | K2: Revenue (Ft) | L2: No.of SeS | N2: Liters | O2: No.of SeS | Q2: Revenue (Ft) | R2: No.of SeS
D3: MAX. | E3: =MAX(E19:E429) -> 28.993577 | F3: =COUNTIF(E$19:E$429,">"&E4) -> 166 | H3: =MAX(H19:H429) -> 2.8219574e+08 | I3: =COUNTIF(H$19:H$429,">"&H4) -> 130 | K3: =MAX(K19:K429) -> 3.341031e+08 | L3: =COUNTIF(K$19:K$429,">"&K4) -> 153 | N3: =MAX(N19:N429) -> 7.4002441e+09 | O3: =COUNTIF(N$19:N$429,">"&N4) -> 194 | Q3: =MAX(Q19:Q429) -> 44622686 | R3: =COUNTIF(Q$19:Q$429,">"&Q4) -> 127 | T3: MAX | U3: =MAX(W19:W429) -> 475
D4: AVG. | E4: =AVERAGE(E19:E429) -> 8.826164 | F4: ô | H4: =AVERAGE(H19:H429) -> 32287064 | I4: ô | K4: =AVERAGE(K19:K429) -> 55060029 | L4: ô | N4: =AVERAGE(N19:N429) -> 1.7091721e+09 | O4: ô | Q4: =AVERAGE(Q19:Q429) -> 4216758.7 | R4: ô | T4: AVERAGE | U4: =AVERAGEIF(W19:W429,">0") -> 182.73723
C5: Set criteria which differentiate SeS' and influence their complexity | D5: MIN. | E5: =MIN(E19:E429) -> 0 | F5: =COUNTIF(E$19:E$429,"<"&E4) -> 245 | H5: =MIN(H19:H429) -> 0 | I5: =COUNTIF(H$19:H$429,"<"&H4) -> 281 | K5: =MIN(K19:K429) -> 0 | L5: =COUNTIF(K$19:K$429,"<"&K4) -> 258 | N5: =MIN(N19:N429) -> 0 | O5: =COUNTIF(N$19:N$429,"<"&N4) -> 217 | Q5: =MIN(Q19:Q429) -> 0 | R5: =COUNTIF(Q$19:Q$429,"<"&Q4) -> 284 | T5: MIN | U5: =SMALL(W19:W429,COUNTIF(W19:W429,0)+1) -> 25.5
C7: 2. step | D7: RANGES | E7: Ranges | F7: No.of SeS | G7: Points | H7: Ranges | I7: No.of SeS | J7: Points | K7: Ranges | L7: No.of SeS | M7: Points | N7: Ranges | O7: No.of SeS | P7: Points | Q7: Ranges | R7: No.of SeS | S7: Points | T7: Values | U7: No.of SeS | V7: Points | W7: CATEGORY | X7: POINTS | Z7: No.of SeS | AA7: %
C8: Set ranges for each criterion and set points for ranges | D8: top 10% of ranking | F8: =COUNTIFS(E$19:E$429,">"&E9) -> 40 | G8: 150 | I8: =COUNTIFS(H$19:H$429,">"&H9) -> 42 | J8: 125 | L8: =COUNTIFS(K$19:K$429,">"&K9) -> 42 | M8: 100 | O8: =COUNTIFS(N$19:N$429,">"&N9) -> 42 | P8: 75 | R8: =COUNTIFS(Q$19:Q$429,">"&Q9) -> 42 | S8: 25 | T8: Has Highway | U8: =COUNTIF(T$19:T$429,T8) -> 34 | V8: 25 | W8: I | X8: > | Y8: =Y9 -> 325 | Z8: =COUNTIFS(W$19:W$429,">"&Y9) -> 46 | AA8: =Z8/$Y$12 -> 0.11192214 | AB8: top 10% of ranking
C9: Only blue numbers are to be changed | D9: next 20% of ranking | E9: {=INDEX(_xlfn._xlws.SORT(E19:E429,,1),TRUNC(COUNT(E19:E429)*(0.9)))} -> 13.451626 | F9: =COUNTIFS(E$19:E$429,">"&E10, E$19:E$429,"<="&E9) -> 81 | G9: 75 | H9: {=INDEX(_xlfn._xlws.SORT(H$19:H$429,,1),COUNT(H$19:H$429)*(0.9))} -> 60403867 | I9: =COUNTIFS(H$19:H$429,">"&H10, H$19:H$429,"<="&H9) -> 82 | J9: 62.5 | K9: {=INDEX(_xlfn._xlws.SORT(K$19:K$429,,1),TRUNC(COUNT(K$19:K$429)*(0.9)))} -> 97091226 | L9: =COUNTIFS(K$19:K$429,">"&K10, K$19:K$429,"<="&K9) -> 82 | M9: 50 | N9: {=INDEX(_xlfn._xlws.SORT(N$19:N$429,,1),TRUNC(COUNT(N$19:N$429)*(0.9)))} -> 2.7618267e+09 | O9: =COUNTIFS(N$19:N$429,">"&N10, N$19:N$429,"<="&N9) -> 82 | P9: 40 | Q9: {=INDEX(_xlfn._xlws.SORT(Q$19:Q$429,,1),TRUNC(COUNT(Q$19:Q$429)*(0.9)))} -> 14839420 | R9: =COUNTIFS(Q$19:Q$429,">"&Q10, Q$19:Q$429,"<="&Q9) -> 82 | S9: 12.5 | T9: No Highway | U9: =COUNTIF(T$19:T$429,T9) -> 377 | V9: 12.5 | W9: II | X9: =Y10&" -" -> 192.5 - | Y9: 325 | Z9: =COUNTIFS(W$19:W$429,">"&Y10, W$19:W$429,"<="&Y9) -> 95 | AA9: =Z9/$Y$12 -> 0.23114355 | AB9: next 20% of ranking
D10: next 35% of ranking | E10: {=INDEX(_xlfn._xlws.SORT(E$19:E$429,,1),TRUNC(COUNT(E$19:E$429)*(0.7)))} -> 9.6974105 | F10: =COUNTIFS(E$19:E$429,">"&E11, E$19:E$429,"<="&E10) -> 146 | G10: 45 | H10: {=INDEX(_xlfn._xlws.SORT(H$19:H$429,,1),COUNT(H$19:H$429)*(0.7))} -> 33023613 | I10: =COUNTIFS(H$19:H$429,">"&H11, H$19:H$429,"<="&H10) -> 144 | J10: 37.5 | K10: {=INDEX(_xlfn._xlws.SORT(K$19:K$429,,1),TRUNC(COUNT(K$19:K$429)*(0.7)))} -> 61459303 | L10: =COUNTIFS(K$19:K$429,">"&K11, K$19:K$429,"<="&K10) -> 144 | M10: 30 | N10: {=INDEX(_xlfn._xlws.SORT(N$19:N$429,,1),TRUNC(COUNT(N$19:N$429)*(0.7)))} -> 2.106685e+09 | O10: =COUNTIFS(N$19:N$429,">"&N11, N$19:N$429,"<="&N10) -> 144 | P10: 22 | Q10: {=INDEX(_xlfn._xlws.SORT(Q$19:Q$429,,1),TRUNC(COUNT(Q$19:Q$429)*(0.7)))} -> 4383858.3 | R10: =COUNTIFS(Q$19:Q$429,">"&Q11, Q$19:Q$429,"<="&Q10) -> 31 | S10: 7.5 | W10: III | X10: =Y11&" -" -> 120.5 - | Y10: 192.5 | Z10: =COUNTIFS(W$19:W$429,">"&Y11, W$19:W$429,"<="&Y10) -> 158 | AA10: =Z10/$Y$12 -> 0.38442822 | AB10: next 40% of ranking
C11: Hints: 1) balance with number of SeS which fall within a range 2) criteria with greater impact on SeS complexity should get more points | D11: bottom 35% of ranking | E11: {=INDEX(_xlfn._xlws.SORT(E$19:E$429,,1),TRUNC(COUNT(E$19:E$429)*(0.35)))} -> 6.506607 | F11: =COUNTIFS(E$19:E$429,">="&E12, E$19:E$429,"<="&E11) -> 144 | G11: 30 | H11: {=INDEX(_xlfn._xlws.SORT(H$19:H$429,,1),COUNT(H$19:H$429)*(0.35))} -> 17219525 | I11: =COUNTIFS(H$19:H$429,">="&H12, H$19:H$429,"<="&H11) -> 143 | J11: 25 | K11: {=INDEX(_xlfn._xlws.SORT(K$19:K$429,,1),TRUNC(COUNT(K$19:K$429)*(0.35)))} -> 37639149 | L11: =COUNTIFS(K$19:K$429,">="&K12, K$19:K$429,"<="&K11) -> 143 | M11: 20 | N11: {=INDEX(_xlfn._xlws.SORT(N$19:N$429,,1),TRUNC(COUNT(N$19:N$429)*(0.35)))} -> 1.3744732e+09 | O11: =COUNTIFS(N$19:N$429,">="&N12, N$19:N$429,"<="&N11) -> 143 | P11: 13 | Q11: {=INDEX(_xlfn._xlws.SORT(Q$19:Q$429,,1),TRUNC(COUNT(Q$19:Q$429)*(0.35)))} -> 0 | R11: =COUNTIFS(Q$19:Q$429,">="&Q12, Q$19:Q$429,"<="&Q11) -> 256 | S11: 5 | W11: IV | X11: ="0 -" -> 0 - | Y11: 120.5 | Z11: =COUNTIFS(W$19:W$429,"<="&Y11) -> 112 | AA11: =Z11/$Y$12 -> 0.27250608 | AB11: bottom 30% of ranking
E12: 0 | H12: 0 | K12: 0 | N12: 0 | Q12: 0 | W12: Total no. of SeS: | Y12: =SUM(Z8:Z11) -> 411 | AA12: =Y12/$Y$12 -> 1
C13: Fill in data for criteria in the table below | D13: Total no. od SeS: | F13: =SUM(F8:F11) -> 411 | I13: =SUM(I8:I11) -> 411 | L13: =SUM(L8:L11) -> 411 | O13: =SUM(O8:O11) -> 411 | R13: =SUM(R8:R11) -> 411 | U13: =SUM(U8:U12) -> 411
E15: EMPLOYEES | H15: GASTRO | K15: TOTAL NON-FUEL | N15: TOTAL FUEL | Q15: CAR WASH | T15: HIGHWAY | W15: 3 | X15: 3 | Y15: 3
W16: 4 | X16: 4 | Y16: 4
A17: Area Manager | B17: Code | C17: Service Enabling System | E17: No. of Employees | F17: No. of Emp. POINTS | H17: GASTRO revenue (Ft) | I17: TOTAL FC POINTS | K17: TOTAL NON-FUEL revenue (Ft) | L17: TOTAL NF POINTS | N17: TOTAL FUEL (Liter) | O17: FUEL POINTS | Q17: CAR WASH revenue (Ft) | R17: CAR WASH POINTS | T17: Highway indicator | U17: CAR WASH POINTS | W17: TOTAL SCORE | X17: NEW CATEGORY (ROMAN) | Y17: NEW CATEGORY (ARABIC)
B18: =B17 -> Code | C18: =C17 -> Service Enabling System | E18: =E17 -> No. of Employees | F18: =F17 -> No. of Emp. POINTS | H18: =H17 -> GASTRO revenue (Ft) | I18: =I17 -> TOTAL FC POINTS | K18: =K17 -> TOTAL NON-FUEL revenue (Ft) | L18: =L17 -> TOTAL NF POINTS | N18: =N17 -> TOTAL FUEL (Liter) | O18: =O17 -> FUEL POINTS | Q18: =Q17 -> CAR WASH revenue (Ft) | R18: =R17 -> CAR WASH POINTS | T18: =T17 -> Highway indicator | U18: =U17 -> CAR WASH POINTS | W18: =W17 -> TOTAL SCORE | X18: =X17 -> NEW CATEGORY (ROMAN) | Y18: =Y17 -> NEW CATEGORY (ARABIC)
A19: Area Manager 1 | B19: 7990200 | C19: Service Enabling System1 | E19: 6.131607 | F19: =IF(E19=0,0,IF(E19<=E$11,G$11,IF(E19<=E$10,G$10,IF(E19<=E$9,G$9,G$8)))) -> 30 | H19: 18387591 | I19: =IF(H19=0,0,IF(H19<=H$11,J$11,IF(H19<=H$10,J$10,IF(H19<=H$9,J$9,J$8)))) -> 37.5 | K19: 42922021 | L19: =IF(K19=0,0,IF(K19<=K$11,M$11,IF(K19<=K$10,M$10,IF(K19<=K$9,M$9,M$8)))) -> 30 | N19: 1.7712494e+09 | O19: =IF(N19=0,0,IF(N19<=N$11,P$11,IF(N19<=N$10,P$10,IF(N19<=N$9,P$9,P$8)))) -> 22 | Q19: 0 | R19: =IF(Q18=0,0,IF(Q18<=Q$11,S$11,IF(Q18<=Q$10,S$10,IF(Q18<=Q$9,S$9,S$8)))) -> 25 | T19: No Highway | U19: =IF(T19=0,0,IF(T19=T$9,V$9,V$8)) -> 12.5 | W19: =F19+I19+L19+O19+R19+U19 -> 157 | X19: =IF(W19<=$Y$11,$W$11,IF(W19<=$Y$10,$W$10,IF(W19<=$Y$9,$W$9,$W$8))) -> III | Y19: =IF(X19="IV",4,IF(X19="III",3,IF(X19="II",2,1))) -> 3
A20: Area Manager 2 | B20: 6172100 | C20: Service Enabling System2 | E20: 6.4649403 | F20: =IF(E20=0,0,IF(E20<=E$11,G$11,IF(E20<=E$10,G$10,IF(E20<=E$9,G$9,G$8)))) -> 30 | H20: 18222206 | I20: =IF(H20=0,0,IF(H20<=H$11,J$11,IF(H20<=H$10,J$10,IF(H20<=H$9,J$9,J$8)))) -> 37.5 | K20: 31859119 | L20: =IF(K20=0,0,IF(K20<=K$11,M$11,IF(K20<=K$10,M$10,IF(K20<=K$9,M$9,M$8)))) -> 20 | N20: 1.6927532e+09 | O20: =IF(N20=0,0,IF(N20<=N$11,P$11,IF(N20<=N$10,P$10,IF(N20<=N$9,P$9,P$8)))) -> 22 | Q20: 0 | R20: =IF(Q19=0,0,IF(Q19<=Q$11,S$11,IF(Q19<=Q$10,S$10,IF(Q19<=Q$9,S$9,S$8)))) -> 0 | T20: No Highway | U20: =IF(T20=0,0,IF(T20=T$9,V$9,V$8)) -> 12.5 | W20: =F20+I20+L20+O20+R20+U20 -> 122 | X20: =IF(W20<=$Y$11,$W$11,IF(W20<=$Y$10,$W$10,IF(W20<=$Y$9,$W$9,$W$8))) -> III | Y20: =IF(X20="IV",4,IF(X20="III",3,IF(X20="II",2,1))) -> 3
A21: Area Manager 3 | B21: 3836200 | C21: Service Enabling System3 | E21: 6.381607 | F21: =IF(E21=0,0,IF(E21<=E$11,G$11,IF(E21<=E$10,G$10,IF(E21<=E$9,G$9,G$8)))) -> 30 | H21: 12939378 | I21: =IF(H21=0,0,IF(H21<=H$11,J$11,IF(H21<=H$10,J$10,IF(H21<=H$9,J$9,J$8)))) -> 25 | K21: 52553933 | L21: =IF(K21=0,0,IF(K21<=K$11,M$11,IF(K21<=K$10,M$10,IF(K21<=K$9,M$9,M$8)))) -> 30 | N21: 1.5375573e+09 | O21: =IF(N21=0,0,IF(N21<=N$11,P$11,IF(N21<=N$10,P$10,IF(N21<=N$9,P$9,P$8)))) -> 22 | Q21: 0 | R21: =IF(Q21=0,0,IF(Q21<=Q$11,S$11,IF(Q21<=Q$10,S$10,IF(Q21<=Q$9,S$9,S$8)))) -> 0 | T21: No Highway | U21: =IF(T21=0,0,IF(T21=T$9,V$9,V$8)) -> 12.5 | W21: =F21+I21+L21+O21+R21+U21 -> 119.5 | X21: =IF(W21<=$Y$11,$W$11,IF(W21<=$Y$10,$W$10,IF(W21<=$Y$9,$W$9,$W$8))) -> IV | Y21: =IF(X21="IV",4,IF(X21="III",3,IF(X21="II",2,1))) -> 4 | AC21: 2
A22: Area Manager 4 | B22: 4287600 | C22: Service Enabling System4 | E22: 6.5695789 | F22: =IF(E22=0,0,IF(E22<=E$11,G$11,IF(E22<=E$10,G$10,IF(E22<=E$9,G$9,G$8)))) -> 45 | H22: 22201509 | I22: =IF(H22=0,0,IF(H22<=H$11,J$11,IF(H22<=H$10,J$10,IF(H22<=H$9,J$9,J$8)))) -> 37.5 | K22: 43323022 | L22: =IF(K22=0,0,IF(K22<=K$11,M$11,IF(K22<=K$10,M$10,IF(K22<=K$9,M$9,M$8)))) -> 30 | N22: 2.0112564e+09 | O22: =IF(N22=0,0,IF(N22<=N$11,P$11,IF(N22<=N$10,P$10,IF(N22<=N$9,P$9,P$8)))) -> 22 | Q22: 11171200 | R22: =IF(Q22=0,0,IF(Q22<=Q$11,S$11,IF(Q22<=Q$10,S$10,IF(Q22<=Q$9,S$9,S$8)))) -> 12.5 | T22: No Highway | U22: =IF(T22=0,0,IF(T22=T$9,V$9,V$8)) -> 12.5 | W22: =F22+I22+L22+O22+R22+U22 -> 159.5 | X22: =IF(W22<=$Y$11,$W$11,IF(W22<=$Y$10,$W$10,IF(W22<=$Y$9,$W$9,$W$8))) -> III | Y22: =IF(X22="IV",4,IF(X22="III",3,IF(X22="II",2,1))) -> 3 | AC22: 3
A23: Area Manager 5 | B23: 3559900 | C23: Service Enabling System5 | E23: 6.8195789 | F23: =IF(E23=0,0,IF(E23<=E$11,G$11,IF(E23<=E$10,G$10,IF(E23<=E$9,G$9,G$8)))) -> 45 | H23: 16463433 | I23: =IF(H23=0,0,IF(H23<=H$11,J$11,IF(H23<=H$10,J$10,IF(H23<=H$9,J$9,J$8)))) -> 25 | K23: 46730954 | L23: =IF(K23=0,0,IF(K23<=K$11,M$11,IF(K23<=K$10,M$10,IF(K23<=K$9,M$9,M$8)))) -> 30 | N23: 1.5607576e+09 | O23: =IF(N23=0,0,IF(N23<=N$11,P$11,IF(N23<=N$10,P$10,IF(N23<=N$9,P$9,P$8)))) -> 22 | Q23: 0 | R23: =IF(Q23=0,0,IF(Q23<=Q$11,S$11,IF(Q23<=Q$10,S$10,IF(Q23<=Q$9,S$9,S$8)))) -> 0 | T23: No Highway | U23: =IF(T23=0,0,IF(T23=T$9,V$9,V$8)) -> 12.5 | W23: =F23+I23+L23+O23+R23+U23 -> 134.5 | X23: =IF(W23<=$Y$11,$W$11,IF(W23<=$Y$10,$W$10,IF(W23<=$Y$9,$W$9,$W$8))) -> III | Y23: =IF(X23="IV",4,IF(X23="III",3,IF(X23="II",2,1))) -> 3 | AC23: 4
A24: Area Manager 6 | B24: 6246600 | C24: Service Enabling System6 | E24: 6.2982736 | F24: =IF(E24=0,0,IF(E24<=E$11,G$11,IF(E24<=E$10,G$10,IF(E24<=E$9,G$9,G$8)))) -> 30 | H24: 11475939 | I24: =IF(H24=0,0,IF(H24<=H$11,J$11,IF(H24<=H$10,J$10,IF(H24<=H$9,J$9,J$8)))) -> 25 | K24: 35211972 | L24: =IF(K24=0,0,IF(K24<=K$11,M$11,IF(K24<=K$10,M$10,IF(K24<=K$9,M$9,M$8)))) -> 20 | N24: 9.9808875e+08 | O24: =IF(N24=0,0,IF(N24<=N$11,P$11,IF(N24<=N$10,P$10,IF(N24<=N$9,P$9,P$8)))) -> 13 | Q24: 0 | R24: =IF(Q24=0,0,IF(Q24<=Q$11,S$11,IF(Q24<=Q$10,S$10,IF(Q24<=Q$9,S$9,S$8)))) -> 0 | T24: No Highway | U24: =IF(T24=0,0,IF(T24=T$9,V$9,V$8)) -> 12.5 | W24: =F24+I24+L24+O24+R24+U24 -> 100.5 | X24: =IF(W24<=$Y$11,$W$11,IF(W24<=$Y$10,$W$10,IF(W24<=$Y$9,$W$9,$W$8))) -> IV | Y24: =IF(X24="IV",4,IF(X24="III",3,IF(X24="II",2,1))) -> 4
A25: Area Manager 4 | B25: 4237400 | C25: Service Enabling System7 | E25: 5.5056631 | F25: =IF(E25=0,0,IF(E25<=E$11,G$11,IF(E25<=E$10,G$10,IF(E25<=E$9,G$9,G$8)))) -> 30 | H25: 22563282 | I25: =IF(H25=0,0,IF(H25<=H$11,J$11,IF(H25<=H$10,J$10,IF(H25<=H$9,J$9,J$8)))) -> 37.5 | K25: 49200236 | L25: =IF(K25=0,0,IF(K25<=K$11,M$11,IF(K25<=K$10,M$10,IF(K25<=K$9,M$9,M$8)))) -> 30 | N25: 7.122357e+08 | O25: =IF(N25=0,0,IF(N25<=N$11,P$11,IF(N25<=N$10,P$10,IF(N25<=N$9,P$9,P$8)))) -> 13 | Q25: 0 | R25: =IF(Q25=0,0,IF(Q25<=Q$11,S$11,IF(Q25<=Q$10,S$10,IF(Q25<=Q$9,S$9,S$8)))) -> 0 | T25: No Highway | U25: =IF(T25=0,0,IF(T25=T$9,V$9,V$8)) -> 12.5 | W25: =F25+I25+L25+O25+R25+U25 -> 123 | X25: =IF(W25<=$Y$11,$W$11,IF(W25<=$Y$10,$W$10,IF(W25<=$Y$9,$W$9,$W$8))) -> III | Y25: =IF(X25="IV",4,IF(X25="III",3,IF(X25="II",2,1))) -> 3
A26: Area Manager 6 | B26: 7870200 | C26: Service Enabling System8 | E26: 10.135382 | F26: =IF(E26=0,0,IF(E26<=E$11,G$11,IF(E26<=E$10,G$10,IF(E26<=E$9,G$9,G$8)))) -> 75 | H26: 35321225 | I26: =IF(H26=0,0,IF(H26<=H$11,J$11,IF(H26<=H$10,J$10,IF(H26<=H$9,J$9,J$8)))) -> 62.5 | K26: 47914999 | L26: =IF(K26=0,0,IF(K26<=K$11,M$11,IF(K26<=K$10,M$10,IF(K26<=K$9,M$9,M$8)))) -> 30 | N26: 2.1130297e+09 | O26: =IF(N26=0,0,IF(N26<=N$11,P$11,IF(N26<=N$10,P$10,IF(N26<=N$9,P$9,P$8)))) -> 40 | Q26: 7176299.2 | R26: =IF(Q26=0,0,IF(Q26<=Q$11,S$11,IF(Q26<=Q$10,S$10,IF(Q26<=Q$9,S$9,S$8)))) -> 12.5 | T26: No Highway | U26: =IF(T26=0,0,IF(T26=T$9,V$9,V$8)) -> 12.5 | W26: =F26+I26+L26+O26+R26+U26 -> 232.5 | X26: =IF(W26<=$Y$11,$W$11,IF(W26<=$Y$10,$W$10,IF(W26<=$Y$9,$W$9,$W$8))) -> II | Y26: =IF(X26="IV",4,IF(X26="III",3,IF(X26="II",2,1))) -> 2
A27: Area Manager 4 | B27: 4238500 | C27: Service Enabling System9 | E27: 10.135382 | F27: =IF(E27=0,0,IF(E27<=E$11,G$11,IF(E27<=E$10,G$10,IF(E27<=E$9,G$9,G$8)))) -> 75 | H27: 65285859 | I27: =IF(H27=0,0,IF(H27<=H$11,J$11,IF(H27<=H$10,J$10,IF(H27<=H$9,J$9,J$8)))) -> 125 | K27: 67991186 | L27: =IF(K27=0,0,IF(K27<=K$11,M$11,IF(K27<=K$10,M$10,IF(K27<=K$9,M$9,M$8)))) -> 50 | N27: 1.4758418e+09 | O27: =IF(N27=0,0,IF(N27<=N$11,P$11,IF(N27<=N$10,P$10,IF(N27<=N$9,P$9,P$8)))) -> 22 | Q27: 0 | R27: =IF(Q27=0,0,IF(Q27<=Q$11,S$11,IF(Q27<=Q$10,S$10,IF(Q27<=Q$9,S$9,S$8)))) -> 0 | T27: No Highway | U27: =IF(T27=0,0,IF(T27=T$9,V$9,V$8)) -> 12.5 | W27: =F27+I27+L27+O27+R27+U27 -> 284.5 | X27: =IF(W27<=$Y$11,$W$11,IF(W27<=$Y$10,$W$10,IF(W27<=$Y$9,$W$9,$W$8))) -> II | Y27: =IF(X27="IV",4,IF(X27="III",3,IF(X27="II",2,1))) -> 2
A28: Area Manager 7 | B28: 7337100 | C28: Service Enabling System10 | E28: 6.6161 | F28: =IF(E28=0,0,IF(E28<=E$11,G$11,IF(E28<=E$10,G$10,IF(E28<=E$9,G$9,G$8)))) -> 45 | H28: 13387366 | I28: =IF(H28=0,0,IF(H28<=H$11,J$11,IF(H28<=H$10,J$10,IF(H28<=H$9,J$9,J$8)))) -> 25 | K28: 38703113 | L28: =IF(K28=0,0,IF(K28<=K$11,M$11,IF(K28<=K$10,M$10,IF(K28<=K$9,M$9,M$8)))) -> 30 | N28: 1.5683303e+09 | O28: =IF(N28=0,0,IF(N28<=N$11,P$11,IF(N28<=N$10,P$10,IF(N28<=N$9,P$9,P$8)))) -> 22 | Q28: 0 | R28: =IF(Q28=0,0,IF(Q28<=Q$11,S$11,IF(Q28<=Q$10,S$10,IF(Q28<=Q$9,S$9,S$8)))) -> 0 | T28: No Highway | U28: =IF(T28=0,0,IF(T28=T$9,V$9,V$8)) -> 12.5 | W28: =F28+I28+L28+O28+R28+U28 -> 134.5 | X28: =IF(W28<=$Y$11,$W$11,IF(W28<=$Y$10,$W$10,IF(W28<=$Y$9,$W$9,$W$8))) -> III | Y28: =IF(X28="IV",4,IF(X28="III",3,IF(X28="II",2,1))) -> 3
A29: Area Manager 8 | B29: 3545900 | C29: Service Enabling System11 | E29: 13.451626 | F29: =IF(E29=0,0,IF(E29<=E$11,G$11,IF(E29<=E$10,G$10,IF(E29<=E$9,G$9,G$8)))) -> 75 | H29: 23668642 | I29: =IF(H29=0,0,IF(H29<=H$11,J$11,IF(H29<=H$10,J$10,IF(H29<=H$9,J$9,J$8)))) -> 37.5 | K29: 58848501 | L29: =IF(K29=0,0,IF(K29<=K$11,M$11,IF(K29<=K$10,M$10,IF(K29<=K$9,M$9,M$8)))) -> 30 | N29: 2.1700502e+09 | O29: =IF(N29=0,0,IF(N29<=N$11,P$11,IF(N29<=N$10,P$10,IF(N29<=N$9,P$9,P$8)))) -> 40 | Q29: 1252148.1 | R29: =IF(Q29=0,0,IF(Q29<=Q$11,S$11,IF(Q29<=Q$10,S$10,IF(Q29<=Q$9,S$9,S$8)))) -> 7.5 | T29: No Highway | U29: =IF(T29=0,0,IF(T29=T$9,V$9,V$8)) -> 12.5 | W29: =F29+I29+L29+O29+R29+U29 -> 202.5 | X29: =IF(W29<=$Y$11,$W$11,IF(W29<=$Y$10,$W$10,IF(W29<=$Y$9,$W$9,$W$8))) -> II | Y29: =IF(X29="IV",4,IF(X29="III",3,IF(X29="II",2,1))) -> 2
A30: Area Manager 9 | B30: 4242900 | C30: Service Enabling System12 | E30: 10.135382 | F30: =IF(E30=0,0,IF(E30<=E$11,G$11,IF(E30<=E$10,G$10,IF(E30<=E$9,G$9,G$8)))) -> 75 | H30: 70170988 | I30: =IF(H30=0,0,IF(H30<=H$11,J$11,IF(H30<=H$10,J$10,IF(H30<=H$9,J$9,J$8)))) -> 125 | K30: 1.1361453e+08 | L30: =IF(K30=0,0,IF(K30<=K$11,M$11,IF(K30<=K$10,M$10,IF(K30<=K$9,M$9,M$8)))) -> 100 | N30: 2.3163671e+09 | O30: =IF(N30=0,0,IF(N30<=N$11,P$11,IF(N30<=N$10,P$10,IF(N30<=N$9,P$9,P$8)))) -> 40 | Q30: 0 | R30: =IF(Q30=0,0,IF(Q30<=Q$11,S$11,IF(Q30<=Q$10,S$10,IF(Q30<=Q$9,S$9,S$8)))) -> 0 | T30: No Highway | U30: =IF(T30=0,0,IF(T30=T$9,V$9,V$8)) -> 12.5 | W30: =F30+I30+L30+O30+R30+U30 -> 352.5 | X30: =IF(W30<=$Y$11,$W$11,IF(W30<=$Y$10,$W$10,IF(W30<=$Y$9,$W$9,$W$8))) -> I | Y30: =IF(X30="IV",4,IF(X30="III",3,IF(X30="II",2,1))) -> 1
A31: Area Manager 9 | B31: 4268400 | C31: Service Enabling System13 | E31: 5.693635 | F31: =IF(E31=0,0,IF(E31<=E$11,G$11,IF(E31<=E$10,G$10,IF(E31<=E$9,G$9,G$8)))) -> 30 | H31: 28798256 | I31: =IF(H31=0,0,IF(H31<=H$11,J$11,IF(H31<=H$10,J$10,IF(H31<=H$9,J$9,J$8)))) -> 37.5 | K31: 79342868 | L31: =IF(K31=0,0,IF(K31<=K$11,M$11,IF(K31<=K$10,M$10,IF(K31<=K$9,M$9,M$8)))) -> 50 | N31: 1.8632632e+09 | O31: =IF(N31=0,0,IF(N31<=N$11,P$11,IF(N31<=N$10,P$10,IF(N31<=N$9,P$9,P$8)))) -> 22 | Q31: 0 | R31: =IF(Q31=0,0,IF(Q31<=Q$11,S$11,IF(Q31<=Q$10,S$10,IF(Q31<=Q$9,S$9,S$8)))) -> 0 | T31: No Highway | U31: =IF(T31=0,0,IF(T31=T$9,V$9,V$8)) -> 12.5 | W31: =F31+I31+L31+O31+R31+U31 -> 152 | X31: =IF(W31<=$Y$11,$W$11,IF(W31<=$Y$10,$W$10,IF(W31<=$Y$9,$W$9,$W$8))) -> III | Y31: =IF(X31="IV",4,IF(X31="III",3,IF(X31="II",2,1))) -> 3
A32: Area Manager 4 | B32: 8245200 | C32: Service Enabling System14 | E32: 5.5056631 | F32: =IF(E32=0,0,IF(E32<=E$11,G$11,IF(E32<=E$10,G$10,IF(E32<=E$9,G$9,G$8)))) -> 30 | H32: 28219862 | I32: =IF(H32=0,0,IF(H32<=H$11,J$11,IF(H32<=H$10,J$10,IF(H32<=H$9,J$9,J$8)))) -> 37.5 | K32: 44122399 | L32: =IF(K32=0,0,IF(K32<=K$11,M$11,IF(K32<=K$10,M$10,IF(K32<=K$9,M$9,M$8)))) -> 30 | N32: 7.938546e+08 | O32: =IF(N32=0,0,IF(N32<=N$11,P$11,IF(N32<=N$10,P$10,IF(N32<=N$9,P$9,P$8)))) -> 13 | Q32: 0 | R32: =IF(Q32=0,0,IF(Q32<=Q$11,S$11,IF(Q32<=Q$10,S$10,IF(Q32<=Q$9,S$9,S$8)))) -> 0 | T32: No Highway | U32: =IF(T32=0,0,IF(T32=T$9,V$9,V$8)) -> 12.5 | W32: =F32+I32+L32+O32+R32+U32 -> 123 | X32: =IF(W32<=$Y$11,$W$11,IF(W32<=$Y$10,$W$10,IF(W32<=$Y$9,$W$9,$W$8))) -> III | Y32: =IF(X32="IV",4,IF(X32="III",3,IF(X32="II",2,1))) -> 3
A33: Area Manager 4 | B33: 5065400 | C33: Service Enabling System15 | E33: 6.131607 | F33: =IF(E33=0,0,IF(E33<=E$11,G$11,IF(E33<=E$10,G$10,IF(E33<=E$9,G$9,G$8)))) -> 30 | H33: 26977481 | I33: =IF(H33=0,0,IF(H33<=H$11,J$11,IF(H33<=H$10,J$10,IF(H33<=H$9,J$9,J$8)))) -> 37.5 | K33: 69619586 | L33: =IF(K33=0,0,IF(K33<=K$11,M$11,IF(K33<=K$10,M$10,IF(K33<=K$9,M$9,M$8)))) -> 50 | N33: 1.813463e+09 | O33: =IF(N33=0,0,IF(N33<=N$11,P$11,IF(N33<=N$10,P$10,IF(N33<=N$9,P$9,P$8)))) -> 22 | Q33: 0 | R33: =IF(Q33=0,0,IF(Q33<=Q$11,S$11,IF(Q33<=Q$10,S$10,IF(Q33<=Q$9,S$9,S$8)))) -> 0 | T33: No Highway | U33: =IF(T33=0,0,IF(T33=T$9,V$9,V$8)) -> 12.5 | W33: =F33+I33+L33+O33+R33+U33 -> 152 | X33: =IF(W33<=$Y$11,$W$11,IF(W33<=$Y$10,$W$10,IF(W33<=$Y$9,$W$9,$W$8))) -> III | Y33: =IF(X33="IV",4,IF(X33="III",3,IF(X33="II",2,1))) -> 3
A34: Area Manager 1 | B34: 4240700 | C34: Service Enabling System16 | E34: 10.135382 | F34: =IF(E34=0,0,IF(E34<=E$11,G$11,IF(E34<=E$10,G$10,IF(E34<=E$9,G$9,G$8)))) -> 75 | H34: 55495457 | I34: =IF(H34=0,0,IF(H34<=H$11,J$11,IF(H34<=H$10,J$10,IF(H34<=H$9,J$9,J$8)))) -> 62.5 | K34: 94431896 | L34: =IF(K34=0,0,IF(K34<=K$11,M$11,IF(K34<=K$10,M$10,IF(K34<=K$9,M$9,M$8)))) -> 50 | N34: 2.2825791e+09 | O34: =IF(N34=0,0,IF(N34<=N$11,P$11,IF(N34<=N$10,P$10,IF(N34<=N$9,P$9,P$8)))) -> 40 | Q34: 11308544 | R34: =IF(Q34=0,0,IF(Q34<=Q$11,S$11,IF(Q34<=Q$10,S$10,IF(Q34<=Q$9,S$9,S$8)))) -> 12.5 | T34: No Highway | U34: =IF(T34=0,0,IF(T34=T$9,V$9,V$8)) -> 12.5 | W34: =F34+I34+L34+O34+R34+U34 -> 252.5 | X34: =IF(W34<=$Y$11,$W$11,IF(W34<=$Y$10,$W$10,IF(W34<=$Y$9,$W$9,$W$8))) -> II | Y34: =IF(X34="IV",4,IF(X34="III",3,IF(X34="II",2,1))) -> 2
A35: Area Manager 4 | B35: 5039200 | C35: Service Enabling System17 | E35: 16.041951 | F35: =IF(E35=0,0,IF(E35<=E$11,G$11,IF(E35<=E$10,G$10,IF(E35<=E$9,G$9,G$8)))) -> 150 | H35: 96400527 | I35: =IF(H35=0,0,IF(H35<=H$11,J$11,IF(H35<=H$10,J$10,IF(H35<=H$9,J$9,J$8)))) -> 125 | K35: 1.7288181e+08 | L35: =IF(K35=0,0,IF(K35<=K$11,M$11,IF(K35<=K$10,M$10,IF(K35<=K$9,M$9,M$8)))) -> 100 | N35: 2.1430985e+09 | O35: =IF(N35=0,0,IF(N35<=N$11,P$11,IF(N35<=N$10,P$10,IF(N35<=N$9,P$9,P$8)))) -> 40 | Q35: 0 | R35: =IF(Q35=0,0,IF(Q35<=Q$11,S$11,IF(Q35<=Q$10,S$10,IF(Q35<=Q$9,S$9,S$8)))) -> 0 | T35: Has Highway | U35: =IF(T35=0,0,IF(T35=T$9,V$9,V$8)) -> 25 | W35: =F35+I35+L35+O35+R35+U35 -> 440 | X35: =IF(W35<=$Y$11,$W$11,IF(W35<=$Y$10,$W$10,IF(W35<=$Y$9,$W$9,$W$8))) -> I | Y35: =IF(X35="IV",4,IF(X35="III",3,IF(X35="II",2,1))) -> 1
... A429: Area Manager 4 | B429: 4267300 | C429: Service Enabling System411 | E429: 6.131607 | F429: =IF(E429=0,0,IF(E429<=E$11,G$11,IF(E429<=E$10,G$10,IF(E429<=E$9,G$9,G$8)))) -> 30 | H429: 32659717 | I429: =IF(H429=0,0,IF(H429<=H$11,J$11,IF(H429<=H$10,J$10,IF(H429<=H$9,J$9,J$8)))) -> 37.5 | K429: 59087598 | L429: =IF(K429=0,0,IF(K429<=K$11,M$11,IF(K429<=K$10,M$10,IF(K429<=K$9,M$9,M$8)))) -> 30 | N429: 1.9602402e+09 | O429: =IF(N429=0,0,IF(N429<=N$11,P$11,IF(N429<=N$10,P$10,IF(N429<=N$9,P$9,P$8)))) -> 22 | Q429: 0 | R429: =IF(Q429=0,0,IF(Q429<=Q$11,S$11,IF(Q429<=Q$10,S$10,IF(Q429<=Q$9,S$9,S$8)))) -> 0 | T429: No Highway | U429: =IF(T429=0,0,IF(T429=T$9,V$9,V$8)) -> 12.5 | W429: =F429+I429+L429+O429+R429+U429 -> 132 | X429: =IF(W429<=$Y$11,$W$11,IF(W429<=$Y$10,$W$10,IF(W429<=$Y$9,$W$9,$W$8))) -> III | Y429: =IF(X429="IV",4,IF(X429="III",3,IF(X429="II",2,1))) -> 3

Sheet calcuation
A1: EMPLOYEES | E1: TOTAL FUEL | I1: LPG | M1: TOTAL NON-FUEL | Q1: GASTRO | U1: CAR WASH | Y1: Total
A2: Code | B2: GASTRO revenue (EUR) | C2: d | E2: Code | F2: GASTRO revenue (EUR) | G2: d | I2: d | J2: d | K2: d | M2: d | N2: d | O2: d | Q2: d | R2: d | S2: d | U2: d | V2: d | W2: d | Y2: d | Z2: d | AA2: d
A3: 10748 | B3: 34.48 | C3: =PERCENTRANK($B$3:$B$241,B3) -> 1 | E3: 10612 | F3: 9320662.4 | G3: =PERCENTRANK($F$3:$F$241,F3) -> 1 | I3: 10106 | J3: 522419.41 | K3: =PERCENTRANK($J$3:$J$118,J3) -> 1 | M3: 10748 | N3: 3036978.2 | O3: =PERCENTRANK($N$3:$N$241,N3) -> 1 | Q3: 10748 | R3: 1385751.1 | S3: =PERCENTRANK($R$3:$R$241,R3) -> 1 | U3: 20401 | V3: 81496.34 | W3: =PERCENTRANK($V$3:$V$184,V3) -> 1 | Y3: 10106 | Z3: 482.5 | AA3: =PERCENTRANK($Z$3:$Z$241,Z3) -> 1
A4: 40144 | B4: 26.76 | C4: =PERCENTRANK($B$3:$B$241,B4) -> 0.995 | E4: 10611 | F4: 7483728.3 | G4: =PERCENTRANK($F$3:$F$241,F4) -> 0.995 | I4: 10124 | J4: 473992.41 | K4: =PERCENTRANK($J$3:$J$118,J4) -> 0.991 | M4: 10612 | N4: 2588735.5 | O4: =PERCENTRANK($N$3:$N$241,N4) -> 0.995 | Q4: 11412 | R4: 1025325.2 | S4: =PERCENTRANK($R$3:$R$241,R4) -> 0.995 | U4: 20519 | V4: 70870.22 | W4: =PERCENTRANK($V$3:$V$184,V4) -> 0.994 | Y4: 11420 | Z4: 475 | AA4: =PERCENTRANK($Z$3:$Z$241,Z4) -> 0.995
A5: 40145 | B5: 26.07 | C5: =PERCENTRANK($B$3:$B$241,B5) -> 0.991 | E5: 10748 | F5: 7396433.9 | G5: =PERCENTRANK($F$3:$F$241,F5) -> 0.991 | I5: 30602 | J5: 376425.44 | K5: =PERCENTRANK($J$3:$J$118,J5) -> 0.982 | M5: 11412 | N5: 2431440.9 | O5: =PERCENTRANK($N$3:$N$241,N5) -> 0.991 | Q5: 30418 | R5: 726701.71 | S5: =PERCENTRANK($R$3:$R$241,R5) -> 0.991 | U5: 11803 | V5: 65474.52 | W5: =PERCENTRANK($V$3:$V$184,V5) -> 0.988 | Y5: 10105 | Z5: 462.5 | AA5: =PERCENTRANK($Z$3:$Z$241,Z5) -> 0.987
A6: 11412 | B6: 25.69 | C6: =PERCENTRANK($B$3:$B$241,B6) -> 0.987 | E6: 11906 | F6: 6933824.9 | G6: =PERCENTRANK($F$3:$F$241,F6) -> 0.987 | I6: 11906 | J6: 373292.52 | K6: =PERCENTRANK($J$3:$J$118,J6) -> 0.973 | M6: 10105 | N6: 2119676 | O6: =PERCENTRANK($N$3:$N$241,N6) -> 0.987 | Q6: 40144 | R6: 668748.97 | S6: =PERCENTRANK($R$3:$R$241,R6) -> 0.987 | U6: 10101 | V6: 61525.31 | W6: =PERCENTRANK($V$3:$V$184,V6) -> 0.983 | Y6: 10748 | Z6: 462.5 | AA6: =PERCENTRANK($Z$3:$Z$241,Z6) -> 0.987
A7: 40206 | B7: 25.09 | C7: =PERCENTRANK($B$3:$B$241,B7) -> 0.983 | E7: 20404 | F7: 6398878.2 | G7: =PERCENTRANK($F$3:$F$241,F7) -> 0.983 | I7: 10103 | J7: 303144.44 | K7: =PERCENTRANK($J$3:$J$118,J7) -> 0.965 | M7: 30418 | N7: 1890209.1 | O7: =PERCENTRANK($N$3:$N$241,N7) -> 0.983 | Q7: 30608 | R7: 660580.67 | S7: =PERCENTRANK($R$3:$R$241,R7) -> 0.983 | U7: 10124 | V7: 60843.28 | W7: =PERCENTRANK($V$3:$V$184,V7) -> 0.977 | Y7: 30608 | Z7: 457.5 | AA7: =PERCENTRANK($Z$3:$Z$241,Z7) -> 0.983
A8: 10612 | B8: 21.9 | C8: =PERCENTRANK($B$3:$B$241,B8) -> 0.978 | E8: 11706 | F8: 6125738.3 | G8: =PERCENTRANK($F$3:$F$241,F8) -> 0.978 | I8: 40212 | J8: 296474.04 | K8: =PERCENTRANK($J$3:$J$118,J8) -> 0.956 | M8: 30608 | N8: 1778932.5 | O8: =PERCENTRANK($N$3:$N$241,N8) -> 0.978 | Q8: 10612 | R8: 584663.09 | S8: =PERCENTRANK($R$3:$R$241,R8) -> 0.978 | U8: 10737 | V8: 60234.79 | W8: =PERCENTRANK($V$3:$V$184,V8) -> 0.972 | Y8: 11412 | Z8: 455 | AA8: =PERCENTRANK($Z$3:$Z$241,Z8) -> 0.978
A9: 20216 | B9: 20.08 | C9: =PERCENTRANK($B$3:$B$241,B9) -> 0.974 | E9: 10105 | F9: 6003290.4 | G9: =PERCENTRANK($F$3:$F$241,F9) -> 0.974 | I9: 20520 | J9: 295361.28 | K9: =PERCENTRANK($J$3:$J$118,J9) -> 0.947 | M9: 10611 | N9: 1693369.5 | O9: =PERCENTRANK($N$3:$N$241,N9) -> 0.974 | Q9: 40131 | R9: 569548.58 | S9: =PERCENTRANK($R$3:$R$241,R9) -> 0.974 | U9: 40139 | V9: 59334.92 | W9: =PERCENTRANK($V$3:$V$184,V9) -> 0.966 | Y9: 10611 | Z9: 450 | AA9: =PERCENTRANK($Z$3:$Z$241,Z9) -> 0.97
A10: 10611 | B10: 19.13 | C10: =PERCENTRANK($B$3:$B$241,B10) -> 0.97 | E10: 11211 | F10: 5986867.2 | G10: =PERCENTRANK($F$3:$F$241,F10) -> 0.97 | I10: 20435 | J10: 280655.84 | K10: =PERCENTRANK($J$3:$J$118,J10) -> 0.939 | M10: 40144 | N10: 1618942.9 | O10: =PERCENTRANK($N$3:$N$241,N10) -> 0.97 | Q10: 40206 | R10: 549693.46 | S10: =PERCENTRANK($R$3:$R$241,R10) -> 0.97 | U10: 40109 | V10: 58707.57 | W10: =PERCENTRANK($V$3:$V$184,V10) -> 0.961 | Y10: 10612 | Z10: 450 | AA10: =PERCENTRANK($Z$3:$Z$241,Z10) -> 0.97
A11: 11501 | B11: 16.49 | C11: =PERCENTRANK($B$3:$B$241,B11) -> 0.966 | E11: 11420 | F11: 5861059.8 | G11: =PERCENTRANK($F$3:$F$241,F11) -> 0.966 | I11: 11420 | J11: 279314.44 | K11: =PERCENTRANK($J$3:$J$118,J11) -> 0.93 | M11: 40131 | N11: 1579016.1 | O11: =PERCENTRANK($N$3:$N$241,N11) -> 0.966 | Q11: 20216 | R11: 529071.79 | S11: =PERCENTRANK($R$3:$R$241,R11) -> 0.966 | U11: 40123 | V11: 58551.21 | W11: =PERCENTRANK($V$3:$V$184,V11) -> 0.955 | Y11: 30418 | Z11: 422.5 | AA11: =PERCENTRANK($Z$3:$Z$241,Z11) -> 0.957
A12: 40130 | B12: 15.9 | C12: =PERCENTRANK($B$3:$B$241,B12) -> 0.957 | E12: 10101 | F12: 5695264.1 | G12: =PERCENTRANK($F$3:$F$241,F12) -> 0.962 | I12: 40203 | J12: 278462.32 | K12: =PERCENTRANK($J$3:$J$118,J12) -> 0.921 | M12: 40206 | N12: 1424894.4 | O12: =PERCENTRANK($N$3:$N$241,N12) -> 0.962 | Q12: 40145 | R12: 521121.5 | S12: =PERCENTRANK($R$3:$R$241,R12) -> 0.962 | U12: 30614 | V12: 57919.07 | W12: =PERCENTRANK($V$3:$V$184,V12) -> 0.95 | Y12: 40144 | Z12: 422.5 | AA12: =PERCENTRANK($Z$3:$Z$241,Z12) -> 0.957
A13: 40131 | B13: 15.9 | C13: =PERCENTRANK($B$3:$B$241,B13) -> 0.957 | E13: 11123 | F13: 5417726.9 | G13: =PERCENTRANK($F$3:$F$241,F13) -> 0.957 | I13: 30612 | J13: 278263.8 | K13: =PERCENTRANK($J$3:$J$118,J13) -> 0.913 | M13: 40145 | N13: 1396111 | O13: =PERCENTRANK($N$3:$N$241,N13) -> 0.957 | Q13: 10611 | R13: 495775.66 | S13: =PERCENTRANK($R$3:$R$241,R13) -> 0.957 | U13: 40114 | V13: 57524.93 | W13: =PERCENTRANK($V$3:$V$184,V13) -> 0.944 | Y13: 40206 | Z13: 422.5 | AA13: =PERCENTRANK($Z$3:$Z$241,Z13) -> 0.957
A14: 10120 | B14: 14.65 | C14: =PERCENTRANK($B$3:$B$241,B14) -> 0.953 | E14: 30216 | F14: 5361257.6 | G14: =PERCENTRANK($F$3:$F$241,F14) -> 0.953 | I14: 10737 | J14: 277065.15 | K14: =PERCENTRANK($J$3:$J$118,J14) -> 0.904 | M14: 10120 | N14: 1395393.7 | O14: =PERCENTRANK($N$3:$N$241,N14) -> 0.953 | Q14: 40130 | R14: 494149.6 | S14: =PERCENTRANK($R$3:$R$241,R14) -> 0.953 | U14: 10714 | V14: 57420.61 | W14: =PERCENTRANK($V$3:$V$184,V14) -> 0.939 | Y14: 40130 | Z14: 420 | AA14: =PERCENTRANK($Z$3:$Z$241,Z14) -> 0.949
... A118: 11208 | B118: 7.37 | C118: =PERCENTRANK($B$3:$B$241,B118) -> 0.516 | E118: 40125 | F118: 2779436 | G118: =PERCENTRANK($F$3:$F$241,F118) -> 0.516 | I118: 10101 | J118: 1795.89 | K118: =PERCENTRANK($J$3:$J$118,J118) -> 0 | M118: 11616 | N118: 625385.4 | O118: =PERCENTRANK($N$3:$N$241,N118) -> 0.516 | Q118: 40116 | R118: 60860.32 | S118: =PERCENTRANK($R$3:$R$241,R118) -> 0.516 | U118: 11409 | V118: 135.83 | W118: =PERCENTRANK($V$3:$V$184,V118) -> 0.364 | Y118: 20913 | Z118: 149.5 | AA118: =PERCENTRANK($Z$3:$Z$241,Z118) -> 0.516
A119: 10137 | B119: 7.34 | C119: =PERCENTRANK($B$3:$B$241,B119) -> 0.508 | E119: 10711 | F119: 2766835.9 | G119: =PERCENTRANK($F$3:$F$241,F119) -> 0.512 | M119: 20408 | N119: 624701.18 | O119: =PERCENTRANK($N$3:$N$241,N119) -> 0.512 | Q119: 10507 | R119: 60609.52 | S119: =PERCENTRANK($R$3:$R$241,R119) -> 0.512 | U119: 30602 | V119: 132.5 | W119: =PERCENTRANK($V$3:$V$184,V119) -> 0.359 | Y119: 20513 | Z119: 147.5 | AA119: =PERCENTRANK($Z$3:$Z$241,Z119) -> 0.512
A120: 40204 | B120: 7.34 | C120: =PERCENTRANK($B$3:$B$241,B120) -> 0.508 | E120: 10507 | F120: 2725355.6 | G120: =PERCENTRANK($F$3:$F$241,F120) -> 0.508 | M120: 40114 | N120: 620962.3 | O120: =PERCENTRANK($N$3:$N$241,N120) -> 0.508 | Q120: 40213 | R120: 60262.86 | S120: =PERCENTRANK($R$3:$R$241,R120) -> 0.508 | U120: 30216 | V120: 131.25 | W120: =PERCENTRANK($V$3:$V$184,V120) -> 0.353 | Y120: 11304 | Z120: 147 | AA120: =PERCENTRANK($Z$3:$Z$241,Z120) -> 0.491
A121: 11304 | B121: 7.33 | C121: =PERCENTRANK($B$3:$B$241,B121) -> 0.491 | E121: 11210 | F121: 2709488 | G121: =PERCENTRANK($F$3:$F$241,F121) -> 0.504 | M121: 11601 | N121: 619070.99 | O121: =PERCENTRANK($N$3:$N$241,N121) -> 0.504 | Q121: 40212 | R121: 59994.42 | S121: =PERCENTRANK($R$3:$R$241,R121) -> 0.504 | U121: 30407 | V121: 125.07 | W121: =PERCENTRANK($V$3:$V$184,V121) -> 0.348 | Y121: 11401 | Z121: 147 | AA121: =PERCENTRANK($Z$3:$Z$241,Z121) -> 0.491
A122: 11613 | B122: 7.33 | C122: =PERCENTRANK($B$3:$B$241,B122) -> 0.491 | E122: 11117 | F122: 2698589.3 | G122: =PERCENTRANK($F$3:$F$241,F122) -> 0.5 | M122: 11809 | N122: 618627.31 | O122: =PERCENTRANK($N$3:$N$241,N122) -> 0.5 | Q122: 10133 | R122: 59377.36 | S122: =PERCENTRANK($R$3:$R$241,R122) -> 0.5 | U122: 10137 | V122: 123.83 | W122: =PERCENTRANK($V$3:$V$184,V122) -> 0.342 | Y122: 20205 | Z122: 147 | AA122: =PERCENTRANK($Z$3:$Z$241,Z122) -> 0.491
A123: 11909 | B123: 7.33 | C123: =PERCENTRANK($B$3:$B$241,B123) -> 0.491 | E123: 10744 | F123: 2696635.2 | G123: =PERCENTRANK($F$3:$F$241,F123) -> 0.495 | M123: 11901 | N123: 615457 | O123: =PERCENTRANK($N$3:$N$241,N123) -> 0.495 | Q123: 10736 | R123: 59358.81 | S123: =PERCENTRANK($R$3:$R$241,R123) -> 0.495 | U123: 30612 | V123: 122.92 | W123: =PERCENTRANK($V$3:$V$184,V123) -> 0.337 | Y123: 20215 | Z123: 147 | AA123: =PERCENTRANK($Z$3:$Z$241,Z123) -> 0.491
A124: 30412 | B124: 7.33 | C124: =PERCENTRANK($B$3:$B$241,B124) -> 0.491 | E124: 20903 | F124: 2684685.3 | G124: =PERCENTRANK($F$3:$F$241,F124) -> 0.491 | M124: 20903 | N124: 607140.9 | O124: =PERCENTRANK($N$3:$N$241,N124) -> 0.491 | Q124: 30421 | R124: 59346.21 | S124: =PERCENTRANK($R$3:$R$241,R124) -> 0.491 | U124: 20210 | V124: 119.17 | W124: =PERCENTRANK($V$3:$V$184,V124) -> 0.331 | Y124: 40113 | Z124: 147 | AA124: =PERCENTRANK($Z$3:$Z$241,Z124) -> 0.491
A125: 10605 | B125: 7.29 | C125: =PERCENTRANK($B$3:$B$241,B125) -> 0.487 | E125: 20911 | F125: 2656701.1 | G125: =PERCENTRANK($F$3:$F$241,F125) -> 0.487 | M125: 40208 | N125: 606018.83 | O125: =PERCENTRANK($N$3:$N$241,N125) -> 0.487 | Q125: 20513 | R125: 59325.93 | S125: =PERCENTRANK($R$3:$R$241,R125) -> 0.487 | U125: 10724 | V125: 112.91 | W125: =PERCENTRANK($V$3:$V$184,V125) -> 0.325 | Y125: 20905 | Z125: 145.5 | AA125: =PERCENTRANK($Z$3:$Z$241,Z125) -> 0.487
A126: 11204 | B126: 7.17 | C126: =PERCENTRANK($B$3:$B$241,B126) -> 0.478 | E126: 11109 | F126: 2654291.3 | G126: =PERCENTRANK($F$3:$F$241,F126) -> 0.483 | M126: 11909 | N126: 595237.39 | O126: =PERCENTRANK($N$3:$N$241,N126) -> 0.483 | Q126: 30618 | R126: 59123.46 | S126: =PERCENTRANK($R$3:$R$241,R126) -> 0.483 | U126: 10118 | V126: 106.25 | W126: =PERCENTRANK($V$3:$V$184,V126) -> 0.32 | Y126: 11510 | Z126: 144.5 | AA126: =PERCENTRANK($Z$3:$Z$241,Z126) -> 0.483
A127: 40147 | B127: 7.17 | C127: =PERCENTRANK($B$3:$B$241,B127) -> 0.478 | E127: 30615 | F127: 2652588.4 | G127: =PERCENTRANK($F$3:$F$241,F127) -> 0.478 | M127: 11211 | N127: 591154.3 | O127: =PERCENTRANK($N$3:$N$241,N127) -> 0.478 | Q127: 10518 | R127: 58935.57 | S127: =PERCENTRANK($R$3:$R$241,R127) -> 0.478 | U127: 20433 | V127: 105 | W127: =PERCENTRANK($V$3:$V$184,V127) -> 0.314 | Y127: 11210 | Z127: 142 | AA127: =PERCENTRANK($Z$3:$Z$241,Z127) -> 0.466
A128: 10501 | B128: 7.12 | C128: =PERCENTRANK($B$3:$B$241,B128) -> 0.474 | E128: 40120 | F128: 2640531.7 | G128: =PERCENTRANK($F$3:$F$241,F128) -> 0.474 | M128: 11710 | N128: 590586.08 | O128: =PERCENTRANK($N$3:$N$241,N128) -> 0.474 | Q128: 20408 | R128: 57990.55 | S128: =PERCENTRANK($R$3:$R$241,R128) -> 0.474 | U128: 20909 | V128: 95.41 | W128: =PERCENTRANK($V$3:$V$184,V128) -> 0.309 | Y128: 20908 | Z128: 142 | AA128: =PERCENTRANK($Z$3:$Z$241,Z128) -> 0.466
A129: 10128 | B129: 7.09 | C129: =PERCENTRANK($B$3:$B$241,B129) -> 0.457 | E129: 10714 | F129: 2625498.1 | G129: =PERCENTRANK($F$3:$F$241,F129) -> 0.47 | M129: 11814 | N129: 590372.06 | O129: =PERCENTRANK($N$3:$N$241,N129) -> 0.47 | Q129: 11509 | R129: 57859.35 | S129: =PERCENTRANK($R$3:$R$241,R129) -> 0.47 | U129: 11117 | V129: 92.08 | W129: =PERCENTRANK($V$3:$V$184,V129) -> 0.303 | Y129: 30402 | Z129: 142 | AA129: =PERCENTRANK($Z$3:$Z$241,Z129) -> 0.466
A130: 11509 | B130: 7.09 | C130: =PERCENTRANK($B$3:$B$241,B130) -> 0.457 | E130: 11708 | F130: 2624579.5 | G130: =PERCENTRANK($F$3:$F$241,F130) -> 0.466 | M130: 40213 | N130: 589590.25 | O130: =PERCENTRANK($N$3:$N$241,N130) -> 0.466 | Q130: 30612 | R130: 57858.74 | S130: =PERCENTRANK($R$3:$R$241,R130) -> 0.466 | U130: 30619 | V130: 91.69 | W130: =PERCENTRANK($V$3:$V$184,V130) -> 0.298 | Y130: 30618 | Z130: 142 | AA130: =PERCENTRANK($Z$3:$Z$241,Z130) -> 0.466
... A184: 20431 | B184: 5.63 | C184: =PERCENTRANK($B$3:$B$241,B184) -> 0.239 | E184: 11311 | F184: 2077951.7 | G184: =PERCENTRANK($F$3:$F$241,F184) -> 0.239 | M184: 20526 | N184: 459644.27 | O184: =PERCENTRANK($N$3:$N$241,N184) -> 0.239 | Q184: 20909 | R184: 41164.56 | S184: =PERCENTRANK($R$3:$R$241,R184) -> 0.239 | U184: 10105 | V184: 0.83 | W184: =PERCENTRANK($V$3:$V$184,V184) -> 0 | Y184: 40204 | Z184: 110.5 | AA184: =PERCENTRANK($Z$3:$Z$241,Z184) -> 0.235
A185: 10744 | B185: 5.62 | C185: =PERCENTRANK($B$3:$B$241,B185) -> 0.231 | E185: 11214 | F185: 2076453 | G185: =PERCENTRANK($F$3:$F$241,F185) -> 0.235 | M185: 20908 | N185: 447651.29 | O185: =PERCENTRANK($N$3:$N$241,N185) -> 0.235 | Q185: 10714 | R185: 40906.56 | S185: =PERCENTRANK($R$3:$R$241,R185) -> 0.235 | Y185: 40207 | Z185: 110.5 | AA185: =PERCENTRANK($Z$3:$Z$241,Z185) -> 0.235
A186: 20526 | B186: 5.62 | C186: =PERCENTRANK($B$3:$B$241,B186) -> 0.231 | E186: 20909 | F186: 2075138.2 | G186: =PERCENTRANK($F$3:$F$241,F186) -> 0.231 | M186: 10118 | N186: 446076.93 | O186: =PERCENTRANK($N$3:$N$241,N186) -> 0.231 | Q186: 40202 | R186: 40474.91 | S186: =PERCENTRANK($R$3:$R$241,R186) -> 0.231 | Y186: 10118 | Z186: 109.5 | AA186: =PERCENTRANK($Z$3:$Z$241,Z186) -> 0.218
A187: 11117 | B187: 5.6 | C187: =PERCENTRANK($B$3:$B$241,B187) -> 0.226 | E187: 11606 | F187: 2065301.9 | G187: =PERCENTRANK($F$3:$F$241,F187) -> 0.226 | M187: 40106 | N187: 441644.51 | O187: =PERCENTRANK($N$3:$N$241,N187) -> 0.226 | Q187: 11311 | R187: 40126.87 | S187: =PERCENTRANK($R$3:$R$241,R187) -> 0.226 | Y187: 11116 | Z187: 109.5 | AA187: =PERCENTRANK($Z$3:$Z$241,Z187) -> 0.218
A188: 11708 | B188: 5.53 | C188: =PERCENTRANK($B$3:$B$241,B188) -> 0.222 | E188: 11502 | F188: 2061993.6 | G188: =PERCENTRANK($F$3:$F$241,F188) -> 0.222 | M188: 40115 | N188: 440165.9 | O188: =PERCENTRANK($N$3:$N$241,N188) -> 0.222 | Q188: 11911 | R188: 40083.43 | S188: =PERCENTRANK($R$3:$R$241,R188) -> 0.222 | Y188: 11618 | Z188: 109.5 | AA188: =PERCENTRANK($Z$3:$Z$241,Z188) -> 0.218
A189: 11212 | B189: 5.5 | C189: =PERCENTRANK($B$3:$B$241,B189) -> 0.218 | E189: 11417 | F189: 2052483.3 | G189: =PERCENTRANK($F$3:$F$241,F189) -> 0.218 | M189: 10144 | N189: 437925.83 | O189: =PERCENTRANK($N$3:$N$241,N189) -> 0.218 | Q189: 20421 | R189: 39433.72 | S189: =PERCENTRANK($R$3:$R$241,R189) -> 0.218 | Y189: 11904 | Z189: 109.5 | AA189: =PERCENTRANK($Z$3:$Z$241,Z189) -> 0.218
A190: 40127 | B190: 5.38 | C190: =PERCENTRANK($B$3:$B$241,B190) -> 0.214 | E190: 40116 | F190: 2032888.7 | G190: =PERCENTRANK($F$3:$F$241,F190) -> 0.214 | M190: 40204 | N190: 435825.78 | O190: =PERCENTRANK($N$3:$N$241,N190) -> 0.214 | Q190: 20433 | R190: 38451.56 | S190: =PERCENTRANK($R$3:$R$241,R190) -> 0.214 | Y190: 11406 | Z190: 108 | AA190: =PERCENTRANK($Z$3:$Z$241,Z190) -> 0.205
A191: 11911 | B191: 5.27 | C191: =PERCENTRANK($B$3:$B$241,B191) -> 0.205 | E191: 10137 | F191: 2011947.9 | G191: =PERCENTRANK($F$3:$F$241,F191) -> 0.21 | M191: 40126 | N191: 431632.78 | O191: =PERCENTRANK($N$3:$N$241,N191) -> 0.21 | Q191: 11403 | R191: 38434.5 | S191: =PERCENTRANK($R$3:$R$241,R191) -> 0.21 | Y191: 40106 | Z191: 108 | AA191: =PERCENTRANK($Z$3:$Z$241,Z191) -> 0.205
A192: 20424 | B192: 5.27 | C192: =PERCENTRANK($B$3:$B$241,B192) -> 0.205 | E192: 11616 | F192: 1995794.6 | G192: =PERCENTRANK($F$3:$F$241,F192) -> 0.205 | M192: 10502 | N192: 427230.64 | O192: =PERCENTRANK($N$3:$N$241,N192) -> 0.205 | Q192: 11618 | R192: 38401.3 | S192: =PERCENTRANK($R$3:$R$241,R192) -> 0.205 | Y192: 40127 | Z192: 108 | AA192: =PERCENTRANK($Z$3:$Z$241,Z192) -> 0.205
A193: 11312 | B193: 5.24 | C193: =PERCENTRANK($B$3:$B$241,B193) -> 0.201 | E193: 20526 | F193: 1993781.7 | G193: =PERCENTRANK($F$3:$F$241,F193) -> 0.201 | M193: 40146 | N193: 422698.58 | O193: =PERCENTRANK($N$3:$N$241,N193) -> 0.201 | Q193: 10128 | R193: 38159.43 | S193: =PERCENTRANK($R$3:$R$241,R193) -> 0.201 | Y193: 10140 | Z193: 105.5 | AA193: =PERCENTRANK($Z$3:$Z$241,Z193) -> 0.189
A194: 20513 | B194: 5.23 | C194: =PERCENTRANK($B$3:$B$241,B194) -> 0.197 | E194: 11814 | F194: 1993302.2 | G194: =PERCENTRANK($F$3:$F$241,F194) -> 0.197 | M194: 11117 | N194: 413349.44 | O194: =PERCENTRANK($N$3:$N$241,N194) -> 0.197 | Q194: 30407 | R194: 37917.6 | S194: =PERCENTRANK($R$3:$R$241,R194) -> 0.197 | Y194: 11814 | Z194: 105.5 | AA194: =PERCENTRANK($Z$3:$Z$241,Z194) -> 0.189
A195: 10118 | B195: 5.21 | C195: =PERCENTRANK($B$3:$B$241,B195) -> 0.193 | E195: 40105 | F195: 1985072.4 | G195: =PERCENTRANK($F$3:$F$241,F195) -> 0.193 | M195: 20909 | N195: 410894.02 | O195: =PERCENTRANK($N$3:$N$241,N195) -> 0.193 | Q195: 10137 | R195: 37624.14 | S195: =PERCENTRANK($R$3:$R$241,R195) -> 0.193 | Y195: 20421 | Z195: 105.5 | AA195: =PERCENTRANK($Z$3:$Z$241,Z195) -> 0.189
A196: 20421 | B196: 5.18 | C196: =PERCENTRANK($B$3:$B$241,B196) -> 0.189 | E196: 40208 | F196: 1980024.3 | G196: =PERCENTRANK($F$3:$F$241,F196) -> 0.189 | M196: 11602 | N196: 410323.16 | O196: =PERCENTRANK($N$3:$N$241,N196) -> 0.189 | Q196: 10140 | R196: 37361.78 | S196: =PERCENTRANK($R$3:$R$241,R196) -> 0.189 | Y196: 20511 | Z196: 105.5 | AA196: =PERCENTRANK($Z$3:$Z$241,Z196) -> 0.189
... A241: 10130 | B241: 0 | C241: =PERCENTRANK($B$3:$B$241,B241) -> 0 | E241: 10135 | F241: 0 | G241: =PERCENTRANK($F$3:$F$241,F241) -> 0 | M241: 10130 | N241: 1157 | O241: =PERCENTRANK($N$3:$N$241,N241) -> 0 | Q241: 10130 | R241: 0 | S241: =PERCENTRANK($R$3:$R$241,R241) -> 0 | Y241: 10130 | Z241: 33 | AA241: =PERCENTRANK($Z$3:$Z$241,Z241) -> 0

Sheet kalkulačka
B1: X | F1: =COUNT(B2:B275) -> 19
B2: 4943.49 | C2: NO FC | D2: 1 | F2: 0.1 | G2: 0.2 | H2: 0.4 | I2: 0.3
B3: 4502.59 | C3: NO FC | D3: 2 | F3: =ROUNDUP(F1*10%,0) -> 2 | G3: =ROUNDUP(F1*F2+F1*G2,0) -> 6 | H3: =ROUNDUP(F1*F2+F1*G2+F1*H2,0) -> 14 | M3: 27 | N3: =M3/SUM($M$3:$M$6) -> 0.099630996
B4: 3878.79 | C4: NO FC | D4: 3 | F4: =_xlfn.XLOOKUP(F$3,$D:$D,$B:$B,0,0) -> 4502.59 | G4: =_xlfn.XLOOKUP(G$3,$D:$D,$B:$B,0,0) -> 2379.1 | H4: =_xlfn.XLOOKUP(H$3,$D:$D,$B:$B,0,0) -> 0 | M4: 52 | N4: =M4/SUM($M$3:$M$6) -> 0.19188192
B5: 3138.19 | C5: NO FC | D5: 4 | M5: 110 | N5: =M5/SUM($M$3:$M$6) -> 0.40590406
B6: 2781.83 | C6: NO FC | D6: 5 | M6: 82 | N6: =M6/SUM($M$3:$M$6) -> 0.30258303
B7: 2379.1 | C7: NO FC | D7: 6
B8: 2119.53 | C8: NO FC | D8: 7
B9: 2111.8 | C9: NO FC | D9: 8
B10: 1906.87 | C10: NO FC | D10: 9
B11: 1279.9 | C11: NO FC | D11: 10
B12: 1064.18 | C12: NO FC | D12: 11
B13: 0 | C13: NO FC | D13: 12
B14: 0 | C14: NO FC | D14: 13
B15: 0 | C15: NO FC | D15: 14
B16: 0 | C16: NO FC | D16: 15
B17: 0 | C17: NO FC | D17: 16
B18: 0 | C18: NO FC | D18: 17
... B20: 0 | C20: NO FC | D20: 19
D21: 20
D22: 21
D23: 22
D24: 23
D25: 24
D26: 25
D27: 26
D28: 27
D29: 28
D30: 29
D31: 30
D32: 31
... D275: 274

Sheet Sheet1
A1: Code | B1: SeS name | C1: old fee | D1: new fee | E1: diff | F1: koment | H1: Sum of diff | O1: Increase/Decrease | P1: Ses Name | Q1: Suma
A2: 10748 | B2: Zeleneč I. | C2: 300 | D2: 300 | E2: =D2-C2 -> 0 | F2: =IF(E2>0,"Increase",IF(E2<0,"Decrase",0)) -> 0 | H2: koment | I2: SeS name | J2: Total | O2: Decrase | P2: Bánovce nad Bebravou - Trenčianska II. | Q2: -100
A3: 10612 | B3: Sekule I. | C3: 300 | D3: 300 | E3: =D3-C3 -> 0 | F3: =IF(E3>0,"Increase",IF(E3<0,"Decrase",0)) -> 0 | H3: 0 | I3: Bánovce nad Bebravou | J3: 0 | P3: Bardejov-Prešovská | Q3: -100
A4: 30418 | B4: Štrba | C4: 300 | D4: 300 | E4: =D4-C4 -> 0 | F4: =IF(E4>0,"Increase",IF(E4<0,"Decrase",0)) -> 0 | I4: Banská Bystrica-Jakub | J4: 0 | P4: Bošany | Q4: -50
A5: 11412 | B5: Trenčín-Zamarovce | C5: 300 | D5: 300 | E5: =D5-C5 -> 0 | F5: =IF(E5>0,"Increase",IF(E5<0,"Decrase",0)) -> 0 | I5: Banská Bystrica-Kremnička | J5: 0 | P5: Bratislava - Dolnozemská II. | Q5: -100
A6: 10611 | B6: Sekule II. | C6: 300 | D6: 300 | E6: =D6-C6 -> 0 | F6: =IF(E6>0,"Increase",IF(E6<0,"Decrase",0)) -> 0 | I6: Banská Bystrica-Partizánska | J6: 0 | P6: Bratislava - Dúbravka II. | Q6: -50
A7: 10105 | B7: Bratislava-DČS Zlaté Piesky | C7: 300 | D7: 300 | E7: =D7-C7 -> 0 | F7: =IF(E7>0,"Increase",IF(E7<0,"Decrase",0)) -> 0 | I7: Banská Bystrica-Rudlovská | J7: 0 | P7: Bratislava-Bajkalská II. | Q7: -100
A8: 30608 | B8: Malý Šariš-sever | C8: 300 | D8: 300 | E8: =D8-C8 -> 0 | F8: =IF(E8>0,"Increase",IF(E8<0,"Decrase",0)) -> 0 | I8: Banská Bystrica-Štiavničky | J8: 0 | P8: Bratislava-Botanická | Q8: -100
A9: 10706 | B9: Ilava II. | C9: 300 | D9: 300 | E9: =D9-C9 -> 0 | F9: =IF(E9>0,"Increase",IF(E9<0,"Decrase",0)) -> 0 | I9: Banská Bystrica-Zvolenská | J9: 0 | P9: Bratislava-Petržalka I. | Q9: -100
A10: 10101 | B10: Bratislava-Záhorská Bystrica | C10: 200 | D10: 200 | E10: =D10-C10 -> 0 | F10: =IF(E10>0,"Increase",IF(E10<0,"Decrase",0)) -> 0 | I10: Banská Štiavnica | J10: 0 | P10: Bratislava-ul.Sch.-Trnavského | Q10: -50
A11: 40141 | B11: Žilina-Kysucká | C11: 200 | D11: 300 | E11: =D11-C11 -> 100 | F11: =IF(E11>0,"Increase",IF(E11<0,"Decrase",0)) -> Increase | I11: Beladice | J11: 0 | P11: Bratislava-Vrakunská | Q11: -100
A12: 11701 | B12: Bytča | C12: 300 | D12: 300 | E12: =D12-C12 -> 0 | F12: =IF(E12>0,"Increase",IF(E12<0,"Decrase",0)) -> 0 | I12: Bernolákovo | J12: 0 | P12: Dubnica nad Váhom | Q12: -50
A13: 20216 | B13: Ivachnová | C13: 300 | D13: 300 | E13: =D13-C13 -> 0 | F13: =IF(E13>0,"Increase",IF(E13<0,"Decrase",0)) -> 0 | I13: Blatná na Ostrove | J13: 0 | P13: Dunajská Lužná | Q13: -100
A14: 40131 | B14: Budča-Sever | C14: 300 | D14: 300 | E14: =D14-C14 -> 0 | F14: =IF(E14>0,"Increase",IF(E14<0,"Decrase",0)) -> 0 | I14: Bratislava - Panónska | J14: 0 | P14: Dunajská Streda-Bratislavská I. | Q14: -50
A15: 40130 | B15: Budča-Juh | C15: 300 | D15: 300 | E15: =D15-C15 -> 0 | F15: =IF(E15>0,"Increase",IF(E15<0,"Decrase",0)) -> 0 | I15: Bratislava – Prístavná | J15: 0 | P15: Gabčíkovo | Q15: -50
... A58: 40108 | B58: Bánovce nad Bebravou - Trenčianska II. | C58: 200 | D58: 100 | E58: =D58-C58 -> -100 | F58: =IF(E58>0,"Increase",IF(E58<0,"Decrase",0)) -> Decrase | I58: Košice - Textilná | J58: 0 | P58: Žilina-Vysokoškolákov | Q58: -100
A59: 20913 | B59: Liptovský Hrádok-Pod celinami | C59: 200 | D59: 100 | E59: =D59-C59 -> -100 | F59: =IF(E59>0,"Increase",IF(E59<0,"Decrase",0)) -> Decrase | I59: Košice-Alejová | J59: 0 | O59: Increase | P59: Bardejov-Duklianska | Q59: 100
A60: 11122 | B60: Veľký Meder | C60: 100 | D60: 100 | E60: =D60-C60 -> 0 | F60: =IF(E60>0,"Increase",IF(E60<0,"Decrase",0)) -> 0 | I60: Košice-Barca | J60: 0 | P60: Bratislava-Zlaté Piesky | Q60: 100
A61: 11507 | B61: Senica | C61: 200 | D61: 200 | E61: =D61-C61 -> 0 | F61: =IF(E61>0,"Increase",IF(E61<0,"Decrase",0)) -> 0 | I61: Košice-Festivalové námestie | J61: 0 | P61: DČS Hrádok | Q61: 100
A62: 40120 | B62: Holíč-Bratislavská | C62: 200 | D62: 100 | E62: =D62-C62 -> -100 | F62: =IF(E62>0,"Increase",IF(E62<0,"Decrase",0)) -> Decrase | I62: Košice-Hutnícka | J62: 0 | P62: Košice - Dargovských hrdinov | Q62: 50
A63: 20401 | B63: Banská Bystrica-Partizánska | C63: 200 | D63: 200 | E63: =D63-C63 -> 0 | F63: =IF(E63>0,"Increase",IF(E63<0,"Decrase",0)) -> 0 | I63: Košice-Jantárová | J63: 0 | P63: Ľubotice​ | Q63: 100
A64: 10527 | B64: Nová Baňa | C64: 200 | D64: 100 | E64: =D64-C64 -> -100 | F64: =IF(E64>0,"Increase",IF(E64<0,"Decrase",0)) -> Decrase | I64: Košice-KVP | J64: 0 | P64: Malacky | Q64: 100
A65: 40118 | B65: Dunajská Lužná | C65: 200 | D65: 100 | E65: =D65-C65 -> -100 | F65: =IF(E65>0,"Increase",IF(E65<0,"Decrase",0)) -> Decrase | I65: Košice-Luník | J65: 0 | P65: Malý Šariš-juh | Q65: 100
A66: 40129 | B66: Banská Bystrica-Zvolenská | C66: 200 | D66: 200 | E66: =D66-C66 -> 0 | F66: =IF(E66>0,"Increase",IF(E66<0,"Decrase",0)) -> 0 | I66: Košice-Moldavská | J66: 0 | P66: Pohranice - Sever | Q66: 100
A67: 40102 | B67: Janovík-Západ | C67: 200 | D67: 200 | E67: =D67-C67 -> 0 | F67: =IF(E67>0,"Increase",IF(E67<0,"Decrase",0)) -> 0 | I67: Košice-Poľov | J67: 0 | P67: Prešov-Levočská | Q67: 100
A68: 40138 | B68: Považská Bystrica-Slovenských partizánov | C68: 200 | D68: 200 | E68: =D68-C68 -> 0 | F68: =IF(E68>0,"Increase",IF(E68<0,"Decrase",0)) -> 0 | I68: Košice-Sečovská | J68: 0 | P68: Trebišov-Hlavná | Q68: 100
A69: 20404 | B69: Brezno | C69: 200 | D69: 200 | E69: =D69-C69 -> 0 | F69: =IF(E69>0,"Increase",IF(E69<0,"Decrase",0)) -> 0 | I69: Košice-Šaca | J69: 0 | P69: Trenčianska Turná | Q69: 100
A70: 11211 | B70: Malacky | C70: 100 | D70: 200 | E70: =D70-C70 -> 100 | F70: =IF(E70>0,"Increase",IF(E70<0,"Decrase",0)) -> Increase | I70: Kráľovský Chlmec II. | J70: 0 | P70: Zvolen-Neresnícka | Q70: 100
A71: 40125 | B71: Bratislava-Bratská | C71: 200 | D71: 200 | E71: =D71-C71 -> 0 | F71: =IF(E71>0,"Increase",IF(E71<0,"Decrase",0)) -> 0 | I71: Kremnica | J71: 0 | P71: Žilina-Kysucká | Q71: 100
A72: 30412 | B72: Spišská Nová Ves-Markušovská | C72: 200 | D72: 100 | E72: =D72-C72 -> -100 | F72: =IF(E72>0,"Increase",IF(E72<0,"Decrase",0)) -> Decrase | I72: Krompachy | J72: 0 | O72: Grand Total | Q72: -2850
A73: 40121 | B73: Senec - Senecká | C73: 200 | D73: 200 | E73: =D73-C73 -> 0 | F73: =IF(E73>0,"Increase",IF(E73<0,"Decrase",0)) -> 0 | I73: Krupina | J73: 0
A74: 11811 | B74: Sobrance | C74: 100 | D74: 100 | E74: =D74-C74 -> 0 | F74: =IF(E74>0,"Increase",IF(E74<0,"Decrase",0)) -> 0 | I74: Kúty | J74: 0
A75: 40142 | B75: Košice-Poľov | C75: 200 | D75: 200 | E75: =D75-C75 -> 0 | F75: =IF(E75>0,"Increase",IF(E75<0,"Decrase",0)) -> 0 | I75: Lednické Rovne | J75: 0
A76: 30207 | B76: Michalovce - Sobranecká | C76: 200 | D76: 200 | E76: =D76-C76 -> 0 | F76: =IF(E76>0,"Increase",IF(E76<0,"Decrase",0)) -> 0 | I76: Levice-Družstevnícka | J76: 0
A77: 30205 | B77: Michalovce-Močaranská | C77: 100 | D77: 100 | E77: =D77-C77 -> 0 | F77: =IF(E77>0,"Increase",IF(E77<0,"Decrase",0)) -> 0 | I77: Levice-Ku Bratke | J77: 0
A78: 11509 | B78: Trnava-Bratislavská | C78: 100 | D78: 100 | E78: =D78-C78 -> 0 | F78: =IF(E78>0,"Increase",IF(E78<0,"Decrase",0)) -> 0 | I78: Liptovský Mikuláš-Okoličné | J78: 0
A79: 11901 | B79: Bardejov-Prešovská | C79: 200 | D79: 100 | E79: =D79-C79 -> -100 | F79: =IF(E79>0,"Increase",IF(E79<0,"Decrase",0)) -> Decrase | I79: Lučenec-Opatová | J79: 0
A80: 30127 | B80: Rožňava-Brzotín | C80: 200 | D80: 200 | E80: =D80-C80 -> 0 | F80: =IF(E80>0,"Increase",IF(E80<0,"Decrase",0)) -> 0 | I80: Madunice | J80: 0
A81: 11417 | B81: Sverepec | C81: 200 | D81: 200 | E81: =D81-C81 -> 0 | F81: =IF(E81>0,"Increase",IF(E81<0,"Decrase",0)) -> 0 | I81: Malý Šariš-sever | J81: 0
A82: 30612 | B82: Prešov-Levočská | C82: 100 | D82: 200 | E82: =D82-C82 -> 100 | F82: =IF(E82>0,"Increase",IF(E82<0,"Decrase",0)) -> Increase | I82: Martin-Francúzskych partizánov | J82: 0
A83: 10518 | B83: Zlaté Moravce-Hlavná | C83: 100 | D83: 100 | E83: =D83-C83 -> 0 | F83: =IF(E83>0,"Increase",IF(E83<0,"Decrase",0)) -> 0 | I83: Martin-Kollárova | J83: 0
A84: 30607 | B84: Hanušovce nad Topľou | C84: 100 | D84: 100 | E84: =D84-C84 -> 0 | F84: =IF(E84>0,"Increase",IF(E84<0,"Decrase",0)) -> 0 | I84: Martin-sever | J84: 0
... A164: 20212 | B164: Trstená | C164: 100 | D164: 100 | E164: =D164-C164 -> 0 | F164: =IF(E164>0,"Increase",IF(E164<0,"Decrase",0)) -> 0 | I164: Žilina-Šibenice | J164: 0
A165: 10137 | B165: Blatná na Ostrove | C165: 100 | D165: 100 | E165: =D165-C165 -> 0 | F165: =IF(E165>0,"Increase",IF(E165<0,"Decrase",0)) -> 0 | H165: Decrase | I165: Bánovce nad Bebravou - Trenčianska II. | J165: -100
A166: 30108 | B166: Košice-Moldavská | C166: 100 | D166: 100 | E166: =D166-C166 -> 0 | F166: =IF(E166>0,"Increase",IF(E166<0,"Decrase",0)) -> 0 | I166: Bardejov-Prešovská | J166: -100
A167: 10744 | B167: Šaľa-Galantská | C167: 100 | D167: 50 | E167: =D167-C167 -> -50 | F167: =IF(E167>0,"Increase",IF(E167<0,"Decrase",0)) -> Decrase | I167: Bošany | J167: -50
A168: 11508 | B168: Sereď | C168: 100 | D168: 50 | E168: =D168-C168 -> -50 | F168: =IF(E168>0,"Increase",IF(E168<0,"Decrase",0)) -> Decrase | I168: Bratislava - Dolnozemská II. | J168: -100
A169: 10743 | B169: Šaľa-Veča | C169: 100 | D169: 50 | E169: =D169-C169 -> -50 | F169: =IF(E169>0,"Increase",IF(E169<0,"Decrase",0)) -> Decrase | I169: Bratislava - Dúbravka II. | J169: -50
A170: 30616 | B170: Raslavice | C170: 100 | D170: 50 | E170: =D170-C170 -> -50 | F170: =IF(E170>0,"Increase",IF(E170<0,"Decrase",0)) -> Decrase | I170: Bratislava-Bajkalská II. | J170: -100
A171: 11406 | B171: Myjava | C171: 100 | D171: 50 | E171: =D171-C171 -> -50 | F171: =IF(E171>0,"Increase",IF(E171<0,"Decrase",0)) -> Decrase | I171: Bratislava-Botanická | J171: -100
A172: 11109 | B172: Komárno-Bratislavská | C172: 50 | D172: 50 | E172: =D172-C172 -> 0 | F172: =IF(E172>0,"Increase",IF(E172<0,"Decrase",0)) -> 0 | I172: Bratislava-Petržalka I. | J172: -100
A173: 11502 | B173: Dunajská Streda-Bratislavská I. | C173: 100 | D173: 50 | E173: =D173-C173 -> -50 | F173: =IF(E173>0,"Increase",IF(E173<0,"Decrase",0)) -> Decrase | I173: Bratislava-ul.Sch.-Trnavského | J173: -50
A174: 10140 | B174: Gabčíkovo | C174: 100 | D174: 50 | E174: =D174-C174 -> -50 | F174: =IF(E174>0,"Increase",IF(E174<0,"Decrase",0)) -> Decrase | I174: Bratislava-Vrakunská | J174: -100
A175: 30112 | B175: Košice-Festivalové námestie | C175: 100 | D175: 100 | E175: =D175-C175 -> 0 | F175: =IF(E175>0,"Increase",IF(E175<0,"Decrase",0)) -> 0 | I175: Dubnica nad Váhom | J175: -50
A176: 11902 | B176: Humenné-ul.Osloboditeľov | C176: 100 | D176: 100 | E176: =D176-C176 -> 0 | F176: =IF(E176>0,"Increase",IF(E176<0,"Decrase",0)) -> 0 | I176: Dunajská Lužná | J176: -100
A177: 40202 | B177: Bratislava - Dúbravka II. | C177: 100 | D177: 50 | E177: =D177-C177 -> -50 | F177: =IF(E177>0,"Increase",IF(E177<0,"Decrase",0)) -> Decrase | I177: Dunajská Streda-Bratislavská I. | J177: -50
... A221: 11602 | B221: Banská Bystrica-Štiavničky | C221: 50 | D221: 50 | E221: =D221-C221 -> 0 | F221: =IF(E221>0,"Increase",IF(E221<0,"Decrase",0)) -> 0 | I221: Žilina-Vysokoškolákov | J221: -100
A222: 10109 | B222: Bratislava-Viedenská | C222: 50 | D222: 50 | E222: =D222-C222 -> 0 | F222: =IF(E222>0,"Increase",IF(E222<0,"Decrase",0)) -> 0 | H222: Increase | I222: Bardejov-Duklianska | J222: 100
A223: 10504 | B223: Dudince | C223: 50 | D223: 50 | E223: =D223-C223 -> 0 | F223: =IF(E223>0,"Increase",IF(E223<0,"Decrase",0)) -> 0 | I223: Bratislava-Zlaté Piesky | J223: 100
A224: 11124 | B224: Demandice | C224: 50 | D224: 50 | E224: =D224-C224 -> 0 | F224: =IF(E224>0,"Increase",IF(E224<0,"Decrase",0)) -> 0 | I224: DČS Hrádok | J224: 100
A225: 40132 | B225: Košice-Alejová | C225: 50 | D225: 50 | E225: =D225-C225 -> 0 | F225: =IF(E225>0,"Increase",IF(E225<0,"Decrase",0)) -> 0 | I225: Košice - Dargovských hrdinov | J225: 50
A226: 40107 | B226: Medveďov | C226: 50 | D226: 50 | E226: =D226-C226 -> 0 | F226: =IF(E226>0,"Increase",IF(E226<0,"Decrase",0)) -> 0 | I226: Ľubotice​ | J226: 100
A227: 11912 | B227: Medzilaborce-Dobrianska | C227: 50 | D227: 50 | E227: =D227-C227 -> 0 | F227: =IF(E227>0,"Increase",IF(E227<0,"Decrase",0)) -> 0 | I227: Malacky | J227: 100
A228: 10712 | B228: Trenčianske Teplice | C228: 50 | D228: 50 | E228: =D228-C228 -> 0 | F228: =IF(E228>0,"Increase",IF(E228<0,"Decrase",0)) -> 0 | I228: Malý Šariš-juh | J228: 100
A229: 11404 | B229: Lednické Rovne | C229: 50 | D229: 50 | E229: =D229-C229 -> 0 | F229: =IF(E229>0,"Increase",IF(E229<0,"Decrase",0)) -> 0 | I229: Pohranice - Sever | J229: 100
A230: 10747 | B230: Jaslovské Bohunice | C230: 50 | D230: 50 | E230: =D230-C230 -> 0 | F230: =IF(E230>0,"Increase",IF(E230<0,"Decrase",0)) -> 0 | I230: Prešov-Levočská | J230: 100
A231: 11617 | B231: Zvolen-Lesnícka cesta | C231: 50 | D231: 50 | E231: =D231-C231 -> 0 | F231: =IF(E231>0,"Increase",IF(E231<0,"Decrase",0)) -> 0 | I231: Trebišov-Hlavná | J231: 100
A232: 10133 | B232: Vnútropodniková - lobby | C232: 50 | D232: 50 | E232: =D232-C232 -> 0 | F232: =IF(E232>0,"Increase",IF(E232<0,"Decrase",0)) -> 0 | I232: Trenčianska Turná | J232: 100
A233: 10130 | B233: Slovnaft-vnútropodniková | C233: 50 | D233: 50 | E233: =D233-C233 -> 0 | F233: =IF(E233>0,"Increase",IF(E233<0,"Decrase",0)) -> 0 | I233: Zvolen-Neresnícka | J233: 100
I234: Žilina-Kysucká | J234: 100
H235: Grand Total | J235: -2850

Sheet NEW MODEL SUMMARY
F4: CATEGORIZATION
M5: =COUNTIFS('NEW MODEL BY SES'!X19:X390,"I",'NEW MODEL BY SES'!A19:A390,) -> 0
B6: CATEGORY COMPARISON | C6: No. of SeS by Category CURRENT | F6: No. of SeS by Category NEW MODEL | I6: Difference | K6: Region | L6: Area Manager | M6: Category
B7: COCA | D7: =E7/$E$7 -> #VALUE! | E7: =SUM(E8:E11) -> #VALUE! | G7: =H7/$H$7 -> #DIV/0! | H7: =SUM(H8:H11) -> 0 | M7: I | N7: II | O7: III | P7: IV | Q7: Total
D8: =E8/$E$7 -> #VALUE! | E8: =COUNTIFS('NEW MODEL BY SES'!$D$19:$D$242,$B$7,'NEW MODEL BY SES'!$AA$21:$AA$242,$C8) -> #VALUE! | F8: I | G8: =H8/$H$7 -> #DIV/0! | H8: =COUNTIFS('NEW MODEL BY SES'!$D$19:$D$242,$B$7,'NEW MODEL BY SES'!$X$19:$X$242,$F8) -> 0 | I8: =H8-E8 -> #VALUE! | L8: {=_xlfn.UNIQUE('NEW MODEL BY SES'!A19:A429)} -> Area Manager 1 | M8: =COUNTIFS('NEW MODEL BY SES'!$X$19:$X$429,M$7,'NEW MODEL BY SES'!$A$19:$A$429,$L8) -> 1 | N8: =COUNTIFS('NEW MODEL BY SES'!$X$19:$X$429,N$7,'NEW MODEL BY SES'!$A$19:$A$429,$L8) -> 9 | O8: =COUNTIFS('NEW MODEL BY SES'!$X$19:$X$429,O$7,'NEW MODEL BY SES'!$A$19:$A$429,$L8) -> 9 | P8: =COUNTIFS('NEW MODEL BY SES'!$X$19:$X$429,P$7,'NEW MODEL BY SES'!$A$19:$A$429,$L8) -> 6 | Q8: =SUM(M8:P8) -> 25
C9: III | D9: =E9/$E$7 -> #VALUE! | E9: =COUNTIFS('NEW MODEL BY SES'!$D$19:$D$242,$B$7,'NEW MODEL BY SES'!$AA$21:$AA$242,$C9) -> #VALUE! | F9: II | G9: =H9/$H$7 -> #DIV/0! | H9: =COUNTIFS('NEW MODEL BY SES'!$D$19:$D$242,$B$7,'NEW MODEL BY SES'!$X$19:$X$242,$F9) -> 0 | I9: =H9-E9 -> #VALUE! | L9: Area Manager 2 | M9: =COUNTIFS('NEW MODEL BY SES'!$X$19:$X$429,M$7,'NEW MODEL BY SES'!$A$19:$A$429,$L9) -> 2 | N9: =COUNTIFS('NEW MODEL BY SES'!$X$19:$X$429,N$7,'NEW MODEL BY SES'!$A$19:$A$429,$L9) -> 4 | O9: =COUNTIFS('NEW MODEL BY SES'!$X$19:$X$429,O$7,'NEW MODEL BY SES'!$A$19:$A$429,$L9) -> 13 | P9: =COUNTIFS('NEW MODEL BY SES'!$X$19:$X$429,P$7,'NEW MODEL BY SES'!$A$19:$A$429,$L9) -> 4 | Q9: =SUM(M9:P9) -> 23
C10: II | D10: =E10/$E$7 -> #VALUE! | E10: =COUNTIFS('NEW MODEL BY SES'!$D$19:$D$242,$B$7,'NEW MODEL BY SES'!$AA$21:$AA$242,$C10) -> #VALUE! | F10: III | G10: =H10/$H$7 -> #DIV/0! | H10: =COUNTIFS('NEW MODEL BY SES'!$D$19:$D$242,$B$7,'NEW MODEL BY SES'!$X$19:$X$242,$F10) -> 0 | I10: =H10-E10 -> #VALUE! | L10: Area Manager 3 | M10: =COUNTIFS('NEW MODEL BY SES'!$X$19:$X$429,M$7,'NEW MODEL BY SES'!$A$19:$A$429,$L10) -> 4 | N10: =COUNTIFS('NEW MODEL BY SES'!$X$19:$X$429,N$7,'NEW MODEL BY SES'!$A$19:$A$429,$L10) -> 6 | O10: =COUNTIFS('NEW MODEL BY SES'!$X$19:$X$429,O$7,'NEW MODEL BY SES'!$A$19:$A$429,$L10) -> 6 | P10: =COUNTIFS('NEW MODEL BY SES'!$X$19:$X$429,P$7,'NEW MODEL BY SES'!$A$19:$A$429,$L10) -> 5 | Q10: =SUM(M10:P10) -> 21
C11: I | D11: =E11/$E$7 -> #VALUE! | E11: =COUNTIFS('NEW MODEL BY SES'!$D$19:$D$242,$B$7,'NEW MODEL BY SES'!$AA$21:$AA$242,$C11) -> #VALUE! | F11: IV | G11: =H11/$H$7 -> #DIV/0! | H11: =COUNTIFS('NEW MODEL BY SES'!$D$19:$D$242,$B$7,'NEW MODEL BY SES'!$X$19:$X$242,$F11) -> 0 | I11: =H11-E11 -> #VALUE! | L11: Area Manager 4 | M11: =COUNTIFS('NEW MODEL BY SES'!$X$19:$X$429,M$7,'NEW MODEL BY SES'!$A$19:$A$429,$L11) -> 3 | N11: =COUNTIFS('NEW MODEL BY SES'!$X$19:$X$429,N$7,'NEW MODEL BY SES'!$A$19:$A$429,$L11) -> 5 | O11: =COUNTIFS('NEW MODEL BY SES'!$X$19:$X$429,O$7,'NEW MODEL BY SES'!$A$19:$A$429,$L11) -> 13 | P11: =COUNTIFS('NEW MODEL BY SES'!$X$19:$X$429,P$7,'NEW MODEL BY SES'!$A$19:$A$429,$L11) -> 6 | Q11: =SUM(M11:P11) -> 27
L12: Area Manager 5 | M12: =COUNTIFS('NEW MODEL BY SES'!$X$19:$X$429,M$7,'NEW MODEL BY SES'!$A$19:$A$429,$L12) -> 6 | N12: =COUNTIFS('NEW MODEL BY SES'!$X$19:$X$429,N$7,'NEW MODEL BY SES'!$A$19:$A$429,$L12) -> 7 | O12: =COUNTIFS('NEW MODEL BY SES'!$X$19:$X$429,O$7,'NEW MODEL BY SES'!$A$19:$A$429,$L12) -> 6 | P12: =COUNTIFS('NEW MODEL BY SES'!$X$19:$X$429,P$7,'NEW MODEL BY SES'!$A$19:$A$429,$L12) -> 4 | Q12: =SUM(M12:P12) -> 23
L13: Area Manager 6 | M13: =COUNTIFS('NEW MODEL BY SES'!$X$19:$X$429,M$7,'NEW MODEL BY SES'!$A$19:$A$429,$L13) -> 0 | N13: =COUNTIFS('NEW MODEL BY SES'!$X$19:$X$429,N$7,'NEW MODEL BY SES'!$A$19:$A$429,$L13) -> 6 | O13: =COUNTIFS('NEW MODEL BY SES'!$X$19:$X$429,O$7,'NEW MODEL BY SES'!$A$19:$A$429,$L13) -> 9 | P13: =COUNTIFS('NEW MODEL BY SES'!$X$19:$X$429,P$7,'NEW MODEL BY SES'!$A$19:$A$429,$L13) -> 14 | Q13: =SUM(M13:P13) -> 29
L14: Area Manager 7 | M14: =COUNTIFS('NEW MODEL BY SES'!$X$19:$X$429,M$7,'NEW MODEL BY SES'!$A$19:$A$429,$L14) -> 3 | N14: =COUNTIFS('NEW MODEL BY SES'!$X$19:$X$429,N$7,'NEW MODEL BY SES'!$A$19:$A$429,$L14) -> 3 | O14: =COUNTIFS('NEW MODEL BY SES'!$X$19:$X$429,O$7,'NEW MODEL BY SES'!$A$19:$A$429,$L14) -> 12 | P14: =COUNTIFS('NEW MODEL BY SES'!$X$19:$X$429,P$7,'NEW MODEL BY SES'!$A$19:$A$429,$L14) -> 12 | Q14: =SUM(M14:P14) -> 30
L15: Area Manager 8 | M15: =COUNTIFS('NEW MODEL BY SES'!$X$19:$X$429,M$7,'NEW MODEL BY SES'!$A$19:$A$429,$L15) -> 6 | N15: =COUNTIFS('NEW MODEL BY SES'!$X$19:$X$429,N$7,'NEW MODEL BY SES'!$A$19:$A$429,$L15) -> 6 | O15: =COUNTIFS('NEW MODEL BY SES'!$X$19:$X$429,O$7,'NEW MODEL BY SES'!$A$19:$A$429,$L15) -> 8 | P15: =COUNTIFS('NEW MODEL BY SES'!$X$19:$X$429,P$7,'NEW MODEL BY SES'!$A$19:$A$429,$L15) -> 9 | Q15: =SUM(M15:P15) -> 29
L16: Area Manager 9 | M16: =COUNTIFS('NEW MODEL BY SES'!$X$19:$X$429,M$7,'NEW MODEL BY SES'!$A$19:$A$429,$L16) -> 8 | N16: =COUNTIFS('NEW MODEL BY SES'!$X$19:$X$429,N$7,'NEW MODEL BY SES'!$A$19:$A$429,$L16) -> 8 | O16: =COUNTIFS('NEW MODEL BY SES'!$X$19:$X$429,O$7,'NEW MODEL BY SES'!$A$19:$A$429,$L16) -> 5 | P16: =COUNTIFS('NEW MODEL BY SES'!$X$19:$X$429,P$7,'NEW MODEL BY SES'!$A$19:$A$429,$L16) -> 2 | Q16: =SUM(M16:P16) -> 23
L17: Area Manager 10 | M17: =COUNTIFS('NEW MODEL BY SES'!$X$19:$X$429,M$7,'NEW MODEL BY SES'!$A$19:$A$429,$L17) -> 0 | N17: =COUNTIFS('NEW MODEL BY SES'!$X$19:$X$429,N$7,'NEW MODEL BY SES'!$A$19:$A$429,$L17) -> 5 | O17: =COUNTIFS('NEW MODEL BY SES'!$X$19:$X$429,O$7,'NEW MODEL BY SES'!$A$19:$A$429,$L17) -> 15 | P17: =COUNTIFS('NEW MODEL BY SES'!$X$19:$X$429,P$7,'NEW MODEL BY SES'!$A$19:$A$429,$L17) -> 12 | Q17: =SUM(M17:P17) -> 32
L18: Area Manager 11 | M18: =COUNTIFS('NEW MODEL BY SES'!$X$19:$X$429,M$7,'NEW MODEL BY SES'!$A$19:$A$429,$L18) -> 5 | N18: =COUNTIFS('NEW MODEL BY SES'!$X$19:$X$429,N$7,'NEW MODEL BY SES'!$A$19:$A$429,$L18) -> 4 | O18: =COUNTIFS('NEW MODEL BY SES'!$X$19:$X$429,O$7,'NEW MODEL BY SES'!$A$19:$A$429,$L18) -> 7 | P18: =COUNTIFS('NEW MODEL BY SES'!$X$19:$X$429,P$7,'NEW MODEL BY SES'!$A$19:$A$429,$L18) -> 5 | Q18: =SUM(M18:P18) -> 21
L19: Area Manager 12 | M19: =COUNTIFS('NEW MODEL BY SES'!$X$19:$X$429,M$7,'NEW MODEL BY SES'!$A$19:$A$429,$L19) -> 1 | N19: =COUNTIFS('NEW MODEL BY SES'!$X$19:$X$429,N$7,'NEW MODEL BY SES'!$A$19:$A$429,$L19) -> 4 | O19: =COUNTIFS('NEW MODEL BY SES'!$X$19:$X$429,O$7,'NEW MODEL BY SES'!$A$19:$A$429,$L19) -> 12 | P19: =COUNTIFS('NEW MODEL BY SES'!$X$19:$X$429,P$7,'NEW MODEL BY SES'!$A$19:$A$429,$L19) -> 8 | Q19: =SUM(M19:P19) -> 25
L20: Area Manager 13 | M20: =COUNTIFS('NEW MODEL BY SES'!$X$19:$X$429,M$7,'NEW MODEL BY SES'!$A$19:$A$429,$L20) -> 4 | N20: =COUNTIFS('NEW MODEL BY SES'!$X$19:$X$429,N$7,'NEW MODEL BY SES'!$A$19:$A$429,$L20) -> 5 | O20: =COUNTIFS('NEW MODEL BY SES'!$X$19:$X$429,O$7,'NEW MODEL BY SES'!$A$19:$A$429,$L20) -> 9 | P20: =COUNTIFS('NEW MODEL BY SES'!$X$19:$X$429,P$7,'NEW MODEL BY SES'!$A$19:$A$429,$L20) -> 9 | Q20: =SUM(M20:P20) -> 27
L21: Area Manager 14 | M21: =COUNTIFS('NEW MODEL BY SES'!$X$19:$X$429,M$7,'NEW MODEL BY SES'!$A$19:$A$429,$L21) -> 0 | N21: =COUNTIFS('NEW MODEL BY SES'!$X$19:$X$429,N$7,'NEW MODEL BY SES'!$A$19:$A$429,$L21) -> 6 | O21: =COUNTIFS('NEW MODEL BY SES'!$X$19:$X$429,O$7,'NEW MODEL BY SES'!$A$19:$A$429,$L21) -> 9 | P21: =COUNTIFS('NEW MODEL BY SES'!$X$19:$X$429,P$7,'NEW MODEL BY SES'!$A$19:$A$429,$L21) -> 8 | Q21: =SUM(M21:P21) -> 23
K22: Total | L22: Area Manager 18 | M22: =COUNTIFS('NEW MODEL BY SES'!$X$19:$X$429,M$7,'NEW MODEL BY SES'!$A$19:$A$429,$L22) -> 0 | N22: =COUNTIFS('NEW MODEL BY SES'!$X$19:$X$429,N$7,'NEW MODEL BY SES'!$A$19:$A$429,$L22) -> 3 | O22: =COUNTIFS('NEW MODEL BY SES'!$X$19:$X$429,O$7,'NEW MODEL BY SES'!$A$19:$A$429,$L22) -> 0 | P22: =COUNTIFS('NEW MODEL BY SES'!$X$19:$X$429,P$7,'NEW MODEL BY SES'!$A$19:$A$429,$L22) -> 1 | Q22: =SUM(M22:P22) -> 4
L23: Area Manager 16 | M23: =COUNTIFS('NEW MODEL BY SES'!$X$19:$X$429,M$7,'NEW MODEL BY SES'!$A$19:$A$429,$L23) -> 0 | N23: =COUNTIFS('NEW MODEL BY SES'!$X$19:$X$429,N$7,'NEW MODEL BY SES'!$A$19:$A$429,$L23) -> 8 | O23: =COUNTIFS('NEW MODEL BY SES'!$X$19:$X$429,O$7,'NEW MODEL BY SES'!$A$19:$A$429,$L23) -> 13 | P23: =COUNTIFS('NEW MODEL BY SES'!$X$19:$X$429,P$7,'NEW MODEL BY SES'!$A$19:$A$429,$L23) -> 3 | Q23: =SUM(M23:P23) -> 24
L24: Area Manager 17 | M24: =COUNTIFS('NEW MODEL BY SES'!$X$19:$X$429,M$7,'NEW MODEL BY SES'!$A$19:$A$429,$L24) -> 3 | N24: =COUNTIFS('NEW MODEL BY SES'!$X$19:$X$429,N$7,'NEW MODEL BY SES'!$A$19:$A$429,$L24) -> 6 | O24: =COUNTIFS('NEW MODEL BY SES'!$X$19:$X$429,O$7,'NEW MODEL BY SES'!$A$19:$A$429,$L24) -> 12 | P24: =COUNTIFS('NEW MODEL BY SES'!$X$19:$X$429,P$7,'NEW MODEL BY SES'!$A$19:$A$429,$L24) -> 4 | Q24: =SUM(M24:P24) -> 25
L25: TOTAL | M25: =SUM(M8:M24) -> 46 | N25: =SUM(N8:N24) -> 95 | O25: =SUM(O8:O24) -> 158 | P25: =SUM(P8:P24) -> 112 | Q25: =SUM(M25:P25) -> 411

Sheet SES_by_category
A1: Code | B1: SeS name | C1: TOTAL SCORE | D1: NEW CATEGORY (ARABIC) | E1: ALFA | F1: fee
A2: 10101 | B2: Bratislava - Záhorská Bystrica | C2: =_xlfn.XLOOKUP(A2,'NEW MODEL BY SES'!B:B,'NEW MODEL BY SES'!AC:AC,0,0) -> 0 | D2: =_xlfn.XLOOKUP(A2,'NEW MODEL BY SES'!B:B,'NEW MODEL BY SES'!AD:AD,0,0) -> 0 | F2: =IF(C2="I",300,IF(C2="II",200,IF(C2="III",100,IF(C2="IV",50)))) -> FALSE
A3: 10103 | B3: Bratislava - Zlaté Piesky | C3: =_xlfn.XLOOKUP(A3,'NEW MODEL BY SES'!B:B,'NEW MODEL BY SES'!AC:AC,0,0) -> 0 | D3: =_xlfn.XLOOKUP(A3,'NEW MODEL BY SES'!B:B,'NEW MODEL BY SES'!AD:AD,0,0) -> 0 | F3: =IF(C3="I",300,IF(C3="II",200,IF(C3="III",100,IF(C3="IV",50)))) -> FALSE
A4: 10105 | B4: Bratislava - DČS Zlaté piesky | C4: =_xlfn.XLOOKUP(A4,'NEW MODEL BY SES'!B:B,'NEW MODEL BY SES'!AC:AC,0,0) -> 0 | D4: =_xlfn.XLOOKUP(A4,'NEW MODEL BY SES'!B:B,'NEW MODEL BY SES'!AD:AD,0,0) -> 0 | F4: =IF(C4="I",300,IF(C4="II",200,IF(C4="III",100,IF(C4="IV",50)))) -> FALSE
A5: 10106 | B5: Bratislava - Prístavná | C5: =_xlfn.XLOOKUP(A5,'NEW MODEL BY SES'!B:B,'NEW MODEL BY SES'!AC:AC,0,0) -> 0 | D5: =_xlfn.XLOOKUP(A5,'NEW MODEL BY SES'!B:B,'NEW MODEL BY SES'!AD:AD,0,0) -> 0 | F5: =IF(C5="I",300,IF(C5="II",200,IF(C5="III",100,IF(C5="IV",50)))) -> FALSE
A6: 10108 | B6: Bratislava - Rybničná | C6: =_xlfn.XLOOKUP(A6,'NEW MODEL BY SES'!B:B,'NEW MODEL BY SES'!AC:AC,0,0) -> 0 | D6: =_xlfn.XLOOKUP(A6,'NEW MODEL BY SES'!B:B,'NEW MODEL BY SES'!AD:AD,0,0) -> 0 | F6: =IF(C6="I",300,IF(C6="II",200,IF(C6="III",100,IF(C6="IV",50)))) -> FALSE
A7: 10109 | B7: Bratislava - Viedenská cesta | C7: =_xlfn.XLOOKUP(A7,'NEW MODEL BY SES'!B:B,'NEW MODEL BY SES'!AC:AC,0,0) -> 0 | D7: =_xlfn.XLOOKUP(A7,'NEW MODEL BY SES'!B:B,'NEW MODEL BY SES'!AD:AD,0,0) -> 0 | F7: =IF(C7="I",300,IF(C7="II",200,IF(C7="III",100,IF(C7="IV",50)))) -> FALSE
A8: 10118 | B8: Bernolákovo | C8: =_xlfn.XLOOKUP(A8,'NEW MODEL BY SES'!B:B,'NEW MODEL BY SES'!AC:AC,0,0) -> 0 | D8: =_xlfn.XLOOKUP(A8,'NEW MODEL BY SES'!B:B,'NEW MODEL BY SES'!AD:AD,0,0) -> 0 | F8: =IF(C8="I",300,IF(C8="II",200,IF(C8="III",100,IF(C8="IV",50)))) -> FALSE
A9: 10120 | B9: Pezinok - Šenkvická | C9: =_xlfn.XLOOKUP(A9,'NEW MODEL BY SES'!B:B,'NEW MODEL BY SES'!AC:AC,0,0) -> 0 | D9: =_xlfn.XLOOKUP(A9,'NEW MODEL BY SES'!B:B,'NEW MODEL BY SES'!AD:AD,0,0) -> 0 | F9: =IF(C9="I",300,IF(C9="II",200,IF(C9="III",100,IF(C9="IV",50)))) -> FALSE
A10: 10124 | B10: Bratislava - Dvory IV. | C10: =_xlfn.XLOOKUP(A10,'NEW MODEL BY SES'!B:B,'NEW MODEL BY SES'!AC:AC,0,0) -> 0 | D10: =_xlfn.XLOOKUP(A10,'NEW MODEL BY SES'!B:B,'NEW MODEL BY SES'!AD:AD,0,0) -> 0 | F10: =IF(C10="I",300,IF(C10="II",200,IF(C10="III",100,IF(C10="IV",50)))) -> FALSE
A11: 10128 | B11: Senec - Bratislavská | C11: =_xlfn.XLOOKUP(A11,'NEW MODEL BY SES'!B:B,'NEW MODEL BY SES'!AC:AC,0,0) -> 0 | D11: =_xlfn.XLOOKUP(A11,'NEW MODEL BY SES'!B:B,'NEW MODEL BY SES'!AD:AD,0,0) -> 0 | F11: =IF(C11="I",300,IF(C11="II",200,IF(C11="III",100,IF(C11="IV",50)))) -> FALSE
A12: 10130 | B12: Bratislava - Vnútropodniková ČS | C12: =_xlfn.XLOOKUP(A12,'NEW MODEL BY SES'!B:B,'NEW MODEL BY SES'!AC:AC,0,0) -> 0 | D12: =_xlfn.XLOOKUP(A12,'NEW MODEL BY SES'!B:B,'NEW MODEL BY SES'!AD:AD,0,0) -> 0 | F12: =IF(C12="I",300,IF(C12="II",200,IF(C12="III",100,IF(C12="IV",50)))) -> FALSE
A13: 10133 | B13: Bratislava - Vnútropodniková - Lobby | C13: =_xlfn.XLOOKUP(A13,'NEW MODEL BY SES'!B:B,'NEW MODEL BY SES'!AC:AC,0,0) -> 0 | D13: =_xlfn.XLOOKUP(A13,'NEW MODEL BY SES'!B:B,'NEW MODEL BY SES'!AD:AD,0,0) -> 0 | F13: =IF(C13="I",300,IF(C13="II",200,IF(C13="III",100,IF(C13="IV",50)))) -> FALSE
... A240: 40213 | B240: Prievidza – Nadjazdová? | C240: =_xlfn.XLOOKUP(A240,'NEW MODEL BY SES'!B:B,'NEW MODEL BY SES'!AC:AC,0,0) -> 0 | D240: =_xlfn.XLOOKUP(A240,'NEW MODEL BY SES'!B:B,'NEW MODEL BY SES'!AD:AD,0,0) -> 0 | F240: =IF(C240="I",300,IF(C240="II",200,IF(C240="III",100,IF(C240="IV",50)))) -> FALSE

Sheet SeS in Retail Sales Areas
F1: ='NEW MODEL BY SES'!#REF! -> #REF! | G1: ='NEW MODEL BY SES'!#REF! -> #REF!
B2: Refresh if data were changed in sheet "NEW MODEL SUMMARY" | F2: ='NEW MODEL BY SES'!#REF! -> #REF! | G2: ='NEW MODEL BY SES'!#REF! -> #REF! | H2: ='NEW MODEL BY SES'!#REF! -> #REF!
F3: ='NEW MODEL BY SES'!#REF! -> #REF! | G3: ='NEW MODEL BY SES'!#REF! -> #REF! | H3: ='NEW MODEL BY SES'!#REF! -> #REF!
F4: ='NEW MODEL BY SES'!#REF! -> #REF! | G4: ='NEW MODEL BY SES'!#REF! -> #REF! | H4: ='NEW MODEL BY SES'!#REF! -> #REF!
A5: Region | B5: (mind) | F5: ='NEW MODEL BY SES'!#REF! -> #REF! | G5: ='NEW MODEL BY SES'!#REF! -> #REF! | H5: ='NEW MODEL BY SES'!#REF! -> #REF!
A7: Retail Sales Area | B7: TOTAL SCORE | C7: SeS name | D7: NEW CATEGORY (ROMAN) | F7: No. of Employees | G7: No. of Emp. POINTS | H7: FUEL (lit) | I7: FUEL POINTS | J7: LPG (lit) | K7: LPG POINTS | L7: NON-FUEL SHOP revenue (HRK) | M7: NF SHOP POINTS | N7: LUBRICANTS (revenue HRK) | O7: LUBES POINTS | P7: LPG BOTTLED revenue (HRK) | Q7: LPG BOT. POINTS | R7: GASTRO revenue (HRK) | S7: AB/FC/CC | T7: GASTRO POINTS | U7: CAR WASH revenue (HRK) | V7: CAR WASH POINTS | W7: EXCHANGE OFFFICE | X7: EXCH. OFF. POINTS | Z7: TRANSACTIONS (actual 2019)
A8: HU-12 | B8: 200 | C8: Gyõr, Tatai út | D8: I | F8: í | G8: =IFERROR(VLOOKUP($C8,'NEW MODEL BY SES'!$C$19:$R$242,MATCH('SeS in Retail Sales Areas'!G$7,'NEW MODEL BY SES'!$C$17:$R$17,0),0),"") | H8: =IFERROR(VLOOKUP($C8,'NEW MODEL BY SES'!$C$19:$R$242,MATCH('SeS in Retail Sales Areas'!H$7,'NEW MODEL BY SES'!$C$17:$R$17,0),0),"") | I8: =IFERROR(VLOOKUP($C8,'NEW MODEL BY SES'!$C$19:$R$242,MATCH('SeS in Retail Sales Areas'!I$7,'NEW MODEL BY SES'!$C$17:$R$17,0),0),"") | J8: =IFERROR(VLOOKUP($C8,'NEW MODEL BY SES'!$C$19:$R$242,MATCH('SeS in Retail Sales Areas'!J$7,'NEW MODEL BY SES'!$C$17:$R$17,0),0),"") | K8: =IFERROR(VLOOKUP($C8,'NEW MODEL BY SES'!$C$19:$R$242,MATCH('SeS in Retail Sales Areas'!K$7,'NEW MODEL BY SES'!$C$17:$R$17,0),0),"") | L8: =IFERROR(VLOOKUP($C8,'NEW MODEL BY SES'!$C$19:$R$242,MATCH('SeS in Retail Sales Areas'!L$7,'NEW MODEL BY SES'!$C$17:$R$17,0),0),"") | M8: =IFERROR(VLOOKUP($C8,'NEW MODEL BY SES'!$C$19:$R$242,MATCH('SeS in Retail Sales Areas'!M$7,'NEW MODEL BY SES'!$C$17:$R$17,0),0),"") | N8: =IFERROR(VLOOKUP($C8,'NEW MODEL BY SES'!$C$19:$R$242,MATCH('SeS in Retail Sales Areas'!N$7,'NEW MODEL BY SES'!$C$17:$R$17,0),0),"") | ... X8: =IFERROR(VLOOKUP($C8,'NEW MODEL BY SES'!$C$19:$R$242,MATCH('SeS in Retail Sales Areas'!X$7,'NEW MODEL BY SES'!$C$17:$R$17,0),0),"")
A9: HU-12 | B9: 190 | C9: Gyõr, Nagymegyeri út (Galántai út) | D9: I | F9: =IFERROR(VLOOKUP($C9,'NEW MODEL BY SES'!$C$19:$R$242,MATCH('SeS in Retail Sales Areas'!F$7,'NEW MODEL BY SES'!$C$17:$R$17,0),0),"") | G9: =IFERROR(VLOOKUP($C9,'NEW MODEL BY SES'!$C$19:$R$242,MATCH('SeS in Retail Sales Areas'!G$7,'NEW MODEL BY SES'!$C$17:$R$17,0),0),"") | H9: =IFERROR(VLOOKUP($C9,'NEW MODEL BY SES'!$C$19:$R$242,MATCH('SeS in Retail Sales Areas'!H$7,'NEW MODEL BY SES'!$C$17:$R$17,0),0),"") | I9: =IFERROR(VLOOKUP($C9,'NEW MODEL BY SES'!$C$19:$R$242,MATCH('SeS in Retail Sales Areas'!I$7,'NEW MODEL BY SES'!$C$17:$R$17,0),0),"") | J9: =IFERROR(VLOOKUP($C9,'NEW MODEL BY SES'!$C$19:$R$242,MATCH('SeS in Retail Sales Areas'!J$7,'NEW MODEL BY SES'!$C$17:$R$17,0),0),"") | K9: =IFERROR(VLOOKUP($C9,'NEW MODEL BY SES'!$C$19:$R$242,MATCH('SeS in Retail Sales Areas'!K$7,'NEW MODEL BY SES'!$C$17:$R$17,0),0),"") | L9: =IFERROR(VLOOKUP($C9,'NEW MODEL BY SES'!$C$19:$R$242,MATCH('SeS in Retail Sales Areas'!L$7,'NEW MODEL BY SES'!$C$17:$R$17,0),0),"") | M9: =IFERROR(VLOOKUP($C9,'NEW MODEL BY SES'!$C$19:$R$242,MATCH('SeS in Retail Sales Areas'!M$7,'NEW MODEL BY SES'!$C$17:$R$17,0),0),"") | ... X9: =IFERROR(VLOOKUP($C9,'NEW MODEL BY SES'!$C$19:$R$242,MATCH('SeS in Retail Sales Areas'!X$7,'NEW MODEL BY SES'!$C$17:$R$17,0),0),"")
A10: HU-12 | B10: 155 | C10: Mosonmagyaróvár, M1 II. (bal) | D10: II | F10: =IFERROR(VLOOKUP($C10,'NEW MODEL BY SES'!$C$19:$R$242,MATCH('SeS in Retail Sales Areas'!F$7,'NEW MODEL BY SES'!$C$17:$R$17,0),0),"") | G10: =IFERROR(VLOOKUP($C10,'NEW MODEL BY SES'!$C$19:$R$242,MATCH('SeS in Retail Sales Areas'!G$7,'NEW MODEL BY SES'!$C$17:$R$17,0),0),"") | H10: =IFERROR(VLOOKUP($C10,'NEW MODEL BY SES'!$C$19:$R$242,MATCH('SeS in Retail Sales Areas'!H$7,'NEW MODEL BY SES'!$C$17:$R$17,0),0),"") | I10: =IFERROR(VLOOKUP($C10,'NEW MODEL BY SES'!$C$19:$R$242,MATCH('SeS in Retail Sales Areas'!I$7,'NEW MODEL BY SES'!$C$17:$R$17,0),0),"") | J10: =IFERROR(VLOOKUP($C10,'NEW MODEL BY SES'!$C$19:$R$242,MATCH('SeS in Retail Sales Areas'!J$7,'NEW MODEL BY SES'!$C$17:$R$17,0),0),"") | K10: =IFERROR(VLOOKUP($C10,'NEW MODEL BY SES'!$C$19:$R$242,MATCH('SeS in Retail Sales Areas'!K$7,'NEW MODEL BY SES'!$C$17:$R$17,0),0),"") | L10: =IFERROR(VLOOKUP($C10,'NEW MODEL BY SES'!$C$19:$R$242,MATCH('SeS in Retail Sales Areas'!L$7,'NEW MODEL BY SES'!$C$17:$R$17,0),0),"") | M10: =IFERROR(VLOOKUP($C10,'NEW MODEL BY SES'!$C$19:$R$242,MATCH('SeS in Retail Sales Areas'!M$7,'NEW MODEL BY SES'!$C$17:$R$17,0),0),"") | ... X10: =IFERROR(VLOOKUP($C10,'NEW MODEL BY SES'!$C$19:$R$242,MATCH('SeS in Retail Sales Areas'!X$7,'NEW MODEL BY SES'!$C$17:$R$17,0),0),"")
A11: HU-12 | B11: 154 | C11: Mosonmagyaróvár, M1 I. (jobb) | D11: II | F11: =IFERROR(VLOOKUP($C11,'NEW MODEL BY SES'!$C$19:$R$242,MATCH('SeS in Retail Sales Areas'!F$7,'NEW MODEL BY SES'!$C$17:$R$17,0),0),"") | G11: =IFERROR(VLOOKUP($C11,'NEW MODEL BY SES'!$C$19:$R$242,MATCH('SeS in Retail Sales Areas'!G$7,'NEW MODEL BY SES'!$C$17:$R$17,0),0),"") | H11: =IFERROR(VLOOKUP($C11,'NEW MODEL BY SES'!$C$19:$R$242,MATCH('SeS in Retail Sales Areas'!H$7,'NEW MODEL BY SES'!$C$17:$R$17,0),0),"") | I11: =IFERROR(VLOOKUP($C11,'NEW MODEL BY SES'!$C$19:$R$242,MATCH('SeS in Retail Sales Areas'!I$7,'NEW MODEL BY SES'!$C$17:$R$17,0),0),"") | J11: =IFERROR(VLOOKUP($C11,'NEW MODEL BY SES'!$C$19:$R$242,MATCH('SeS in Retail Sales Areas'!J$7,'NEW MODEL BY SES'!$C$17:$R$17,0),0),"") | K11: =IFERROR(VLOOKUP($C11,'NEW MODEL BY SES'!$C$19:$R$242,MATCH('SeS in Retail Sales Areas'!K$7,'NEW MODEL BY SES'!$C$17:$R$17,0),0),"") | L11: =IFERROR(VLOOKUP($C11,'NEW MODEL BY SES'!$C$19:$R$242,MATCH('SeS in Retail Sales Areas'!L$7,'NEW MODEL BY SES'!$C$17:$R$17,0),0),"") | M11: =IFERROR(VLOOKUP($C11,'NEW MODEL BY SES'!$C$19:$R$242,MATCH('SeS in Retail Sales Areas'!M$7,'NEW MODEL BY SES'!$C$17:$R$17,0),0),"") | ... X11: =IFERROR(VLOOKUP($C11,'NEW MODEL BY SES'!$C$19:$R$242,MATCH('SeS in Retail Sales Areas'!X$7,'NEW MODEL BY SES'!$C$17:$R$17,0),0),"")
A12: HU-12 | B12: 153 | C12: M1 autópálya, 22 km II. (bal) | D12: II | F12: =IFERROR(VLOOKUP($C12,'NEW MODEL BY SES'!$C$19:$R$242,MATCH('SeS in Retail Sales Areas'!F$7,'NEW MODEL BY SES'!$C$17:$R$17,0),0),"") | G12: =IFERROR(VLOOKUP($C12,'NEW MODEL BY SES'!$C$19:$R$242,MATCH('SeS in Retail Sales Areas'!G$7,'NEW MODEL BY SES'!$C$17:$R$17,0),0),"") | H12: =IFERROR(VLOOKUP($C12,'NEW MODEL BY SES'!$C$19:$R$242,MATCH('SeS in Retail Sales Areas'!H$7,'NEW MODEL BY SES'!$C$17:$R$17,0),0),"") | I12: =IFERROR(VLOOKUP($C12,'NEW MODEL BY SES'!$C$19:$R$242,MATCH('SeS in Retail Sales Areas'!I$7,'NEW MODEL BY SES'!$C$17:$R$17,0),0),"") | J12: =IFERROR(VLOOKUP($C12,'NEW MODEL BY SES'!$C$19:$R$242,MATCH('SeS in Retail Sales Areas'!J$7,'NEW MODEL BY SES'!$C$17:$R$17,0),0),"") | K12: =IFERROR(VLOOKUP($C12,'NEW MODEL BY SES'!$C$19:$R$242,MATCH('SeS in Retail Sales Areas'!K$7,'NEW MODEL BY SES'!$C$17:$R$17,0),0),"") | L12: =IFERROR(VLOOKUP($C12,'NEW MODEL BY SES'!$C$19:$R$242,MATCH('SeS in Retail Sales Areas'!L$7,'NEW MODEL BY SES'!$C$17:$R$17,0),0),"") | M12: =IFERROR(VLOOKUP($C12,'NEW MODEL BY SES'!$C$19:$R$242,MATCH('SeS in Retail Sales Areas'!M$7,'NEW MODEL BY SES'!$C$17:$R$17,0),0),"") | ... X12: =IFERROR(VLOOKUP($C12,'NEW MODEL BY SES'!$C$19:$R$242,MATCH('SeS in Retail Sales Areas'!X$7,'NEW MODEL BY SES'!$C$17:$R$17,0),0),"")
A13: HU-12 | B13: 138 | C13: Győr, Szent Imre u. 55. | D13: II | F13: =IFERROR(VLOOKUP($C13,'NEW MODEL BY SES'!$C$19:$R$242,MATCH('SeS in Retail Sales Areas'!F$7,'NEW MODEL BY SES'!$C$17:$R$17,0),0),"") | G13: =IFERROR(VLOOKUP($C13,'NEW MODEL BY SES'!$C$19:$R$242,MATCH('SeS in Retail Sales Areas'!G$7,'NEW MODEL BY SES'!$C$17:$R$17,0),0),"") | H13: =IFERROR(VLOOKUP($C13,'NEW MODEL BY SES'!$C$19:$R$242,MATCH('SeS in Retail Sales Areas'!H$7,'NEW MODEL BY SES'!$C$17:$R$17,0),0),"") | I13: =IFERROR(VLOOKUP($C13,'NEW MODEL BY SES'!$C$19:$R$242,MATCH('SeS in Retail Sales Areas'!I$7,'NEW MODEL BY SES'!$C$17:$R$17,0),0),"") | J13: =IFERROR(VLOOKUP($C13,'NEW MODEL BY SES'!$C$19:$R$242,MATCH('SeS in Retail Sales Areas'!J$7,'NEW MODEL BY SES'!$C$17:$R$17,0),0),"") | K13: =IFERROR(VLOOKUP($C13,'NEW MODEL BY SES'!$C$19:$R$242,MATCH('SeS in Retail Sales Areas'!K$7,'NEW MODEL BY SES'!$C$17:$R$17,0),0),"") | L13: =IFERROR(VLOOKUP($C13,'NEW MODEL BY SES'!$C$19:$R$242,MATCH('SeS in Retail Sales Areas'!L$7,'NEW MODEL BY SES'!$C$17:$R$17,0),0),"") | M13: =IFERROR(VLOOKUP($C13,'NEW MODEL BY SES'!$C$19:$R$242,MATCH('SeS in Retail Sales Areas'!M$7,'NEW MODEL BY SES'!$C$17:$R$17,0),0),"") | ... X13: =IFERROR(VLOOKUP($C13,'NEW MODEL BY SES'!$C$19:$R$242,MATCH('SeS in Retail Sales Areas'!X$7,'NEW MODEL BY SES'!$C$17:$R$17,0),0),"")
A14: HU-12 | B14: 137 | C14: Szombathely, Viktória út 1. | D14: II | F14: =IFERROR(VLOOKUP($C14,'NEW MODEL BY SES'!$C$19:$R$242,MATCH('SeS in Retail Sales Areas'!F$7,'NEW MODEL BY SES'!$C$17:$R$17,0),0),"") | G14: =IFERROR(VLOOKUP($C14,'NEW MODEL BY SES'!$C$19:$R$242,MATCH('SeS in Retail Sales Areas'!G$7,'NEW MODEL BY SES'!$C$17:$R$17,0),0),"") | H14: =IFERROR(VLOOKUP($C14,'NEW MODEL BY SES'!$C$19:$R$242,MATCH('SeS in Retail Sales Areas'!H$7,'NEW MODEL BY SES'!$C$17:$R$17,0),0),"") | I14: =IFERROR(VLOOKUP($C14,'NEW MODEL BY SES'!$C$19:$R$242,MATCH('SeS in Retail Sales Areas'!I$7,'NEW MODEL BY SES'!$C$17:$R$17,0),0),"") | J14: =IFERROR(VLOOKUP($C14,'NEW MODEL BY SES'!$C$19:$R$242,MATCH('SeS in Retail Sales Areas'!J$7,'NEW MODEL BY SES'!$C$17:$R$17,0),0),"") | K14: =IFERROR(VLOOKUP($C14,'NEW MODEL BY SES'!$C$19:$R$242,MATCH('SeS in Retail Sales Areas'!K$7,'NEW MODEL BY SES'!$C$17:$R$17,0),0),"") | L14: =IFERROR(VLOOKUP($C14,'NEW MODEL BY SES'!$C$19:$R$242,MATCH('SeS in Retail Sales Areas'!L$7,'NEW MODEL BY SES'!$C$17:$R$17,0),0),"") | M14: =IFERROR(VLOOKUP($C14,'NEW MODEL BY SES'!$C$19:$R$242,MATCH('SeS in Retail Sales Areas'!M$7,'NEW MODEL BY SES'!$C$17:$R$17,0),0),"") | ... X14: =IFERROR(VLOOKUP($C14,'NEW MODEL BY SES'!$C$19:$R$242,MATCH('SeS in Retail Sales Areas'!X$7,'NEW MODEL BY SES'!$C$17:$R$17,0),0),"")
A15: HU-12 | B15: 133 | C15: Komárom, Mártírok út | D15: II | F15: =IFERROR(VLOOKUP($C15,'NEW MODEL BY SES'!$C$19:$R$242,MATCH('SeS in Retail Sales Areas'!F$7,'NEW MODEL BY SES'!$C$17:$R$17,0),0),"") | G15: =IFERROR(VLOOKUP($C15,'NEW MODEL BY SES'!$C$19:$R$242,MATCH('SeS in Retail Sales Areas'!G$7,'NEW MODEL BY SES'!$C$17:$R$17,0),0),"") | H15: =IFERROR(VLOOKUP($C15,'NEW MODEL BY SES'!$C$19:$R$242,MATCH('SeS in Retail Sales Areas'!H$7,'NEW MODEL BY SES'!$C$17:$R$17,0),0),"") | I15: =IFERROR(VLOOKUP($C15,'NEW MODEL BY SES'!$C$19:$R$242,MATCH('SeS in Retail Sales Areas'!I$7,'NEW MODEL BY SES'!$C$17:$R$17,0),0),"") | J15: =IFERROR(VLOOKUP($C15,'NEW MODEL BY SES'!$C$19:$R$242,MATCH('SeS in Retail Sales Areas'!J$7,'NEW MODEL BY SES'!$C$17:$R$17,0),0),"") | K15: =IFERROR(VLOOKUP($C15,'NEW MODEL BY SES'!$C$19:$R$242,MATCH('SeS in Retail Sales Areas'!K$7,'NEW MODEL BY SES'!$C$17:$R$17,0),0),"") | L15: =IFERROR(VLOOKUP($C15,'NEW MODEL BY SES'!$C$19:$R$242,MATCH('SeS in Retail Sales Areas'!L$7,'NEW MODEL BY SES'!$C$17:$R$17,0),0),"") | M15: =IFERROR(VLOOKUP($C15,'NEW MODEL BY SES'!$C$19:$R$242,MATCH('SeS in Retail Sales Areas'!M$7,'NEW MODEL BY SES'!$C$17:$R$17,0),0),"") | ... X15: =IFERROR(VLOOKUP($C15,'NEW MODEL BY SES'!$C$19:$R$242,MATCH('SeS in Retail Sales Areas'!X$7,'NEW MODEL BY SES'!$C$17:$R$17,0),0),"")
A16: HU-12 | B16: 128 | C16: Gyõr, Budai út | D16: II | F16: =IFERROR(VLOOKUP($C16,'NEW MODEL BY SES'!$C$19:$R$242,MATCH('SeS in Retail Sales Areas'!F$7,'NEW MODEL BY SES'!$C$17:$R$17,0),0),"") | G16: =IFERROR(VLOOKUP($C16,'NEW MODEL BY SES'!$C$19:$R$242,MATCH('SeS in Retail Sales Areas'!G$7,'NEW MODEL BY SES'!$C$17:$R$17,0),0),"") | H16: =IFERROR(VLOOKUP($C16,'NEW MODEL BY SES'!$C$19:$R$242,MATCH('SeS in Retail Sales Areas'!H$7,'NEW MODEL BY SES'!$C$17:$R$17,0),0),"") | I16: =IFERROR(VLOOKUP($C16,'NEW MODEL BY SES'!$C$19:$R$242,MATCH('SeS in Retail Sales Areas'!I$7,'NEW MODEL BY SES'!$C$17:$R$17,0),0),"") | J16: =IFERROR(VLOOKUP($C16,'NEW MODEL BY SES'!$C$19:$R$242,MATCH('SeS in Retail Sales Areas'!J$7,'NEW MODEL BY SES'!$C$17:$R$17,0),0),"") | K16: =IFERROR(VLOOKUP($C16,'NEW MODEL BY SES'!$C$19:$R$242,MATCH('SeS in Retail Sales Areas'!K$7,'NEW MODEL BY SES'!$C$17:$R$17,0),0),"") | L16: =IFERROR(VLOOKUP($C16,'NEW MODEL BY SES'!$C$19:$R$242,MATCH('SeS in Retail Sales Areas'!L$7,'NEW MODEL BY SES'!$C$17:$R$17,0),0),"") | M16: =IFERROR(VLOOKUP($C16,'NEW MODEL BY SES'!$C$19:$R$242,MATCH('SeS in Retail Sales Areas'!M$7,'NEW MODEL BY SES'!$C$17:$R$17,0),0),"") | ... X16: =IFERROR(VLOOKUP($C16,'NEW MODEL BY SES'!$C$19:$R$242,MATCH('SeS in Retail Sales Areas'!X$7,'NEW MODEL BY SES'!$C$17:$R$17,0),0),"")
A17: HU-12 | B17: 123 | C17: Tatabánya, Gyõri út | D17: III | F17: =IFERROR(VLOOKUP($C17,'NEW MODEL BY SES'!$C$19:$R$242,MATCH('SeS in Retail Sales Areas'!F$7,'NEW MODEL BY SES'!$C$17:$R$17,0),0),"") | G17: =IFERROR(VLOOKUP($C17,'NEW MODEL BY SES'!$C$19:$R$242,MATCH('SeS in Retail Sales Areas'!G$7,'NEW MODEL BY SES'!$C$17:$R$17,0),0),"") | H17: =IFERROR(VLOOKUP($C17,'NEW MODEL BY SES'!$C$19:$R$242,MATCH('SeS in Retail Sales Areas'!H$7,'NEW MODEL BY SES'!$C$17:$R$17,0),0),"") | I17: =IFERROR(VLOOKUP($C17,'NEW MODEL BY SES'!$C$19:$R$242,MATCH('SeS in Retail Sales Areas'!I$7,'NEW MODEL BY SES'!$C$17:$R$17,0),0),"") | J17: =IFERROR(VLOOKUP($C17,'NEW MODEL BY SES'!$C$19:$R$242,MATCH('SeS in Retail Sales Areas'!J$7,'NEW MODEL BY SES'!$C$17:$R$17,0),0),"") | K17: =IFERROR(VLOOKUP($C17,'NEW MODEL BY SES'!$C$19:$R$242,MATCH('SeS in Retail Sales Areas'!K$7,'NEW MODEL BY SES'!$C$17:$R$17,0),0),"") | L17: =IFERROR(VLOOKUP($C17,'NEW MODEL BY SES'!$C$19:$R$242,MATCH('SeS in Retail Sales Areas'!L$7,'NEW MODEL BY SES'!$C$17:$R$17,0),0),"") | M17: =IFERROR(VLOOKUP($C17,'NEW MODEL BY SES'!$C$19:$R$242,MATCH('SeS in Retail Sales Areas'!M$7,'NEW MODEL BY SES'!$C$17:$R$17,0),0),"") | ... X17: =IFERROR(VLOOKUP($C17,'NEW MODEL BY SES'!$C$19:$R$242,MATCH('SeS in Retail Sales Areas'!X$7,'NEW MODEL BY SES'!$C$17:$R$17,0),0),"")
A18: HU-12 | B18: 118 | C18: M1 autópálya, 22 km I. (jobb) | D18: III | F18: =IFERROR(VLOOKUP($C18,'NEW MODEL BY SES'!$C$19:$R$242,MATCH('SeS in Retail Sales Areas'!F$7,'NEW MODEL BY SES'!$C$17:$R$17,0),0),"") | G18: =IFERROR(VLOOKUP($C18,'NEW MODEL BY SES'!$C$19:$R$242,MATCH('SeS in Retail Sales Areas'!G$7,'NEW MODEL BY SES'!$C$17:$R$17,0),0),"") | H18: =IFERROR(VLOOKUP($C18,'NEW MODEL BY SES'!$C$19:$R$242,MATCH('SeS in Retail Sales Areas'!H$7,'NEW MODEL BY SES'!$C$17:$R$17,0),0),"") | I18: =IFERROR(VLOOKUP($C18,'NEW MODEL BY SES'!$C$19:$R$242,MATCH('SeS in Retail Sales Areas'!I$7,'NEW MODEL BY SES'!$C$17:$R$17,0),0),"") | J18: =IFERROR(VLOOKUP($C18,'NEW MODEL BY SES'!$C$19:$R$242,MATCH('SeS in Retail Sales Areas'!J$7,'NEW MODEL BY SES'!$C$17:$R$17,0),0),"") | K18: =IFERROR(VLOOKUP($C18,'NEW MODEL BY SES'!$C$19:$R$242,MATCH('SeS in Retail Sales Areas'!K$7,'NEW MODEL BY SES'!$C$17:$R$17,0),0),"") | L18: =IFERROR(VLOOKUP($C18,'NEW MODEL BY SES'!$C$19:$R$242,MATCH('SeS in Retail Sales Areas'!L$7,'NEW MODEL BY SES'!$C$17:$R$17,0),0),"") | M18: =IFERROR(VLOOKUP($C18,'NEW MODEL BY SES'!$C$19:$R$242,MATCH('SeS in Retail Sales Areas'!M$7,'NEW MODEL BY SES'!$C$17:$R$17,0),0),"") | ... X18: =IFERROR(VLOOKUP($C18,'NEW MODEL BY SES'!$C$19:$R$242,MATCH('SeS in Retail Sales Areas'!X$7,'NEW MODEL BY SES'!$C$17:$R$17,0),0),"")
A19: HU-12 | B19: 113 | C19: Rajka, Bem József u. | D19: III | F19: =IFERROR(VLOOKUP($C19,'NEW MODEL BY SES'!$C$19:$R$242,MATCH('SeS in Retail Sales Areas'!F$7,'NEW MODEL BY SES'!$C$17:$R$17,0),0),"") | G19: =IFERROR(VLOOKUP($C19,'NEW MODEL BY SES'!$C$19:$R$242,MATCH('SeS in Retail Sales Areas'!G$7,'NEW MODEL BY SES'!$C$17:$R$17,0),0),"") | H19: =IFERROR(VLOOKUP($C19,'NEW MODEL BY SES'!$C$19:$R$242,MATCH('SeS in Retail Sales Areas'!H$7,'NEW MODEL BY SES'!$C$17:$R$17,0),0),"") | I19: =IFERROR(VLOOKUP($C19,'NEW MODEL BY SES'!$C$19:$R$242,MATCH('SeS in Retail Sales Areas'!I$7,'NEW MODEL BY SES'!$C$17:$R$17,0),0),"") | J19: =IFERROR(VLOOKUP($C19,'NEW MODEL BY SES'!$C$19:$R$242,MATCH('SeS in Retail Sales Areas'!J$7,'NEW MODEL BY SES'!$C$17:$R$17,0),0),"") | K19: =IFERROR(VLOOKUP($C19,'NEW MODEL BY SES'!$C$19:$R$242,MATCH('SeS in Retail Sales Areas'!K$7,'NEW MODEL BY SES'!$C$17:$R$17,0),0),"") | L19: =IFERROR(VLOOKUP($C19,'NEW MODEL BY SES'!$C$19:$R$242,MATCH('SeS in Retail Sales Areas'!L$7,'NEW MODEL BY SES'!$C$17:$R$17,0),0),"") | M19: =IFERROR(VLOOKUP($C19,'NEW MODEL BY SES'!$C$19:$R$242,MATCH('SeS in Retail Sales Areas'!M$7,'NEW MODEL BY SES'!$C$17:$R$17,0),0),"") | ... X19: =IFERROR(VLOOKUP($C19,'NEW MODEL BY SES'!$C$19:$R$242,MATCH('SeS in Retail Sales Areas'!X$7,'NEW MODEL BY SES'!$C$17:$R$17,0),0),"")
A20: HU-12 | B20: 108 | C20: Csorna, Soproni út | D20: III | F20: =IFERROR(VLOOKUP($C20,'NEW MODEL BY SES'!$C$19:$R$242,MATCH('SeS in Retail Sales Areas'!F$7,'NEW MODEL BY SES'!$C$17:$R$17,0),0),"") | G20: =IFERROR(VLOOKUP($C20,'NEW MODEL BY SES'!$C$19:$R$242,MATCH('SeS in Retail Sales Areas'!G$7,'NEW MODEL BY SES'!$C$17:$R$17,0),0),"") | H20: =IFERROR(VLOOKUP($C20,'NEW MODEL BY SES'!$C$19:$R$242,MATCH('SeS in Retail Sales Areas'!H$7,'NEW MODEL BY SES'!$C$17:$R$17,0),0),"") | I20: =IFERROR(VLOOKUP($C20,'NEW MODEL BY SES'!$C$19:$R$242,MATCH('SeS in Retail Sales Areas'!I$7,'NEW MODEL BY SES'!$C$17:$R$17,0),0),"") | J20: =IFERROR(VLOOKUP($C20,'NEW MODEL BY SES'!$C$19:$R$242,MATCH('SeS in Retail Sales Areas'!J$7,'NEW MODEL BY SES'!$C$17:$R$17,0),0),"") | K20: =IFERROR(VLOOKUP($C20,'NEW MODEL BY SES'!$C$19:$R$242,MATCH('SeS in Retail Sales Areas'!K$7,'NEW MODEL BY SES'!$C$17:$R$17,0),0),"") | L20: =IFERROR(VLOOKUP($C20,'NEW MODEL BY SES'!$C$19:$R$242,MATCH('SeS in Retail Sales Areas'!L$7,'NEW MODEL BY SES'!$C$17:$R$17,0),0),"") | M20: =IFERROR(VLOOKUP($C20,'NEW MODEL BY SES'!$C$19:$R$242,MATCH('SeS in Retail Sales Areas'!M$7,'NEW MODEL BY SES'!$C$17:$R$17,0),0),"") | ... X20: =IFERROR(VLOOKUP($C20,'NEW MODEL BY SES'!$C$19:$R$242,MATCH('SeS in Retail Sales Areas'!X$7,'NEW MODEL BY SES'!$C$17:$R$17,0),0),"")
... A446: HU-03 | B446: 67 | C446: Miskolc, Boldva u. 2. | D446: IV | F446: =IFERROR(VLOOKUP($C446,'NEW MODEL BY SES'!$C$19:$R$242,MATCH('SeS in Retail Sales Areas'!F$7,'NEW MODEL BY SES'!$C$17:$R$17,0),0),"") | G446: =IFERROR(VLOOKUP($C446,'NEW MODEL BY SES'!$C$19:$R$242,MATCH('SeS in Retail Sales Areas'!G$7,'NEW MODEL BY SES'!$C$17:$R$17,0),0),"") | H446: =IFERROR(VLOOKUP($C446,'NEW MODEL BY SES'!$C$19:$R$242,MATCH('SeS in Retail Sales Areas'!H$7,'NEW MODEL BY SES'!$C$17:$R$17,0),0),"") | I446: =IFERROR(VLOOKUP($C446,'NEW MODEL BY SES'!$C$19:$R$242,MATCH('SeS in Retail Sales Areas'!I$7,'NEW MODEL BY SES'!$C$17:$R$17,0),0),"") | J446: =IFERROR(VLOOKUP($C446,'NEW MODEL BY SES'!$C$19:$R$242,MATCH('SeS in Retail Sales Areas'!J$7,'NEW MODEL BY SES'!$C$17:$R$17,0),0),"") | K446: =IFERROR(VLOOKUP($C446,'NEW MODEL BY SES'!$C$19:$R$242,MATCH('SeS in Retail Sales Areas'!K$7,'NEW MODEL BY SES'!$C$17:$R$17,0),0),"") | L446: =IFERROR(VLOOKUP($C446,'NEW MODEL BY SES'!$C$19:$R$242,MATCH('SeS in Retail Sales Areas'!L$7,'NEW MODEL BY SES'!$C$17:$R$17,0),0),"") | M446: =IFERROR(VLOOKUP($C446,'NEW MODEL BY SES'!$C$19:$R$242,MATCH('SeS in Retail Sales Areas'!M$7,'NEW MODEL BY SES'!$C$17:$R$17,0),0),"") | ... X446: =IFERROR(VLOOKUP($C446,'NEW MODEL BY SES'!$C$19:$R$242,MATCH('SeS in Retail Sales Areas'!X$7,'NEW MODEL BY SES'!$C$17:$R$17,0),0),"")
A447: Végösszeg

Sheet Changes description
B3: Key changes in comparison with the current model | H3: Promjene u načinu određivanja kategorija
B5: Change | C5: Explanation | H5: Promjena | I5: Obrazloženje
B6: The current or subsequent year plan is used for categorization instead of the turnover achieved in the previous year | C6: The achievement (last year results) contains numerous one-off/temporary influences on the decrease or growth of traffic (see data on the sheet "Indicator of sale interruption), while the plan is consistent and reflects the expected “effort” for SeS, so the category should be evaluated by the future expectation rather than the previous situation. | H6: Umjesto ostvarenog prometa iz prethodne godine, za kateogorizaciju se koristi plan tekuće ili naredne godine | I6: Ostvarenje sadrži brojne jednokratne/privremene utjecaje na pad ili rast prometa (više na listu "Indicator of sale interruption"), dok je plan konzistentan i odražava očekivani "napor" za MPM pa kategorija treba vrednovati za buduće, a ne prijašnje stanje.
B7: Fuels shall be expressed in litres instead of tonnes | C7: The plan and sale results at the SeS are expressed in litres in all reports , therefore it is easiers for users to comprehand liters than tons. | H7: Goriva se iskazuju u litrama umjesto u tonama | I7: Planiranje i praćenje ostvarenja na MPM iskazuje se u izvještajima u litrama te je korisnicma taj podatak dostupniji i lakši za predočiti.
B8: The NON-FUEL criterion is divided into categories that are scored individualy | C8: All components (artice categories which are planned on SeS level) of NON-FUEL are added: Shop, Bottled LPG, Motor oils and Industrial lubricants, Gastro and Car wash | H8: Kriterij NEGORIVA podjeljen je u kategorije koje se boduju pojedinačno | I8: Dodane su sve komponente koje čine NEGORIVA: RŠP, Plin u boci, Ulja i maziva, Ugostiteljstvo i Autopraonice
B9: NON-FUEL | C9: Turnover (HRK) | D9: % in total | E9: Margin (HRK) | F9: % in total | H9: Kategorije NEGORIVA | I9: PROMET (HRK) | J9: Udio u uk. | K9: Marža (HRK) | L9: Udio u uk.
B10: NON-FUEL total | C10: 1.4002826e+09 | D10: =C10/$I$10 -> 1 | E10: 3.0202209e+08 | F10: =E10/$K$10 -> 1 | H10: NEGORIVA UKUPNO kn | I10: 1.4002826e+09 | J10: =I10/$I$10 -> 1 | K10: 3.0202209e+08 | L10: =K10/$K$10 -> 1
B11: Shop | C11: 1104343188 | D11: =C11/$I$10 -> 0.78865737 | E11: 1.6967611e+08 | F11: =E11/$K$10 -> 0.56180032 | H11: RŠP | I11: 1104343188 | J11: =I11/$I$10 -> 0.78865737 | K11: 1.6967611e+08 | L11: =K11/$K$10 -> 0.56180032
B12: Bottled LPG | C12: 1.2130623e+08 | D12: =C12/$I$10 -> 0.086629818 | E12: 35625559 | F12: =E12/$K$10 -> 0.1179568 | H12: Plin u boci | I12: 1.2130623e+08 | J12: =I12/$I$10 -> 0.086629818 | K12: 35625559 | L12: =K12/$K$10 -> 0.1179568
B13: Motor oils and Industrial lubricants | C13: 47279367 | D13: =C13/$I$10 -> 0.033764161 | E13: 13615802 | F13: =E13/$K$10 -> 0.045082139 | H13: Ulja i maziva | I13: 47279367 | J13: =I13/$I$10 -> 0.033764161 | K13: 13615802 | L13: =K13/$K$10 -> 0.045082139
B14: Gastro | C14: 121067523 | D14: =C14/$I$10 -> 0.08645935 | E14: 77725939 | F14: =E14/$K$10 -> 0.25735183 | H14: Ugostiteljstvo | I14: 121067523 | J14: =I14/$I$10 -> 0.08645935 | K14: 77725939 | L14: =K14/$K$10 -> 0.25735183
B15: Car wash | C15: 6286292 | D15: =C15/$I$10 -> 0.0044893024 | E15: 5378687.2 | F15: =E15/$K$10 -> 0.01780892 | H15: Autopraonice | I15: 6286292 | J15: =I15/$I$10 -> 0.0044893024 | K15: 5378687.2 | L15: =K15/$K$10 -> 0.01780892
B16: Each criterion is divided into ranges, and each range is awarded points. The sum of points is the final score of SeS based on which the category is determined. " | C16: Several criteria enable more precise evaluation of the complexity of SeS. The scoring of the ranges of different criteria by different number of points makes it possible to differentiate criteria by importance, i.e. the impact of a particular criterion on the complexity and burden on a given SeS, as well as its importance in the network. | H16: Svaki kriterij podijeljen je u raspone, a svakom rasponu dodjeljuju se bodovi. Zbroj bodova je konačna ocjena MPM temeljem koje se određuje kategorija. | I16: Više kriterija omogućuje preciznije vrednovanje kompleksnosti MPM. Bodovanje raspona različitih kriterija različitim brojem bodova omogućuje razlikovanje kriterija po važnosti, tj. utjecaju pojedinog kriterija na složenost i zahtjevnost rada na određenom MPM, kao i njegovu važnost u mreži.
B17: Razdvojen prihod u kategoriji Ugostiteljstvo na FC/AB i CC | C17: A certain number of SeS which have CC (coffee corner without food preparation), generate large revenues with much less involvement of workers and managers than the engagement needed to achieve the same or similar income at FC/AB. Therefore, for the same income range, the CC is awarded a smaller number of points. | H17: Razdvojen prihod u kategoriji Ugostiteljstvo na FC/AB i CC | I17: Određeni broj MPM koja imaju samo CC (coffee corner bez pripreme hrane), ostvaruju velike prihode uz puno manji angažman radnika i Voditelja u odnosu angažman potreban da se isti ili sličan prihod ostvari na FC/AB. Zbog toga se za isti raspon prihoda, CC-u dodjeljuje manji broj bodova.
B18: Introduced criterion "number of employess" | C18: The number of workers significantly affects the workload and responsibilities of the manager Number of Employees significantly Impacts the responsibility and burden fo the head of sea | H18: Uveden kriterij za bodovanje "broj radnika" | I18: Broj radnika značajno utječe na radno opterećenje i odgovornost Voditelja
B19: Number fo categiries is expanded form three to four, and ranking is in reverse order. Category 1 (one) is reserved for flagship SeS only, those few with highest turnover, complexity of offering and burden for employees and head od SeS. | C19: Old New - I III II II III I IV | H19: Proširen broj kategorija s tri na četiri te je obrnut redoslijed. Prva kateogorija dodjeljuje se samo malom broju MPM s najvećim prometom, najkompleksnijim sadržajima te najvećim opeterećenjem radnika i voditelja. | I19: Staro Novo - I III II II III I IV
B20: "Numer of transactions" is not taken as a criterion for categorization | C20: "Number of transactions" is vague criterion which is therefore substituted by other specific criteria that incorporate either turnover, service time or burden. One transaction equally represents sale of LPG, full tank of fuel or one pack of cigarettes which are all very different in values, time and burden, and their separate evaluation much better contribute to the fair categorization. Most criteria are based on planned values (BU) and no. of transactions is not being planned. | H20: Broj transasakcija nije uvršten kao kriterij u kategorizaciji | I20: „Brojnik transakcija” je preopćenit kriterij, te ga zamijenjuju drugi kriteriji koji obuhvaćaju promet, trajanje usluge i napor radnika. Jedna transakcija jednako predstavlja prodaju UNP za automobile, punog spremnika goriva ili jednog pakiranja cigareta, koje su sve vrlo različite po vrijednosti, vremenu i opterećenju te njihova pojedinačna evaluacija bolje pridonosi kategorizaciji. Većina kriterija zasniva se na planiranim vrijednostima, pa i sa te osnove transakcije nisu pogodne za uvrštavanje kao kriterij jer transakcije se ne planiraju.

Sheet current criteria
D2: CATEGORIZATION
D3: Dokument: Postupak organizacije rada na maloprodajnim mjestima, izdanje 05, datum stupanja na snagu 7.2.2017.
R4: CATEGORIZATION CRITERIA
S6: III | V6: II | Z6: II | AC6: II | AE6: I
R7: FUEL (T) | S7: ≥ | T7: 3500 | V7: ≥ | W7: 3500 | Y7: 2000 | Z7: ≤ > | AA7: 3500 | AB7: < | AC7: 2000 | AE7: < | AF7: 2000
R9: NON-FUEL(000 HRK) | S9: ≥ | T9: 1500 | V9: < | W9: 1500 | Z9: N/A | AB9: ≥ | AC9: 1500 | AE9: < | AF9: 1500
B10: III
B23: II
B35: I

Sheet Indicator of sale interruption
A1: Rbr | B1: Lokacija | C1: Šifra REGIJA | D1: REGIJA | E1: Šifra RPM | F1: Reg. područje maloprodaje - RPM | G1: Šifra pogleda MM | H1: SAP šifra lokacije | I1: Dodatna šifra | J1: Profitni centar (planska šifra) | K1: Profitni centar (izvještajna šifra) | L1: PSUM indikator | M1: Naziv maloprodajnog mjesta | N1: Napomena | O1: =SUM(O2:O482) -> 89 | P1: I 2019. | Q1: II 2019. | R1: III 2019. | S1: IV 2019. | T1: V 2019. | U1: VI 2019. | V1: VII 2019. | W1: VIII 2019. | X1: IX 2019. | Y1: X 2019. | Z1: XI 2019. | AA1: XII 2019. | AB1: =SUM(AB2:AB482) -> 134 | AC1: I 2018. | AD1: II 2018. | AE1: III 2018. | AF1: IV 2018. | AG1: V 2018. | AH1: VI 2018. | AI1: VII 2018. | AJ1: VIII 2018. | AK1: IX 2018. | AL1: X 2018. | AM1: XI 2018. | AN1: XII 2018. | AO1: =SUM(AO2:AO482) -> 131 | AP1: I 2017. | AQ1: II 2017. | AR1: III 2017. | AS1: IV 2017. | AT1: V 2017. | AU1: VI 2017. | AV1: VII 2017. | AW1: VIII 2017. | AX1: IX 2017. | AY1: X 2017. | AZ1: XI 2017. | BA1: XII 2017. | BB1: =SUM(BB2:BB482) -> 109 | BC1: I 2016. | BD1: II 2016. | BE1: III 2016. | BF1: IV 2016. | BG1: V 2016. | BH1: VI 2016. | BI1: VII 2016. | BJ1: VIII 2016. | BK1: IX 2016. | BL1: X 2016. | BM1: XI 2016. | BN1: XII 2016. | BO1: =SUM(BO2:BO482) -> 176 | BP1: I 2015. | BQ1: II 2015. | BR1: III 2015. | BS1: IV 2015. | BT1: V 2015. | BU1: VI 2015. | BV1: VII 2015. | BW1: VIII 2015. | BX1: IX 2015. | BY1: X 2015. | BZ1: XI 2015. | CA1: XII 2015.
A2: 1 | B2: 1 | C2: 01007-103 | D2: ZAPAD | E2: 01007-10303 | F2: Z3 Karlovac | G2: S079 | H2: S079 | J2: 712309S | K2: 0100/712309S | L2: PSUM | M2: Duga Resa | N2: 17.06.2015. primopredaja BP u ruke partnera - PSUM | O2: =COUNTIF(P2:AA2,"NE") -> 0 | P2: DA | Q2: DA | R2: DA | S2: DA | T2: DA | U2: DA | V2: DA | W2: DA | X2: DA | Y2: DA | Z2: DA | AA2: DA | AB2: =COUNTIF(AC2:AN2,"NE") -> 0 | AC2: DA | AD2: DA | AE2: DA | AF2: DA | AG2: DA | AH2: DA | AI2: DA | AJ2: DA | AK2: DA | AL2: DA | AM2: DA | AN2: DA | AO2: =COUNTIF(AC2:AM2,"NE") -> 0 | AP2: DA | AQ2: DA | AR2: DA | AS2: DA | AT2: DA | AU2: DA | AV2: DA | AW2: DA | AX2: DA | AY2: DA | AZ2: DA | BA2: DA | BB2: =COUNTIF(AP2:AZ2,"NE") -> 0 | BC2: DA | BD2: DA | BE2: DA | BF2: DA | BG2: DA | BH2: DA | BI2: DA | BJ2: DA | BK2: DA | BL2: DA | BM2: DA | BN2: DA | BO2: =COUNTIF(BC2:BM2,"NE") -> 0 | BP2: DA | BQ2: DA | BR2: DA | BS2: DA | BT2: DA | BU2: DA | BV2: DA | BW2: DA | BX2: DA | BY2: DA | BZ2: DA | CA2: DA
A3: 2 | B3: Z | C3: 01007-103 | D3: ZAPAD | E3: 01007-10303 | F3: Z3 Karlovac | G3: S083 | H3: S083 | J3: 712313S | K3: 01007-12113 | M3: Jasenak | N3: Z. 29.03.2012. (OJ 50001513 brisanje 31.03.2012.) | O3: =COUNTIF(P3:AA3,"NE") -> 0 | AB3: =COUNTIF(AC3:AN3,"NE") -> 0 | AO3: =COUNTIF(AC3:AM3,"NE") -> 0 | BB3: =COUNTIF(AP3:AZ3,"NE") -> 0 | BO3: =COUNTIF(BC3:BM3,"NE") -> 0
A4: 3 | B4: 1 | C4: 01007-103 | D4: ZAPAD | E4: 01007-10303 | F4: Z3 Karlovac | G4: S071 | H4: S071 | J4: 712301S | K4: 0100/712301S | M4: Josipdol | N4: Z. 28.08. do 02.11.2017. (projekt održavanja/modernizacija cca 45 dana); | O4: =COUNTIF(P4:AA4,"NE") -> 0 | P4: DA | Q4: DA | R4: DA | S4: DA | T4: DA | U4: DA | V4: DA | W4: DA | X4: DA | Y4: DA | Z4: DA | AA4: DA | AB4: =COUNTIF(AC4:AN4,"NE") -> 0 | AC4: DA | AD4: DA | AE4: DA | AF4: DA | AG4: DA | AH4: DA | AI4: DA | AJ4: DA | AK4: DA | AL4: DA | AM4: DA | AN4: DA | AO4: =COUNTIF(AC4:AM4,"NE") -> 0 | AP4: DA | AQ4: DA | AR4: DA | AS4: DA | AT4: DA | AU4: DA | AV4: DA | AW4: NE | AX4: NE | AY4: NE | AZ4: NE | BA4: DA | BB4: =COUNTIF(AP4:AZ4,"NE") -> 4 | BC4: DA | BD4: DA | BE4: DA | BF4: DA | BG4: DA | BH4: DA | BI4: DA | BJ4: DA | BK4: DA | BL4: DA | BM4: DA | BN4: DA | BO4: =COUNTIF(BC4:BM4,"NE") -> 0 | BP4: DA | BQ4: DA | BR4: DA | BS4: DA | BT4: DA | BU4: DA | BV4: DA | BW4: DA | BX4: DA | BY4: DA | BZ4: DA | CA4: DA
A5: 4 | B5: Z | C5: 01007-103 | D5: ZAPAD | E5: 01007-10303 | F5: Z3 Karlovac | G5: H420 | H5: H420 | J5: 712317S | K5: 01007-12117 | M5: Karlovac LU EL | N5: Z. 23.07.2014.; trajno Z. 31.08.2014. -brisanje OJ 50001512; | O5: =COUNTIF(P5:AA5,"NE") -> 0 | AB5: =COUNTIF(AC5:AN5,"NE") -> 0 | AO5: =COUNTIF(AC5:AM5,"NE") -> 0 | BB5: =COUNTIF(AP5:AZ5,"NE") -> 0 | BO5: =COUNTIF(BC5:BM5,"NE") -> 0
A6: 5 | B6: 1 | C6: 01007-103 | D6: ZAPAD | E6: 01007-10303 | F6: Z3 Karlovac | G6: S080 | H6: S080 | J6: 712310S | K6: 0100/712310S | L6: PSUM | M6: Karlovac-Dubovac | N6: 30.09.2017. promjena PSUM partnera (29.07.2014. primopredaja BP u ruke partnera - PSUM) | O6: =COUNTIF(P6:AA6,"NE") -> 0 | P6: DA | Q6: DA | R6: DA | S6: DA | T6: DA | U6: DA | V6: DA | W6: DA | X6: DA | Y6: DA | Z6: DA | AA6: DA | AB6: =COUNTIF(AC6:AN6,"NE") -> 0 | AC6: DA | AD6: DA | AE6: DA | AF6: DA | AG6: DA | AH6: DA | AI6: DA | AJ6: DA | AK6: DA | AL6: DA | AM6: DA | AN6: DA | AO6: =COUNTIF(AC6:AM6,"NE") -> 0 | AP6: DA | AQ6: DA | AR6: DA | AS6: DA | AT6: DA | AU6: DA | AV6: DA | AW6: DA | AX6: NE | AY6: DA | AZ6: DA | BA6: DA | BB6: =COUNTIF(AP6:AZ6,"NE") -> 1 | BC6: DA | BD6: DA | BE6: DA | BF6: DA | BG6: DA | BH6: DA | BI6: DA | BJ6: DA | BK6: DA | BL6: DA | BM6: DA | BN6: DA | BO6: =COUNTIF(BC6:BM6,"NE") -> 0 | BP6: DA | BQ6: DA | BR6: DA | BS6: DA | BT6: DA | BU6: DA | BV6: DA | BW6: DA | BX6: DA | BY6: DA | BZ6: DA | CA6: DA
A7: 6 | B7: 1 | C7: 01007-103 | D7: ZAPAD | E7: 01007-10303 | F7: Z3 Karlovac | G7: S072 | H7: S072 | I7: H072 | J7: 712302S | K7: 0100/712302S | M7: Karlovac-Ilovac | O7: =COUNTIF(P7:AA7,"NE") -> 0 | P7: DA | Q7: DA | R7: DA | S7: DA | T7: DA | U7: DA | V7: DA | W7: DA | X7: DA | Y7: DA | Z7: DA | AA7: DA | AB7: =COUNTIF(AC7:AN7,"NE") -> 0 | AC7: DA | AD7: DA | AE7: DA | AF7: DA | AG7: DA | AH7: DA | AI7: DA | AJ7: DA | AK7: DA | AL7: DA | AM7: DA | AN7: DA | AO7: =COUNTIF(AC7:AM7,"NE") -> 0 | AP7: DA | AQ7: DA | AR7: DA | AS7: DA | AT7: DA | AU7: DA | AV7: DA | AW7: DA | AX7: DA | AY7: DA | AZ7: DA | BA7: DA | BB7: =COUNTIF(AP7:AZ7,"NE") -> 0 | BC7: DA | BD7: DA | BE7: DA | BF7: DA | BG7: DA | BH7: DA | BI7: DA | BJ7: DA | BK7: DA | BL7: DA | BM7: DA | BN7: DA | BO7: =COUNTIF(BC7:BM7,"NE") -> 0 | BP7: DA | BQ7: DA | BR7: DA | BS7: DA | BT7: DA | BU7: DA | BV7: DA | BW7: DA | BX7: DA | BY7: DA | BZ7: DA | CA7: DA
A8: 7 | B8: 1 | C8: 01007-103 | D8: ZAPAD | E8: 01007-10303 | F8: Z3 Karlovac | G8: S076 | H8: S076 | J8: 712306S | K8: 0100/712306S | M8: Karlovac-Rakovac | O8: =COUNTIF(P8:AA8,"NE") -> 0 | P8: DA | Q8: DA | R8: DA | S8: DA | T8: DA | U8: DA | V8: DA | W8: DA | X8: DA | Y8: DA | Z8: DA | AA8: DA | AB8: =COUNTIF(AC8:AN8,"NE") -> 0 | AC8: DA | AD8: DA | AE8: DA | AF8: DA | AG8: DA | AH8: DA | AI8: DA | AJ8: DA | AK8: DA | AL8: DA | AM8: DA | AN8: DA | AO8: =COUNTIF(AC8:AM8,"NE") -> 0 | AP8: DA | AQ8: DA | AR8: DA | AS8: DA | AT8: DA | AU8: DA | AV8: DA | AW8: DA | AX8: DA | AY8: DA | AZ8: DA | BA8: DA | BB8: =COUNTIF(AP8:AZ8,"NE") -> 0 | BC8: DA | BD8: DA | BE8: DA | BF8: DA | BG8: DA | BH8: DA | BI8: DA | BJ8: DA | BK8: DA | BL8: DA | BM8: DA | BN8: DA | BO8: =COUNTIF(BC8:BM8,"NE") -> 0 | BP8: DA | BQ8: DA | BR8: DA | BS8: DA | BT8: DA | BU8: DA | BV8: DA | BW8: DA | BX8: DA | BY8: DA | BZ8: DA | CA8: DA
A9: 8 | B9: 1 | C9: 01007-103 | D9: ZAPAD | E9: 01007-10303 | F9: Z3 Karlovac | G9: S077 | H9: S077 | J9: 712307S | K9: 0100/712307S | M9: Karlovac-Smičiklasova | N9: Z. 12.04. do 28.05.2018. (implementacija FC - cca 37 dana) | O9: =COUNTIF(P9:AA9,"NE") -> 0 | P9: DA | Q9: DA | R9: DA | S9: DA | T9: DA | U9: DA | V9: DA | W9: DA | X9: DA | Y9: DA | Z9: DA | AA9: DA | AB9: =COUNTIF(AC9:AN9,"NE") -> 2 | AC9: DA | AD9: DA | AE9: DA | AF9: NE | AG9: NE | AH9: DA | AI9: DA | AJ9: DA | AK9: DA | AL9: DA | AM9: DA | AN9: DA | AO9: =COUNTIF(AC9:AM9,"NE") -> 2 | AP9: DA | AQ9: DA | AR9: DA | AS9: DA | AT9: DA | AU9: DA | AV9: DA | AW9: DA | AX9: DA | AY9: DA | AZ9: DA | BA9: DA | BB9: =COUNTIF(AP9:AZ9,"NE") -> 0 | BC9: DA | BD9: DA | BE9: DA | BF9: DA | BG9: DA | BH9: DA | BI9: DA | BJ9: DA | BK9: DA | BL9: DA | BM9: DA | BN9: DA | BO9: =COUNTIF(BC9:BM9,"NE") -> 0 | BP9: DA | BQ9: DA | BR9: DA | BS9: DA | BT9: DA | BU9: DA | BV9: DA | BW9: DA | BX9: DA | BY9: DA | BZ9: DA | CA9: DA
A10: 9 | C10: 01007-103 | D10: ZAPAD | E10: 01007-10303 | F10: Z3 Karlovac | G10: S077 | H10: C077 | I10: C077 | J10: 712307S | K10: 0100/712307S | M10: Karlovac-Smičiklasova AB | N10: Z. trajno 01.08.2018.(C+S); O. 01.08.2018. Fresh corner | O10: =COUNTIF(P10:AA10,"NE") -> 0 | AB10: =COUNTIF(AC10:AN10,"NE") -> 4 | AF10: NE | AG10: NE | AH10: NE | AI10: NE | AO10: =COUNTIF(AC10:AM10,"NE") -> 4 | BB10: =COUNTIF(AP10:AZ10,"NE") -> 0 | BO10: =COUNTIF(BC10:BM10,"NE") -> 0
A11: 10 | B11: 1 | C11: 01007-103 | D11: ZAPAD | E11: 01007-10303 | F11: Z3 Karlovac | G11: S075 | H11: S075 | I11: H075 | J11: 712305S | K11: 0100/712305S | M11: Ogulin | O11: =COUNTIF(P11:AA11,"NE") -> 0 | P11: DA | Q11: DA | R11: DA | S11: DA | T11: DA | U11: DA | V11: DA | W11: DA | X11: DA | Y11: DA | Z11: DA | AA11: DA | AB11: =COUNTIF(AC11:AN11,"NE") -> 0 | AC11: DA | AD11: DA | AE11: DA | AF11: DA | AG11: DA | AH11: DA | AI11: DA | AJ11: DA | AK11: DA | AL11: DA | AM11: DA | AN11: DA | AO11: =COUNTIF(AC11:AM11,"NE") -> 0 | AP11: DA | AQ11: DA | AR11: DA | AS11: DA | AT11: DA | AU11: DA | AV11: DA | AW11: DA | AX11: DA | AY11: DA | AZ11: DA | BA11: DA | BB11: =COUNTIF(AP11:AZ11,"NE") -> 0 | BC11: DA | BD11: DA | BE11: DA | BF11: DA | BG11: DA | BH11: DA | BI11: DA | BJ11: DA | BK11: DA | BL11: DA | BM11: DA | BN11: DA | BO11: =COUNTIF(BC11:BM11,"NE") -> 0 | BP11: DA | BQ11: DA | BR11: DA | BS11: DA | BT11: DA | BU11: DA | BV11: DA | BW11: DA | BX11: DA | BY11: DA | BZ11: DA | CA11: DA
A12: 11 | B12: 1 | C12: 01007-103 | D12: ZAPAD | E12: 01007-10303 | F12: Z3 Karlovac | G12: S082 | H12: S082 | J12: 712312S | K12: 0100/712312S | M12: Plaški | O12: =COUNTIF(P12:AA12,"NE") -> 0 | P12: DA | Q12: DA | R12: DA | S12: DA | T12: DA | U12: DA | V12: DA | W12: DA | X12: DA | Y12: DA | Z12: DA | AA12: DA | AB12: =COUNTIF(AC12:AN12,"NE") -> 0 | AC12: DA | AD12: DA | AE12: DA | AF12: DA | AG12: DA | AH12: DA | AI12: DA | AJ12: DA | AK12: DA | AL12: DA | AM12: DA | AN12: DA | AO12: =COUNTIF(AC12:AM12,"NE") -> 0 | AP12: DA | AQ12: DA | AR12: DA | AS12: DA | AT12: DA | AU12: DA | AV12: DA | AW12: DA | AX12: DA | AY12: DA | AZ12: DA | BA12: DA | BB12: =COUNTIF(AP12:AZ12,"NE") -> 0 | BC12: DA | BD12: DA | BE12: DA | BF12: DA | BG12: DA | BH12: DA | BI12: DA | BJ12: DA | BK12: DA | BL12: DA | BM12: DA | BN12: DA | BO12: =COUNTIF(BC12:BM12,"NE") -> 0 | BP12: DA | BQ12: DA | BR12: DA | BS12: DA | BT12: DA | BU12: DA | BV12: DA | BW12: DA | BX12: DA | BY12: DA | BZ12: DA | CA12: DA
A13: 12 | B13: 1 | C13: 01007-103 | D13: ZAPAD | E13: 01007-10303 | F13: Z3 Karlovac | G13: S081 | H13: S081 | I13: H081 | J13: 712311S | K13: 0100/712311S | M13: Rakovica | N13: Z. 28.01. do 26.04.2016. (modernizacija cca 40 dana) | O13: =COUNTIF(P13:AA13,"NE") -> 0 | P13: DA | Q13: DA | R13: DA | S13: DA | T13: DA | U13: DA | V13: DA | W13: DA | X13: DA | Y13: DA | Z13: DA | AA13: DA | AB13: =COUNTIF(AC13:AN13,"NE") -> 0 | AC13: DA | AD13: DA | AE13: DA | AF13: DA | AG13: DA | AH13: DA | AI13: DA | AJ13: DA | AK13: DA | AL13: DA | AM13: DA | AN13: DA | AO13: =COUNTIF(AC13:AM13,"NE") -> 0 | AP13: DA | AQ13: DA | AR13: DA | AS13: DA | AT13: DA | AU13: DA | AV13: DA | AW13: DA | AX13: DA | AY13: DA | AZ13: DA | BA13: DA | BB13: =COUNTIF(AP13:AZ13,"NE") -> 0 | BC13: NE | BD13: NE | BE13: NE | BF13: NE | BG13: DA | BH13: DA | BI13: DA | BJ13: DA | BK13: DA | BL13: DA | BM13: DA | BN13: DA | BO13: =COUNTIF(BC13:BM13,"NE") -> 4 | BP13: DA | BQ13: DA | BR13: DA | BS13: DA | BT13: DA | BU13: DA | BV13: DA | BW13: DA | BX13: DA | BY13: DA | BZ13: DA | CA13: DA
A14: 13 | B14: 1 | C14: 01007-103 | D14: ZAPAD | E14: 01007-10303 | F14: Z3 Karlovac | G14: S073 | H14: S073 | J14: 712303S | K14: 0100/712303S | M14: Slunj | O14: =COUNTIF(P14:AA14,"NE") -> 0 | P14: DA | Q14: DA | R14: DA | S14: DA | T14: DA | U14: DA | V14: DA | W14: DA | X14: DA | Y14: DA | Z14: DA | AA14: DA | AB14: =COUNTIF(AC14:AN14,"NE") -> 0 | AC14: DA | AD14: DA | AE14: DA | AF14: DA | AG14: DA | AH14: DA | AI14: DA | AJ14: DA | AK14: DA | AL14: DA | AM14: DA | AN14: DA | AO14: =COUNTIF(AC14:AM14,"NE") -> 0 | AP14: DA | AQ14: DA | AR14: DA | AS14: DA | AT14: DA | AU14: DA | AV14: DA | AW14: DA | AX14: DA | AY14: DA | AZ14: DA | BA14: DA | BB14: =COUNTIF(AP14:AZ14,"NE") -> 0 | BC14: DA | BD14: DA | BE14: DA | BF14: DA | BG14: DA | BH14: DA | BI14: DA | BJ14: DA | BK14: DA | BL14: DA | BM14: DA | BN14: DA | BO14: =COUNTIF(BC14:BM14,"NE") -> 0 | BP14: DA | BQ14: DA | BR14: DA | BS14: DA | BT14: DA | BU14: DA | BV14: DA | BW14: DA | BX14: DA | BY14: DA | BZ14: DA | CA14: DA
A15: 14 | B15: 1 | C15: 01007-103 | D15: ZAPAD | E15: 01007-10303 | F15: Z3 Karlovac | G15: S078 | H15: S078 | I15: H078 | J15: 712308S | K15: 0100/712308S | M15: Vojnić | N15: Z. 03.12.2018. do 10.03.2019. (modernizacija cca 45 dana) | O15: =COUNTIF(P15:AA15,"NE") -> 3 | P15: NE | Q15: NE | R15: NE | S15: DA | T15: DA | U15: DA | V15: DA | W15: DA | X15: DA | Y15: DA | Z15: DA | AA15: DA | AB15: =COUNTIF(AC15:AN15,"NE") -> 1 | AC15: DA | AD15: DA | AE15: DA | AF15: DA | AG15: DA | AH15: DA | AI15: DA | AJ15: DA | AK15: DA | AL15: DA | AM15: DA | AN15: NE | AO15: =COUNTIF(AC15:AM15,"NE") -> 0 | AP15: DA | AQ15: DA | AR15: DA | AS15: DA | AT15: DA | AU15: DA | AV15: DA | AW15: DA | AX15: DA | AY15: DA | AZ15: DA | BA15: DA | BB15: =COUNTIF(AP15:AZ15,"NE") -> 0 | BC15: DA | BD15: DA | BE15: DA | BF15: DA | BG15: DA | BH15: DA | BI15: DA | BJ15: DA | BK15: DA | BL15: DA | BM15: DA | BN15: DA | BO15: =COUNTIF(BC15:BM15,"NE") -> 0 | BP15: DA | BQ15: DA | BR15: DA | BS15: DA | BT15: DA | BU15: DA | BV15: DA | BW15: DA | BX15: DA | BY15: DA | BZ15: DA | CA15: DA
A16: 15 | B16: 1 | C16: 01007-103 | D16: ZAPAD | E16: 01007-10303 | F16: Z3 Karlovac | G16: S430 | H16: S430 | J16: 712318S | K16: 01007-103031 | M16: Vukova Gorica | N16: 04.11.2019. do 19.12.2019. uređenje prodajnog prostora (cca 40 dana, rad iz kontejnera) | O16: =COUNTIF(P16:AA16,"NE") -> 0 | P16: DA | Q16: DA | R16: DA | S16: DA | T16: DA | U16: DA | V16: DA | W16: DA | X16: DA | Y16: DA | Z16: DA | AA16: DA | AB16: =COUNTIF(AC16:AN16,"NE") -> 0 | AC16: DA | AD16: DA | AE16: DA | AF16: DA | AG16: DA | AH16: DA | AI16: DA | AJ16: DA | AK16: DA | AL16: DA | AM16: DA | AN16: DA | AO16: =COUNTIF(AC16:AM16,"NE") -> 0 | AP16: DA | AQ16: DA | AR16: DA | AS16: DA | AT16: DA | AU16: DA | AV16: DA | AW16: DA | AX16: DA | AY16: DA | AZ16: DA | BA16: DA | BB16: =COUNTIF(AP16:AZ16,"NE") -> 0 | BC16: DA | BD16: DA | BE16: DA | BF16: DA | BG16: DA | BH16: DA | BI16: DA | BJ16: DA | BK16: DA | BL16: DA | BM16: DA | BN16: DA | BO16: =COUNTIF(BC16:BM16,"NE") -> 0 | BP16: DA | BQ16: DA | BR16: DA | BS16: DA | BT16: DA | BU16: DA | BV16: DA | BW16: DA | BX16: DA | BY16: DA | BZ16: DA | CA16: DA
A17: 16 | C17: 01007-103 | D17: ZAPAD | E17: 01007-10303 | F17: Z3 Karlovac | G17: S430 | H17: C430 | I17: C430 | J17: 712318C | K17: 01007-103031 | M17: Vukova Gorica restoran-AB | N17: 01.09.2013. promjena naziva (bistro u restoran) | O17: =COUNTIF(P17:AA17,"NE") -> 0 | P17: DA | Q17: DA | R17: DA | S17: DA | T17: DA | U17: DA | V17: DA | W17: DA | X17: DA | Y17: DA | Z17: DA | AA17: DA | AB17: =COUNTIF(AC17:AN17,"NE") -> 0 | AC17: DA | AD17: DA | AE17: DA | AF17: DA | AG17: DA | AH17: DA | AI17: DA | AJ17: DA | AK17: DA | AL17: DA | AM17: DA | AN17: DA | AO17: =COUNTIF(AC17:AM17,"NE") -> 0 | AP17: DA | AQ17: DA | AR17: DA | AS17: DA | AT17: DA | AU17: DA | AV17: DA | AW17: DA | AX17: DA | AY17: DA | AZ17: DA | BA17: DA | BB17: =COUNTIF(AP17:AZ17,"NE") -> 0 | BC17: DA | BD17: DA | BE17: DA | BF17: DA | BG17: DA | BH17: DA | BI17: DA | BJ17: DA | BK17: DA | BL17: DA | BM17: DA | BN17: DA | BO17: =COUNTIF(BC17:BM17,"NE") -> 0 | BP17: DA | BQ17: DA | BR17: DA | BS17: DA | BT17: DA | BU17: DA | BV17: DA | BW17: DA | BX17: DA | BY17: DA | BZ17: DA | CA17: DA
A18: 17 | C18: 01007-103 | D18: ZAPAD | E18: 01007-10303 | F18: Z3 Karlovac | G18: S430 | H18: S431 | I18: S431 | J18: 712318S | K18: 01007-103031 | M18: Vukova Gorica-prodavaonica | N18: 01.02.2016. spajanje sa BP= MPM; radi od 29.06.2007. (tzv suvenirnica) | O18: =COUNTIF(P18:AA18,"NE") -> 0 | P18: DA | Q18: DA | R18: DA | S18: DA | T18: DA | U18: DA | V18: DA | W18: DA | X18: DA | Y18: DA | Z18: DA | AA18: DA | AB18: =COUNTIF(AC18:AN18,"NE") -> 0 | AC18: DA | AD18: DA | AE18: DA | AF18: DA | AG18: DA | AH18: DA | AI18: DA | AJ18: DA | AK18: DA | AL18: DA | AM18: DA | AN18: DA | AO18: =COUNTIF(AC18:AM18,"NE") -> 0 | AP18: DA | AQ18: DA | AR18: DA | AS18: DA | AT18: DA | AU18: DA | AV18: DA | AW18: DA | AX18: DA | AY18: DA | AZ18: DA | BA18: DA | BB18: =COUNTIF(AP18:AZ18,"NE") -> 0 | BC18: DA | BD18: DA | BE18: DA | BF18: DA | BG18: DA | BH18: DA | BI18: DA | BJ18: DA | BK18: DA | BL18: DA | BM18: DA | BN18: DA | BO18: =COUNTIF(BC18:BM18,"NE") -> 0 | BP18: DA | BQ18: DA | BR18: DA | BS18: DA | BT18: DA | BU18: DA | BV18: DA | BW18: DA | BX18: DA | BY18: DA | BZ18: DA | CA18: DA
A19: 18 | B19: 1 | C19: 01007-103 | D19: ZAPAD | E19: 01007-10307 | F19: Z7 Zagreb-sjever | G19: S351 | H19: S351 | J19: 712131S | K19: 0100/712131S | L19: PSUM | M19: Zagreb-Bukovačka | N19: 08.05.2014. primopredaja BP u ruke partnera - PSUM | O19: =COUNTIF(P19:AA19,"NE") -> 0 | P19: DA | Q19: DA | R19: DA | S19: DA | T19: DA | U19: DA | V19: DA | W19: DA | X19: DA | Y19: DA | Z19: DA | AA19: DA | AB19: =COUNTIF(AC19:AN19,"NE") -> 0 | AC19: DA | AD19: DA | AE19: DA | AF19: DA | AG19: DA | AH19: DA | AI19: DA | AJ19: DA | AK19: DA | AL19: DA | AM19: DA | AN19: DA | AO19: =COUNTIF(AC19:AM19,"NE") -> 0 | AP19: DA | AQ19: DA | AR19: DA | AS19: DA | AT19: DA | AU19: DA | AV19: DA | AW19: DA | AX19: DA | AY19: DA | AZ19: DA | BA19: DA | BB19: =COUNTIF(AP19:AZ19,"NE") -> 0 | BC19: DA | BD19: DA | BE19: DA | BF19: DA | BG19: DA | BH19: DA | BI19: DA | BJ19: DA | BK19: DA | BL19: DA | BM19: DA | BN19: DA | BO19: =COUNTIF(BC19:BM19,"NE") -> 0 | BP19: DA | BQ19: DA | BR19: DA | BS19: DA | BT19: DA | BU19: DA | BV19: DA | BW19: DA | BX19: DA | BY19: DA | BZ19: DA | CA19: DA
A20: 19 | B20: 1 | C20: 01007-103 | D20: ZAPAD | E20: 01007-10307 | F20: Z7 Zagreb-sjever | G20: S346 | H20: S346 | J20: 712126S | K20: 0100/712126S | L20: PSUM | M20: Zagreb-Dubrava | N20: (11.09.-03.11.2017. projekt modernizacije-FC cca 30 dana) - rad iz kontejnera; 21.01.2016. primopredaja BP u ruke partnera - PSUM; ('03.2016. nova AP) | O20: =COUNTIF(P20:AA20,"NE") -> 0 | P20: DA | Q20: DA | R20: DA | S20: DA | T20: DA | U20: DA | V20: DA | W20: DA | X20: DA | Y20: DA | Z20: DA | AA20: DA | AB20: =COUNTIF(AC20:AN20,"NE") -> 0 | AC20: DA | AD20: DA | AE20: DA | AF20: DA | AG20: DA | AH20: DA | AI20: DA | AJ20: DA | AK20: DA | AL20: DA | AM20: DA | AN20: DA | AO20: =COUNTIF(AC20:AM20,"NE") -> 0 | AP20: DA | AQ20: DA | AR20: DA | AS20: DA | AT20: DA | AU20: DA | AV20: DA | AW20: DA | AX20: DA | AY20: DA | AZ20: DA | BA20: DA | BB20: =COUNTIF(AP20:AZ20,"NE") -> 0 | BC20: NE | BD20: DA | BE20: DA | BF20: DA | BG20: DA | BH20: DA | BI20: DA | BJ20: DA | BK20: DA | BL20: DA | BM20: DA | BN20: DA | BO20: =COUNTIF(BC20:BM20,"NE") -> 1 | BP20: DA | BQ20: DA | BR20: DA | BS20: DA | BT20: DA | BU20: DA | BV20: DA | BW20: DA | BX20: DA | BY20: DA | BZ20: DA | CA20: DA
A21: 20 | C21: 01007-103 | D21: ZAPAD | E21: 01007-10307 | F21: Z7 Zagreb-sjever | G21: S346 | H21: C346 | I21: C346 | J21: 712126S | K21: 0100/712126S | L21: PSUM | M21: Zagreb-Dubrava AB | N21: Z. trajno 01.08.2018.(C+S); O. 18.12.2017. Fresh corner | O21: =COUNTIF(P21:AA21,"NE") -> 0 | AB21: =COUNTIF(AC21:AN21,"NE") -> 0 | AC21: DA | AD21: DA | AE21: DA | AF21: DA | AG21: DA | AH21: DA | AI21: DA | AO21: =COUNTIF(AC21:AM21,"NE") -> 0 | AY21: NE | AZ21: NE | BA21: NE | BB21: =COUNTIF(AP21:AZ21,"NE") -> 2 | BO21: =COUNTIF(BC21:BM21,"NE") -> 0
A22: 21 | C22: 01007-103 | D22: ZAPAD | E22: 01007-10307 | F22: Z7 Zagreb-sjever | G22: S346 | H22: S426 | I22: S426 | J22: 712126L | K22: 0100/712126S | M22: Zagreb-Dubrava AP | N22: O. 05.04.2016.; Z. trajno 30.06.2015.-brisana OJ 50001432; (Z. 01.07.2014. - tehnički nedostaci) | O22: =COUNTIF(P22:AA22,"NE") -> 0 | AB22: =COUNTIF(AC22:AN22,"NE") -> 0 | AO22: =COUNTIF(AC22:AM22,"NE") -> 0 | BB22: =COUNTIF(AP22:AZ22,"NE") -> 0 | BO22: =COUNTIF(BC22:BM22,"NE") -> 0 | BP22: NE | BQ22: NE | BR22: NE | BS22: NE | BT22: NE | BU22: NE
A23: 22 | B23: 1 | C23: 01007-103 | D23: ZAPAD | E23: 01007-10307 | F23: Z7 Zagreb-sjever | G23: S356 | H23: S356 | J23: 712146S | K23: 0100/712146S | M23: Zagreb-Heinzelova | N23: Z. 19.08.2019. do ? 12.2019. (kapitalna rekonstrukcija - KDR - cca 120 dana) | O23: =COUNTIF(P23:AA23,"NE") -> 5 | P23: DA | Q23: DA | R23: DA | S23: DA | T23: DA | U23: DA | V23: DA | W23: NE | X23: NE | Y23: NE | Z23: NE | AA23: NE | AB23: =COUNTIF(AC23:AN23,"NE") -> 0 | AC23: DA | AD23: DA | AE23: DA | AF23: DA | AG23: DA | AH23: DA | AI23: DA | AJ23: DA | AK23: DA | AL23: DA | AM23: DA | AN23: DA | AO23: =COUNTIF(AC23:AM23,"NE") -> 0 | AP23: DA | AQ23: DA | AR23: DA | AS23: DA | AT23: DA | AU23: DA | AV23: DA | AW23: DA | AX23: DA | AY23: DA | AZ23: DA | BA23: DA | BB23: =COUNTIF(AP23:AZ23,"NE") -> 0 | BC23: DA | BD23: DA | BE23: DA | BF23: DA | BG23: DA | BH23: DA | BI23: DA | BJ23: DA | BK23: DA | BL23: DA | BM23: DA | BN23: DA | BO23: =COUNTIF(BC23:BM23,"NE") -> 0 | BP23: DA | BQ23: DA | BR23: DA | BS23: DA | BT23: DA | BU23: DA | BV23: DA | BW23: DA | BX23: DA | BY23: DA | BZ23: DA | CA23: DA
A24: 23 | B24: 1 | C24: 01007-103 | D24: ZAPAD | E24: 01007-10307 | F24: Z7 Zagreb-sjever | G24: S357 | H24: S357 | J24: 712147S | K24: 0100/712147S | M24: Zagreb-Kranjčevićeva | N24: Z. 26.02. do 19.04.2018. (projekt modernizacije - cca 30 dana) | O24: =COUNTIF(P24:AA24,"NE") -> 0 | P24: DA | Q24: DA | R24: DA | S24: DA | T24: DA | U24: DA | V24: DA | W24: DA | X24: DA | Y24: DA | Z24: DA | AA24: DA | AB24: =COUNTIF(AC24:AN24,"NE") -> 3 | AC24: DA | AD24: NE | AE24: NE | AF24: NE | AG24: DA | AH24: DA | AI24: DA | AJ24: DA | AK24: DA | AL24: DA | AM24: DA | AN24: DA | AO24: =COUNTIF(AC24:AM24,"NE") -> 3 | AP24: DA | AQ24: DA | AR24: DA | AS24: DA | AT24: DA | AU24: DA | AV24: DA | AW24: DA | AX24: DA | AY24: DA | AZ24: DA | BA24: DA | BB24: =COUNTIF(AP24:AZ24,"NE") -> 0 | BC24: DA | BD24: DA | BE24: DA | BF24: DA | BG24: DA | BH24: DA | BI24: DA | BJ24: DA | BK24: DA | BL24: DA | BM24: DA | BN24: DA | BO24: =COUNTIF(BC24:BM24,"NE") -> 0 | BP24: DA | BQ24: DA | BR24: DA | BS24: DA | BT24: DA | BU24: DA | BV24: DA | BW24: DA | BX24: DA | BY24: DA | BZ24: DA | CA24: DA
A25: 24 | B25: 1 | C25: 01007-103 | D25: ZAPAD | E25: 01007-10307 | F25: Z7 Zagreb-sjever | G25: S359 | H25: S359 | J25: 712149S | K25: 0100/712149S | M25: Zagreb-Ksaver | N25: 22.07.2019. do 27.08.2019. implementacija FC (cca 35 dana, rad iz kontejnera) | O25: =COUNTIF(P25:AA25,"NE") -> 0 | P25: DA | Q25: DA | R25: DA | S25: DA | T25: DA | U25: DA | V25: DA | W25: DA | X25: DA | Y25: DA | Z25: DA | AA25: DA | AB25: =COUNTIF(AC25:AN25,"NE") -> 0 | AC25: DA | AD25: DA | AE25: DA | AF25: DA | AG25: DA | AH25: DA | AI25: DA | AJ25: DA | AK25: DA | AL25: DA | AM25: DA | AN25: DA | AO25: =COUNTIF(AC25:AM25,"NE") -> 0 | AP25: DA | AQ25: DA | AR25: DA | AS25: DA | AT25: DA | AU25: DA | AV25: DA | AW25: DA | AX25: DA | AY25: DA | AZ25: DA | BA25: DA | BB25: =COUNTIF(AP25:AZ25,"NE") -> 0 | BC25: DA | BD25: DA | BE25: DA | BF25: DA | BG25: DA | BH25: DA | BI25: DA | BJ25: DA | BK25: DA | BL25: DA | BM25: DA | BN25: DA | BO25: =COUNTIF(BC25:BM25,"NE") -> 0 | BP25: DA | BQ25: DA | BR25: DA | BS25: DA | BT25: DA | BU25: DA | BV25: DA | BW25: DA | BX25: DA | BY25: DA | BZ25: DA | CA25: DA
A26: 25 | B26: 1 | C26: 01007-103 | D26: ZAPAD | E26: 01007-10307 | F26: Z7 Zagreb-sjever | G26: S349 | H26: S349 | J26: 712129S | K26: 0100/712129S | M26: Zagreb-Langov trg | N26: Z. 15.03. do 01.05.2018. (implementacija FC - cca 32 dana) | O26: =COUNTIF(P26:AA26,"NE") -> 0 | P26: DA | Q26: DA | R26: DA | S26: DA | T26: DA | U26: DA | V26: DA | W26: DA | X26: DA | Y26: DA | Z26: DA | AA26: DA | AB26: =COUNTIF(AC26:AN26,"NE") -> 3 | AC26: DA | AD26: DA | AE26: NE | AF26: NE | AG26: NE | AH26: DA | AI26: DA | AJ26: DA | AK26: DA | AL26: DA | AM26: DA | AN26: DA | AO26: =COUNTIF(AC26:AM26,"NE") -> 3 | AP26: DA | AQ26: DA | AR26: DA | AS26: DA | AT26: DA | AU26: DA | AV26: DA | AW26: DA | AX26: DA | AY26: DA | AZ26: DA | BA26: DA | BB26: =COUNTIF(AP26:AZ26,"NE") -> 0 | BC26: DA | BD26: DA | BE26: DA | BF26: DA | BG26: DA | BH26: DA | BI26: DA | BJ26: DA | BK26: DA | BL26: DA | BM26: DA | BN26: DA | BO26: =COUNTIF(BC26:BM26,"NE") -> 0 | BP26: DA | BQ26: DA | BR26: DA | BS26: DA | BT26: DA | BU26: DA | BV26: DA | BW26: DA | BX26: DA | BY26: DA | BZ26: DA | CA26: DA
A27: 26 | C27: 01007-103 | D27: ZAPAD | E27: 01007-10307 | F27: Z7 Zagreb-sjever | G27: S349 | H27: C349 | I27: C349 | J27: 712129S | K27: 0100/712129S | M27: Zagreb-Langov trg AB | N27: Z. trajno 01.08.2018.(C+S); O. ? 2018. Fresh corner | O27: =COUNTIF(P27:AA27,"NE") -> 0 | AB27: =COUNTIF(AC27:AN27,"NE") -> 4 | AF27: NE | AG27: NE | AH27: NE | AI27: NE | AO27: =COUNTIF(AC27:AM27,"NE") -> 4 | BB27: =COUNTIF(AP27:AZ27,"NE") -> 0 | BO27: =COUNTIF(BC27:BM27,"NE") -> 0
A28: 27 | B28: 1 | C28: 01007-103 | D28: ZAPAD | E28: 01007-10307 | F28: Z7 Zagreb-sjever | G28: S367 | H28: S367 | J28: 712162S | K28: 0100/712162S | L28: PSUM | M28: Zagreb-Maksimirska-jug | N28: 12.05.2014. primopredaja BP u ruke partnera - PSUM | O28: =COUNTIF(P28:AA28,"NE") -> 0 | P28: DA | Q28: DA | R28: DA | S28: DA | T28: DA | U28: DA | V28: DA | W28: DA | X28: DA | Y28: DA | Z28: DA | AA28: DA | AB28: =COUNTIF(AC28:AN28,"NE") -> 0 | AC28: DA | AD28: DA | AE28: DA | AF28: DA | AG28: DA | AH28: DA | AI28: DA | AJ28: DA | AK28: DA | AL28: DA | AM28: DA | AN28: DA | AO28: =COUNTIF(AC28:AM28,"NE") -> 0 | AP28: DA | AQ28: DA | AR28: DA | AS28: DA | AT28: DA | AU28: DA | AV28: DA | AW28: DA | AX28: DA | AY28: DA | AZ28: DA | BA28: DA | BB28: =COUNTIF(AP28:AZ28,"NE") -> 0 | BC28: DA | BD28: DA | BE28: DA | BF28: DA | BG28: DA | BH28: DA | BI28: DA | BJ28: DA | BK28: DA | BL28: DA | BM28: DA | BN28: DA | BO28: =COUNTIF(BC28:BM28,"NE") -> 0 | BP28: DA | BQ28: DA | BR28: DA | BS28: DA | BT28: DA | BU28: DA | BV28: DA | BW28: DA | BX28: DA | BY28: DA | BZ28: DA | CA28: DA
A29: 28 | B29: 1 | C29: 01007-103 | D29: ZAPAD | E29: 01007-10307 | F29: Z7 Zagreb-sjever | G29: S340 | H29: S340 | J29: 712106S | K29: 0100/712106S | L29: PSUM | M29: Zagreb-Maksimirska-sjever | N29: 28.05.2015. primopredaja BP u ruke partnera - PSUM | O29: =COUNTIF(P29:AA29,"NE") -> 0 | P29: DA | Q29: DA | R29: DA | S29: DA | T29: DA | U29: DA | V29: DA | W29: DA | X29: DA | Y29: DA | Z29: DA | AA29: DA | AB29: =COUNTIF(AC29:AN29,"NE") -> 0 | AC29: DA | AD29: DA | AE29: DA | AF29: DA | AG29: DA | AH29: DA | AI29: DA | AJ29: DA | AK29: DA | AL29: DA | AM29: DA | AN29: DA | AO29: =COUNTIF(AC29:AM29,"NE") -> 0 | AP29: DA | AQ29: DA | AR29: DA | AS29: DA | AT29: DA | AU29: DA | AV29: DA | AW29: DA | AX29: DA | AY29: DA | AZ29: DA | BA29: DA | BB29: =COUNTIF(AP29:AZ29,"NE") -> 0 | BC29: DA | BD29: DA | BE29: DA | BF29: DA | BG29: DA | BH29: DA | BI29: DA | BJ29: DA | BK29: DA | BL29: DA | BM29: DA | BN29: DA | BO29: =COUNTIF(BC29:BM29,"NE") -> 0 | BP29: DA | BQ29: DA | BR29: DA | BS29: DA | BT29: DA | BU29: DA | BV29: DA | BW29: DA | BX29: DA | BY29: DA | BZ29: DA | CA29: DA
A30: 29 | B30: 1 | C30: 01007-103 | D30: ZAPAD | E30: 01007-10307 | F30: Z7 Zagreb-sjever | G30: S344 | H30: S344 | J30: 712124S | K30: 0100/712124S | L30: PSUM | M30: Zagreb-Planinska | N30: 26.03.2015. primopredaja BP u ruke partnera - PSUM | O30: =COUNTIF(P30:AA30,"NE") -> 0 | P30: DA | Q30: DA | R30: DA | S30: DA | T30: DA | U30: DA | V30: DA | W30: DA | X30: DA | Y30: DA | Z30: DA | AA30: DA | AB30: =COUNTIF(AC30:AN30,"NE") -> 0 | AC30: DA | AD30: DA | AE30: DA | AF30: DA | AG30: DA | AH30: DA | AI30: DA | AJ30: DA | AK30: DA | AL30: DA | AM30: DA | AN30: DA | AO30: =COUNTIF(AC30:AM30,"NE") -> 0 | AP30: DA | AQ30: DA | AR30: DA | AS30: DA | AT30: DA | AU30: DA | AV30: DA | AW30: DA | AX30: DA | AY30: DA | AZ30: DA | BA30: DA | BB30: =COUNTIF(AP30:AZ30,"NE") -> 0 | BC30: DA | BD30: DA | BE30: DA | BF30: DA | BG30: DA | BH30: DA | BI30: DA | BJ30: DA | BK30: DA | BL30: DA | BM30: DA | BN30: DA | BO30: =COUNTIF(BC30:BM30,"NE") -> 0 | BP30: DA | BQ30: DA | BR30: DA | BS30: DA | BT30: DA | BU30: DA | BV30: DA | BW30: DA | BX30: DA | BY30: DA | BZ30: DA | CA30: DA
A31: 30 | B31: 1 | C31: 01007-103 | D31: ZAPAD | E31: 01007-10307 | F31: Z7 Zagreb-sjever | G31: S350 | H31: S350 | J31: 712130S | K31: 0100/712130S | M31: Zagreb-Resnik | N31: (07.09.-02.11.2017. projekt modernizacije-FC cca 30 dana) - rad iz kontejnera | O31: =COUNTIF(P31:AA31,"NE") -> 0 | P31: DA | Q31: DA | R31: DA | S31: DA | T31: DA | U31: DA | V31: DA | W31: DA | X31: DA | Y31: DA | Z31: DA | AA31: DA | AB31: =COUNTIF(AC31:AN31,"NE") -> 0 | AC31: DA | AD31: DA | AE31: DA | AF31: DA | AG31: DA | AH31: DA | AI31: DA | AJ31: DA | AK31: DA | AL31: DA | AM31: DA | AN31: DA | AO31: =COUNTIF(AC31:AM31,"NE") -> 0 | AP31: DA | AQ31: DA | AR31: DA | AS31: DA | AT31: DA | AU31: DA | AV31: DA | AW31: DA | AX31: DA | AY31: DA | AZ31: DA | BA31: DA | BB31: =COUNTIF(AP31:AZ31,"NE") -> 0 | BC31: DA | BD31: DA | BE31: DA | BF31: DA | BG31: DA | BH31: DA | BI31: DA | BJ31: DA | BK31: DA | BL31: DA | BM31: DA | BN31: DA | BO31: =COUNTIF(BC31:BM31,"NE") -> 0 | BP31: DA | BQ31: DA | BR31: DA | BS31: DA | BT31: DA | BU31: DA | BV31: DA | BW31: DA | BX31: DA | BY31: DA | BZ31: DA | CA31: DA
A32: 31 | C32: 01007-103 | D32: ZAPAD | E32: 01007-10307 | F32: Z7 Zagreb-sjever | G32: S350 | H32: C350 | I32: C350 | J32: 712130S | K32: 0100/712130S | M32: Zagreb-Resnik AB | N32: Z. trajno 01.08.2018.(C+S); O. 18.12.2017. Fresh corner | O32: =COUNTIF(P32:AA32,"NE") -> 0 | AB32: =COUNTIF(AC32:AN32,"NE") -> 0 | AC32: DA | AD32: DA | AE32: DA | AF32: DA | AG32: DA | AH32: DA | AI32: DA | AO32: =COUNTIF(AC32:AM32,"NE") -> 0 | AY32: NE | AZ32: NE | BA32: NE | BB32: =COUNTIF(AP32:AZ32,"NE") -> 2 | BO32: =COUNTIF(BC32:BM32,"NE") -> 0
A33: 32 | B33: 1 | C33: 01007-103 | D33: ZAPAD | E33: 01007-10307 | F33: Z7 Zagreb-sjever | G33: S354 | H33: S354 | J33: 712143S | K33: 0100/712143S | M33: Zagreb-Trešnjevka | O33: =COUNTIF(P33:AA33,"NE") -> 0 | P33: DA | Q33: DA | R33: DA | S33: DA | T33: DA | U33: DA | V33: DA | W33: DA | X33: DA | Y33: DA | Z33: DA | AA33: DA | AB33: =COUNTIF(AC33:AN33,"NE") -> 0 | AC33: DA | AD33: DA | AE33: DA | AF33: DA | AG33: DA | AH33: DA | AI33: DA | AJ33: DA | AK33: DA | AL33: DA | AM33: DA | AN33: DA | AO33: =COUNTIF(AC33:AM33,"NE") -> 0 | AP33: DA | AQ33: DA | AR33: DA | AS33: DA | AT33: DA | AU33: DA | AV33: DA | AW33: DA | AX33: DA | AY33: DA | AZ33: DA | BA33: DA | BB33: =COUNTIF(AP33:AZ33,"NE") -> 0 | BC33: DA | BD33: DA | BE33: DA | BF33: DA | BG33: DA | BH33: DA | BI33: DA | BJ33: DA | BK33: DA | BL33: DA | BM33: DA | BN33: DA | BO33: =COUNTIF(BC33:BM33,"NE") -> 0 | BP33: DA | BQ33: DA | BR33: DA | BS33: DA | BT33: DA | BU33: DA | BV33: DA | BW33: DA | BX33: DA | BY33: DA | BZ33: DA | CA33: DA
A34: 33 | B34: 1 | C34: 01007-103 | D34: ZAPAD | E34: 01007-10307 | F34: Z7 Zagreb-sjever | G34: S347 | H34: S347 | I34: H347 | J34: 712127S | K34: 0100/712127S | M34: Zagreb-Žitnjak | O34: =COUNTIF(P34:AA34,"NE") -> 0 | P34: DA | Q34: DA | R34: DA | S34: DA | T34: DA | U34: DA | V34: DA | W34: DA | X34: DA | Y34: DA | Z34: DA | AA34: DA | AB34: =COUNTIF(AC34:AN34,"NE") -> 0 | AC34: DA | AD34: DA | AE34: DA | AF34: DA | AG34: DA | AH34: DA | AI34: DA | AJ34: DA | AK34: DA | AL34: DA | AM34: DA | AN34: DA | AO34: =COUNTIF(AC34:AM34,"NE") -> 0 | AP34: DA | AQ34: DA | AR34: DA | AS34: DA | AT34: DA | AU34: DA | AV34: DA | AW34: DA | AX34: DA | AY34: DA | AZ34: DA | BA34: DA | BB34: =COUNTIF(AP34:AZ34,"NE") -> 0 | BC34: DA | BD34: DA | BE34: DA | BF34: DA | BG34: DA | BH34: DA | BI34: DA | BJ34: DA | BK34: DA | BL34: DA | BM34: DA | BN34: DA | BO34: =COUNTIF(BC34:BM34,"NE") -> 0 | BP34: DA | BQ34: DA | BR34: DA | BS34: DA | BT34: DA | BU34: DA | BV34: DA | BW34: DA | BX34: DA | BY34: DA | BZ34: DA | CA34: DA
A35: 34 | B35: 1 | C35: 01007-103 | D35: ZAPAD | E35: 01007-10307 | F35: Z7 Zagreb-sjever | G35: S341 | H35: S341 | J35: 712107S | K35: 0100/712107S | M35: Zagreb-Žitnjak-Badel | O35: =COUNTIF(P35:AA35,"NE") -> 0 | P35: DA | Q35: DA | R35: DA | S35: DA | T35: DA | U35: DA | V35: DA | W35: DA | X35: DA | Y35: DA | Z35: DA | AA35: DA | AB35: =COUNTIF(AC35:AN35,"NE") -> 0 | AC35: DA | AD35: DA | AE35: DA | AF35: DA | AG35: DA | AH35: DA | AI35: DA | AJ35: DA | AK35: DA | AL35: DA | AM35: DA | AN35: DA | AO35: =COUNTIF(AC35:AM35,"NE") -> 0 | AP35: DA | AQ35: DA | AR35: DA | AS35: DA | AT35: DA | AU35: DA | AV35: DA | AW35: DA | AX35: DA | AY35: DA | AZ35: DA | BA35: DA | BB35: =COUNTIF(AP35:AZ35,"NE") -> 0 | BC35: DA | BD35: DA | BE35: DA | BF35: DA | BG35: DA | BH35: DA | BI35: DA | BJ35: DA | BK35: DA | BL35: DA | BM35: DA | BN35: DA | BO35: =COUNTIF(BC35:BM35,"NE") -> 0 | BP35: DA | BQ35: DA | BR35: DA | BS35: DA | BT35: DA | BU35: DA | BV35: DA | BW35: DA | BX35: DA | BY35: DA | BZ35: DA | CA35: DA
A36: 35 | B36: 1 | C36: 01007-102 | D36: ISTOK | E36: 01007-10206 | F36: I6 Varaždin | G36: S285 | H36: S285 | I36: H285 | J36: 714106S | K36: 0100/714106S | M36: Čakovec-Novakova | O36: =COUNTIF(P36:AA36,"NE") -> 0 | P36: DA | Q36: DA | R36: DA | S36: DA | T36: DA | U36: DA | V36: DA | W36: DA | X36: DA | Y36: DA | Z36: DA | AA36: DA | AB36: =COUNTIF(AC36:AN36,"NE") -> 0 | AC36: DA | AD36: DA | AE36: DA | AF36: DA | AG36: DA | AH36: DA | AI36: DA | AJ36: DA | AK36: DA | AL36: DA | AM36: DA | AN36: DA | AO36: =COUNTIF(AC36:AM36,"NE") -> 0 | AP36: DA | AQ36: DA | AR36: DA | AS36: DA | AT36: DA | AU36: DA | AV36: DA | AW36: DA | AX36: DA | AY36: DA | AZ36: DA | BA36: DA | BB36: =COUNTIF(AP36:AZ36,"NE") -> 0 | BC36: DA | BD36: DA | BE36: DA | BF36: DA | BG36: DA | BH36: DA | BI36: DA | BJ36: DA | BK36: DA | BL36: DA | BM36: DA | BN36: DA | BO36: =COUNTIF(BC36:BM36,"NE") -> 0 | BP36: DA | BQ36: DA | BR36: DA | BS36: DA | BT36: DA | BU36: DA | BV36: DA | BW36: DA | BX36: DA | BY36: DA | BZ36: DA | CA36: DA
A37: 36 | B37: 1 | C37: 01007-102 | D37: ISTOK | E37: 01007-10206 | F37: I6 Varaždin | G37: S292 | H37: S292 | J37: 714113S | K37: 0100/714113S | M37: Čakovec-Zrinsko-Frankopanska | N37: 24.04.do 18.06.2018. rad iz kontejnera (implementacija FC - cca 40 dana); | O37: =COUNTIF(P37:AA37,"NE") -> 0 | P37: DA | Q37: DA | R37: DA | S37: DA | T37: DA | U37: DA | V37: DA | W37: DA | X37: DA | Y37: DA | Z37: DA | AA37: DA | AB37: =COUNTIF(AC37:AN37,"NE") -> 0 | AC37: DA | AD37: DA | AE37: DA | AF37: DA | AG37: DA | AH37: DA | AI37: DA | AJ37: DA | AK37: DA | AL37: DA | AM37: DA | AN37: DA | AO37: =COUNTIF(AC37:AM37,"NE") -> 0 | AP37: DA | AQ37: DA | AR37: DA | AS37: DA | AT37: DA | AU37: DA | AV37: DA | AW37: DA | AX37: DA | AY37: DA | AZ37: DA | BA37: DA | BB37: =COUNTIF(AP37:AZ37,"NE") -> 0 | BC37: DA | BD37: DA | BE37: DA | BF37: DA | BG37: DA | BH37: DA | BI37: DA | BJ37: DA | BK37: DA | BL37: DA | BM37: DA | BN37: DA | BO37: =COUNTIF(BC37:BM37,"NE") -> 0 | BP37: DA | BQ37: DA | BR37: DA | BS37: DA | BT37: DA | BU37: DA | BV37: DA | BW37: DA | BX37: DA | BY37: DA | BZ37: DA | CA37: DA
A38: 37 | C38: 01007-102 | D38: ISTOK | E38: 01007-10206 | F38: I6 Varaždin | G38: S292 | H38: C292 | I38: C292 | J38: 714113S | K38: 0100/714113S | M38: Čakovec-Zrinsko-Frankopanska AB | N38: Z. trajno 01.08.2018.(C+S); O. 01.08.2018. implementacija FC; (Z. 31.08.2012.-brisana OJ 50001643; Z. 09.08.2012 modernizacija BP | O38: =COUNTIF(P38:AA38,"NE") -> 0 | AB38: =COUNTIF(AC38:AN38,"NE") -> 3 | AG38: NE | AH38: NE | AI38: NE | AO38: =COUNTIF(AC38:AM38,"NE") -> 3 | BB38: =COUNTIF(AP38:AZ38,"NE") -> 0 | BO38: =COUNTIF(BC38:BM38,"NE") -> 0
A39: 38 | B39: 1 | C39: 01007-102 | D39: ISTOK | E39: 01007-10206 | F39: I6 Varaždin | G39: S282 | H39: S282 | J39: 714103S | K39: 0100/714103S | M39: Donja Dubrava | O39: =COUNTIF(P39:AA39,"NE") -> 0 | P39: DA | Q39: DA | R39: DA | S39: DA | T39: DA | U39: DA | V39: DA | W39: DA | X39: DA | Y39: DA | Z39: DA | AA39: DA | AB39: =COUNTIF(AC39:AN39,"NE") -> 0 | AC39: DA | AD39: DA | AE39: DA | AF39: DA | AG39: DA | AH39: DA | AI39: DA | AJ39: DA | AK39: DA | AL39: DA | AM39: DA | AN39: DA | AO39: =COUNTIF(AC39:AM39,"NE") -> 0 | AP39: DA | AQ39: DA | AR39: DA | AS39: DA | AT39: DA | AU39: DA | AV39: DA | AW39: DA | AX39: DA | AY39: DA | AZ39: DA | BA39: DA | BB39: =COUNTIF(AP39:AZ39,"NE") -> 0 | BC39: DA | BD39: DA | BE39: DA | BF39: DA | BG39: DA | BH39: DA | BI39: DA | BJ39: DA | BK39: DA | BL39: DA | BM39: DA | BN39: DA | BO39: =COUNTIF(BC39:BM39,"NE") -> 0 | BP39: DA | BQ39: DA | BR39: DA | BS39: DA | BT39: DA | BU39: DA | BV39: DA | BW39: DA | BX39: DA | BY39: DA | BZ39: DA | CA39: DA
A40: 39 | B40: 1 | C40: 01007-102 | D40: ISTOK | E40: 01007-10206 | F40: I6 Varaždin | G40: S289 | H40: S289 | J40: 714110S | K40: 0100/714110S | M40: Goričan | N40: 12.11.2019. do ?.12.2019. implementacija FC (cca 28 dana, rad iz kontejnera) | O40: =COUNTIF(P40:AA40,"NE") -> 0 | P40: DA | Q40: DA | R40: DA | S40: DA | T40: DA | U40: DA | V40: DA | W40: DA | X40: DA | Y40: DA | Z40: DA | AA40: DA | AB40: =COUNTIF(AC40:AN40,"NE") -> 0 | AC40: DA | AD40: DA | AE40: DA | AF40: DA | AG40: DA | AH40: DA | AI40: DA | AJ40: DA | AK40: DA | AL40: DA | AM40: DA | AN40: DA | AO40: =COUNTIF(AC40:AM40,"NE") -> 0 | AP40: DA | AQ40: DA | AR40: DA | AS40: DA | AT40: DA | AU40: DA | AV40: DA | AW40: DA | AX40: DA | AY40: DA | AZ40: DA | BA40: DA | BB40: =COUNTIF(AP40:AZ40,"NE") -> 0 | BC40: DA | BD40: DA | BE40: DA | BF40: DA | BG40: DA | BH40: DA | BI40: DA | BJ40: DA | BK40: DA | BL40: DA | BM40: DA | BN40: DA | BO40: =COUNTIF(BC40:BM40,"NE") -> 0 | BP40: DA | BQ40: DA | BR40: DA | BS40: DA | BT40: DA | BU40: DA | BV40: DA | BW40: DA | BX40: DA | BY40: DA | BZ40: DA | CA40: DA
A41: 40 | B41: 1 | C41: 01007-102 | D41: ISTOK | E41: 01007-10206 | F41: I6 Varaždin | G41: S287 | H41: S287 | J41: 714108S | K41: 0100/714108S | M41: Ivanec | O41: =COUNTIF(P41:AA41,"NE") -> 0 | P41: DA | Q41: DA | R41: DA | S41: DA | T41: DA | U41: DA | V41: DA | W41: DA | X41: DA | Y41: DA | Z41: DA | AA41: DA | AB41: =COUNTIF(AC41:AN41,"NE") -> 0 | AC41: DA | AD41: DA | AE41: DA | AF41: DA | AG41: DA | AH41: DA | AI41: DA | AJ41: DA | AK41: DA | AL41: DA | AM41: DA | AN41: DA | AO41: =COUNTIF(AC41:AM41,"NE") -> 0 | AP41: DA | AQ41: DA | AR41: DA | AS41: DA | AT41: DA | AU41: DA | AV41: DA | AW41: DA | AX41: DA | AY41: DA | AZ41: DA | BA41: DA | BB41: =COUNTIF(AP41:AZ41,"NE") -> 0 | BC41: DA | BD41: DA | BE41: DA | BF41: DA | BG41: DA | BH41: DA | BI41: DA | BJ41: DA | BK41: DA | BL41: DA | BM41: DA | BN41: DA | BO41: =COUNTIF(BC41:BM41,"NE") -> 0 | BP41: DA | BQ41: DA | BR41: DA | BS41: DA | BT41: DA | BU41: DA | BV41: DA | BW41: DA | BX41: DA | BY41: DA | BZ41: DA | CA41: DA
A42: 41 | B42: 1 | C42: 01007-102 | D42: ISTOK | E42: 01007-10206 | F42: I6 Varaždin | G42: S281 | H42: S281 | J42: 714102S | K42: 0100/714102S | M42: Lepoglava | N42: Z. 02.05. do 02.07.2018. (projekt održavanja cca 40 dana) | O42: =COUNTIF(P42:AA42,"NE") -> 0 | P42: DA | Q42: DA | R42: DA | S42: DA | T42: DA | U42: DA | V42: DA | W42: DA | X42: DA | Y42: DA | Z42: DA | AA42: DA | AB42: =COUNTIF(AC42:AN42,"NE") -> 3 | AC42: DA | AD42: DA | AE42: DA | AF42: DA | AG42: NE | AH42: NE | AI42: NE | AJ42: DA | AK42: DA | AL42: DA | AM42: DA | AN42: DA | AO42: =COUNTIF(AC42:AM42,"NE") -> 3 | AP42: DA | AQ42: DA | AR42: DA | AS42: DA | AT42: DA | AU42: DA | AV42: DA | AW42: DA | AX42: DA | AY42: DA | AZ42: DA | BA42: DA | BB42: =COUNTIF(AP42:AZ42,"NE") -> 0 | BC42: DA | BD42: DA | BE42: DA | BF42: DA | BG42: DA | BH42: DA | BI42: DA | BJ42: DA | BK42: DA | BL42: DA | BM42: DA | BN42: DA | BO42: =COUNTIF(BC42:BM42,"NE") -> 0 | BP42: DA | BQ42: DA | BR42: DA | BS42: DA | BT42: DA | BU42: DA | BV42: DA | BW42: DA | BX42: DA | BY42: DA | BZ42: DA | CA42: DA
A43: 42 | B43: 1 | C43: 01007-102 | D43: ISTOK | E43: 01007-10206 | F43: I6 Varaždin | G43: S286 | H43: S286 | J43: 714107S | K43: 0100/714107S | M43: Ludbreg | N43: Z. 10.04. do 14.10.2018. (kapitalna rekonstrukcija - KDR - cca 140 dana) | O43: =COUNTIF(P43:AA43,"NE") -> 0 | P43: DA | Q43: DA | R43: DA | S43: DA | T43: DA | U43: DA | V43: DA | W43: DA | X43: DA | Y43: DA | Z43: DA | AA43: DA | AB43: =COUNTIF(AC43:AN43,"NE") -> 7 | AC43: DA | AD43: DA | AE43: DA | AF43: NE | AG43: NE | AH43: NE | AI43: NE | AJ43: NE | AK43: NE | AL43: NE | AM43: DA | AN43: DA | AO43: =COUNTIF(AC43:AM43,"NE") -> 7 | AP43: DA | AQ43: DA | AR43: DA | AS43: DA | AT43: DA | AU43: DA | AV43: DA | AW43: DA | AX43: DA | AY43: DA | AZ43: DA | BA43: DA | BB43: =COUNTIF(AP43:AZ43,"NE") -> 0 | BC43: DA | BD43: DA | BE43: DA | BF43: DA | BG43: DA | BH43: DA | BI43: DA | BJ43: DA | BK43: DA | BL43: DA | BM43: DA | BN43: DA | BO43: =COUNTIF(BC43:BM43,"NE") -> 0 | BP43: DA | BQ43: DA | BR43: DA | BS43: DA | BT43: DA | BU43: DA | BV43: DA | BW43: DA | BX43: DA | BY43: DA | BZ43: DA | CA43: DA
A44: 43 | B44: 1 | C44: 01007-102 | D44: ISTOK | E44: 01007-10206 | F44: I6 Varaždin | G44: S296 | H44: S296 | J44: 714117S | K44: 0100/714117S | M44: Mursko Središće | O44: =COUNTIF(P44:AA44,"NE") -> 0 | P44: DA | Q44: DA | R44: DA | S44: DA | T44: DA | U44: DA | V44: DA | W44: DA | X44: DA | Y44: DA | Z44: DA | AA44: DA | AB44: =COUNTIF(AC44:AN44,"NE") -> 0 | AC44: DA | AD44: DA | AE44: DA | AF44: DA | AG44: DA | AH44: DA | AI44: DA | AJ44: DA | AK44: DA | AL44: DA | AM44: DA | AN44: DA | AO44: =COUNTIF(AC44:AM44,"NE") -> 0 | AP44: DA | AQ44: DA | AR44: DA | AS44: DA | AT44: DA | AU44: DA | AV44: DA | AW44: DA | AX44: DA | AY44: DA | AZ44: DA | BA44: DA | BB44: =COUNTIF(AP44:AZ44,"NE") -> 0 | BC44: DA | BD44: DA | BE44: DA | BF44: DA | BG44: DA | BH44: DA | BI44: DA | BJ44: DA | BK44: DA | BL44: DA | BM44: DA | BN44: DA | BO44: =COUNTIF(BC44:BM44,"NE") -> 0 | BP44: DA | BQ44: DA | BR44: DA | BS44: DA | BT44: DA | BU44: DA | BV44: DA | BW44: DA | BX44: DA | BY44: DA | BZ44: DA | CA44: DA
A45: 44 | B45: 1 | C45: 01007-102 | D45: ISTOK | E45: 01007-10206 | F45: I6 Varaždin | G45: S290 | H45: S290 | J45: 714111S | K45: 0100/714111S | M45: Novi Marof | O45: =COUNTIF(P45:AA45,"NE") -> 0 | P45: DA | Q45: DA | R45: DA | S45: DA | T45: DA | U45: DA | V45: DA | W45: DA | X45: DA | Y45: DA | Z45: DA | AA45: DA | AB45: =COUNTIF(AC45:AN45,"NE") -> 0 | AC45: DA | AD45: DA | AE45: DA | AF45: DA | AG45: DA | AH45: DA | AI45: DA | AJ45: DA | AK45: DA | AL45: DA | AM45: DA | AN45: DA | AO45: =COUNTIF(AC45:AM45,"NE") -> 0 | AP45: DA | AQ45: DA | AR45: DA | AS45: DA | AT45: DA | AU45: DA | AV45: DA | AW45: DA | AX45: DA | AY45: DA | AZ45: DA | BA45: DA | BB45: =COUNTIF(AP45:AZ45,"NE") -> 0 | BC45: DA | BD45: DA | BE45: DA | BF45: DA | BG45: DA | BH45: DA | BI45: DA | BJ45: DA | BK45: DA | BL45: DA | BM45: DA | BN45: DA | BO45: =COUNTIF(BC45:BM45,"NE") -> 0 | BP45: DA | BQ45: DA | BR45: DA | BS45: DA | BT45: DA | BU45: DA | BV45: DA | BW45: DA | BX45: DA | BY45: DA | BZ45: DA | CA45: DA
A46: 45 | B46: 1 | C46: 01007-102 | D46: ISTOK | E46: 01007-10206 | F46: I6 Varaždin | G46: S297 | H46: S297 | J46: 714118S | K46: 0100/714118S | M46: Ljubešćica-istok | N46: promj.naziva (Novi Marof-istok) 1.9.2015. | O46: =COUNTIF(P46:AA46,"NE") -> 0 | P46: DA | Q46: DA | R46: DA | S46: DA | T46: DA | U46: DA | V46: DA | W46: DA | X46: DA | Y46: DA | Z46: DA | AA46: DA | AB46: =COUNTIF(AC46:AN46,"NE") -> 0 | AC46: DA | AD46: DA | AE46: DA | AF46: DA | AG46: DA | AH46: DA | AI46: DA | AJ46: DA | AK46: DA | AL46: DA | AM46: DA | AN46: DA | AO46: =COUNTIF(AC46:AM46,"NE") -> 0 | AP46: DA | AQ46: DA | AR46: DA | AS46: DA | AT46: DA | AU46: DA | AV46: DA | AW46: DA | AX46: DA | AY46: DA | AZ46: DA | BA46: DA | BB46: =COUNTIF(AP46:AZ46,"NE") -> 0 | BC46: DA | BD46: DA | BE46: DA | BF46: DA | BG46: DA | BH46: DA | BI46: DA | BJ46: DA | BK46: DA | BL46: DA | BM46: DA | BN46: DA | BO46: =COUNTIF(BC46:BM46,"NE") -> 0 | BP46: DA | BQ46: DA | BR46: DA | BS46: DA | BT46: DA | BU46: DA | BV46: DA | BW46: DA | BX46: DA | BY46: DA | BZ46: DA | CA46: DA
A47: 46 | C47: 01007-102 | D47: ISTOK | E47: 01007-10206 | F47: I6 Varaždin | G47: S297 | H47: C297 | I47: C297 | J47: 714118S | K47: 0100/714118S | M47: Ljubešćica-istok AB | N47: Z. trajno 15.10.2018.(C+S); 31.01.2016.-brisana OJ 50001644; promj.naziva (Novi Marof-istok AB) 1.9.2015.; O. 27.11.2004. | O47: =COUNTIF(P47:AA47,"NE") -> 0 | AB47: =COUNTIF(AC47:AN47,"NE") -> 1 | AC47: DA | AD47: DA | AE47: DA | AF47: DA | AG47: DA | AH47: DA | AI47: DA | AJ47: DA | AK47: NE | AO47: =COUNTIF(AC47:AM47,"NE") -> 1 | AP47: DA | AQ47: DA | AR47: DA | AS47: DA | AT47: DA | AU47: DA | AV47: DA | AW47: DA | AX47: DA | AY47: DA | AZ47: DA | BA47: DA | BB47: =COUNTIF(AP47:AZ47,"NE") -> 0 | BC47: DA | BD47: DA | BE47: DA | BF47: NE | BG47: NE | BH47: NE | BI47: DA | BJ47: DA | BK47: DA | BL47: DA | BM47: DA | BN47: DA | BO47: =COUNTIF(BC47:BM47,"NE") -> 3 | BP47: DA | BQ47: DA | BR47: DA | BS47: DA | BT47: DA | BU47: DA | BV47: DA | BW47: DA | BX47: DA | BY47: DA | BZ47: DA | CA47: DA
A48: 47 | B48: 1 | C48: 01007-102 | D48: ISTOK | E48: 01007-10206 | F48: I6 Varaždin | G48: S298 | H48: S298 | J48: 714119S | K48: 0100/714119S | M48: Ljubešćica-zapad | N48: promj.naziva (Novi Marof-zapad) 1.9.2015. | O48: =COUNTIF(P48:AA48,"NE") -> 0 | P48: DA | Q48: DA | R48: DA | S48: DA | T48: DA | U48: DA | V48: DA | W48: DA | X48: DA | Y48: DA | Z48: DA | AA48: DA | AB48: =COUNTIF(AC48:AN48,"NE") -> 0 | AC48: DA | AD48: DA | AE48: DA | AF48: DA | AG48: DA | AH48: DA | AI48: DA | AJ48: DA | AK48: DA | AL48: DA | AM48: DA | AN48: DA | AO48: =COUNTIF(AC48:AM48,"NE") -> 0 | AP48: DA | AQ48: DA | AR48: DA | AS48: DA | AT48: DA | AU48: DA | AV48: DA | AW48: DA | AX48: DA | AY48: DA | AZ48: DA | BA48: DA | BB48: =COUNTIF(AP48:AZ48,"NE") -> 0 | BC48: DA | BD48: DA | BE48: DA | BF48: DA | BG48: DA | BH48: DA | BI48: DA | BJ48: DA | BK48: DA | BL48: DA | BM48: DA | BN48: DA | BO48: =COUNTIF(BC48:BM48,"NE") -> 0 | BP48: DA | BQ48: DA | BR48: DA | BS48: DA | BT48: DA | BU48: DA | BV48: DA | BW48: DA | BX48: DA | BY48: DA | BZ48: DA | CA48: DA
A49: 48 | C49: 01007-102 | D49: ISTOK | E49: 01007-10206 | F49: I6 Varaždin | G49: S298 | H49: C298 | I49: C298 | J49: 714119S | K49: 0100/714119S | M49: Ljubešćica-zapad AB | N49: Z. trajno 15.10.2018.(C+S); 31.01.2016.-brisana OJ 50001645; promj.naziva (Novi Marof-zapad AB) 1.9.2015.; O. 27.11.2004. | O49: =COUNTIF(P49:AA49,"NE") -> 0 | AB49: =COUNTIF(AC49:AN49,"NE") -> 1 | AC49: DA | AD49: DA | AE49: DA | AF49: DA | AG49: DA | AH49: DA | AI49: DA | AJ49: DA | AK49: NE | AO49: =COUNTIF(AC49:AM49,"NE") -> 1 | AP49: DA | AQ49: DA | AR49: DA | AS49: DA | AT49: DA | AU49: DA | AV49: DA | AW49: DA | AX49: DA | AY49: DA | AZ49: DA | BA49: DA | BB49: =COUNTIF(AP49:AZ49,"NE") -> 0 | BC49: DA | BD49: NE | BE49: NE | BF49: NE | BG49: NE | BH49: DA | BI49: DA | BJ49: DA | BK49: DA | BL49: DA | BM49: DA | BN49: DA | BO49: =COUNTIF(BC49:BM49,"NE") -> 4 | BP49: DA | BQ49: DA | BR49: DA | BS49: DA | BT49: DA | BU49: DA | BV49: DA | BW49: DA | BX49: DA | BY49: DA | BZ49: DA | CA49: DA
A50: 49 | B50: 1 | C50: 01007-102 | D50: ISTOK | E50: 01007-10206 | F50: I6 Varaždin | G50: S291 | H50: S291 | I50: H291 | J50: 714112S | K50: 0100/714112S | M50: Prelog | O50: =COUNTIF(P50:AA50,"NE") -> 0 | P50: DA | Q50: DA | R50: DA | S50: DA | T50: DA | U50: DA | V50: DA | W50: DA | X50: DA | Y50: DA | Z50: DA | AA50: DA | AB50: =COUNTIF(AC50:AN50,"NE") -> 0 | AC50: DA | AD50: DA | AE50: DA | AF50: DA | AG50: DA | AH50: DA | AI50: DA | AJ50: DA | AK50: DA | AL50: DA | AM50: DA | AN50: DA | AO50: =COUNTIF(AC50:AM50,"NE") -> 0 | AP50: DA | AQ50: DA | AR50: DA | AS50: DA | AT50: DA | AU50: DA | AV50: DA | AW50: DA | AX50: DA | AY50: DA | AZ50: DA | BA50: DA | BB50: =COUNTIF(AP50:AZ50,"NE") -> 0 | BC50: DA | BD50: DA | BE50: DA | BF50: DA | BG50: DA | BH50: DA | BI50: DA | BJ50: DA | BK50: DA | BL50: DA | BM50: DA | BN50: DA | BO50: =COUNTIF(BC50:BM50,"NE") -> 0 | BP50: DA | BQ50: DA | BR50: DA | BS50: DA | BT50: DA | BU50: DA | BV50: DA | BW50: DA | BX50: DA | BY50: DA | BZ50: DA | CA50: DA
A51: 50 | B51: 1 | C51: 01007-102 | D51: ISTOK | E51: 01007-10206 | F51: I6 Varaždin | G51: S294 | H51: S294 | I51: H294 | J51: 714115S | K51: 0100/714115S | M51: Štrigova | O51: =COUNTIF(P51:AA51,"NE") -> 0 | P51: DA | Q51: DA | R51: DA | S51: DA | T51: DA | U51: DA | V51: DA | W51: DA | X51: DA | Y51: DA | Z51: DA | AA51: DA | AB51: =COUNTIF(AC51:AN51,"NE") -> 0 | AC51: DA | AD51: DA | AE51: DA | AF51: DA | AG51: DA | AH51: DA | AI51: DA | AJ51: DA | AK51: DA | AL51: DA | AM51: DA | AN51: DA | AO51: =COUNTIF(AC51:AM51,"NE") -> 0 | AP51: DA | AQ51: DA | AR51: DA | AS51: DA | AT51: DA | AU51: DA | AV51: DA | AW51: DA | AX51: DA | AY51: DA | AZ51: DA | BA51: DA | BB51: =COUNTIF(AP51:AZ51,"NE") -> 0 | BC51: DA | BD51: DA | BE51: DA | BF51: DA | BG51: DA | BH51: DA | BI51: DA | BJ51: DA | BK51: DA | BL51: DA | BM51: DA | BN51: DA | BO51: =COUNTIF(BC51:BM51,"NE") -> 0 | BP51: DA | BQ51: DA | BR51: DA | BS51: DA | BT51: DA | BU51: DA | BV51: DA | BW51: DA | BX51: DA | BY51: DA | BZ51: DA | CA51: DA
A52: 51 | B52: 1 | C52: 01007-102 | D52: ISTOK | E52: 01007-10206 | F52: I6 Varaždin | G52: S288 | H52: S288 | J52: 714109S | K52: 0100/714109S | M52: Varaždin Breg | O52: =COUNTIF(P52:AA52,"NE") -> 0 | P52: DA | Q52: DA | R52: DA | S52: DA | T52: DA | U52: DA | V52: DA | W52: DA | X52: DA | Y52: DA | Z52: DA | AA52: DA | AB52: =COUNTIF(AC52:AN52,"NE") -> 0 | AC52: DA | AD52: DA | AE52: DA | AF52: DA | AG52: DA | AH52: DA | AI52: DA | AJ52: DA | AK52: DA | AL52: DA | AM52: DA | AN52: DA | AO52: =COUNTIF(AC52:AM52,"NE") -> 0 | AP52: DA | AQ52: DA | AR52: DA | AS52: DA | AT52: DA | AU52: DA | AV52: DA | AW52: DA | AX52: DA | AY52: DA | AZ52: DA | BA52: DA | BB52: =COUNTIF(AP52:AZ52,"NE") -> 0 | BC52: DA | BD52: DA | BE52: DA | BF52: DA | BG52: DA | BH52: DA | BI52: DA | BJ52: DA | BK52: DA | BL52: DA | BM52: DA | BN52: DA | BO52: =COUNTIF(BC52:BM52,"NE") -> 0 | BP52: DA | BQ52: DA | BR52: DA | BS52: DA | BT52: DA | BU52: DA | BV52: DA | BW52: DA | BX52: DA | BY52: DA | BZ52: DA | CA52: DA
A53: 52 | B53: 1 | C53: 01007-102 | D53: ISTOK | E53: 01007-10206 | F53: I6 Varaždin | G53: S284 | H53: S284 | I53: H284 | J53: 714105S | K53: 0100/714105S | L53: PSUM | M53: Varaždin-Krležina | N53: 04.09. do 25.10.2018. rad iz kontejnera (implementacija FC - cca 45 dana); 17.12.2015. primopredaja MPM u ruke partnera - PSUM | O53: =COUNTIF(P53:AA53,"NE") -> 0 | P53: DA | Q53: DA | R53: DA | S53: DA | T53: DA | U53: DA | V53: DA | W53: DA | X53: DA | Y53: DA | Z53: DA | AA53: DA | AB53: =COUNTIF(AC53:AN53,"NE") -> 0 | AC53: DA | AD53: DA | AE53: DA | AF53: DA | AG53: DA | AH53: DA | AI53: DA | AJ53: DA | AK53: DA | AL53: DA | AM53: DA | AN53: DA | AO53: =COUNTIF(AC53:AM53,"NE") -> 0 | AP53: DA | AQ53: DA | AR53: DA | AS53: DA | AT53: DA | AU53: DA | AV53: DA | AW53: DA | AX53: DA | AY53: DA | AZ53: DA | BA53: DA | BB53: =COUNTIF(AP53:AZ53,"NE") -> 0 | BC53: DA | BD53: DA | BE53: DA | BF53: DA | BG53: DA | BH53: DA | BI53: DA | BJ53: DA | BK53: DA | BL53: DA | BM53: DA | BN53: DA | BO53: =COUNTIF(BC53:BM53,"NE") -> 0 | BP53: DA | BQ53: DA | BR53: NE | BS53: NE | BT53: NE | BU53: NE | BV53: NE | BW53: NE | BX53: DA | BY53: DA | BZ53: DA | CA53: NE
A54: 53 | B54: 1 | C54: 01007-102 | D54: ISTOK | E54: 01007-10206 | F54: I6 Varaždin | G54: S295 | H54: S295 | J54: 714116S | K54: 0100/714116S | L54: PSUM | M54: Varaždin-Međimurska | N54: 05.11.2015. primopredaja BP u ruke partnera - PSUM | O54: =COUNTIF(P54:AA54,"NE") -> 0 | P54: DA | Q54: DA | R54: DA | S54: DA | T54: DA | U54: DA | V54: DA | W54: DA | X54: DA | Y54: DA | Z54: DA | AA54: DA | AB54: =COUNTIF(AC54:AN54,"NE") -> 0 | AC54: DA | AD54: DA | AE54: DA | AF54: DA | AG54: DA | AH54: DA | AI54: DA | AJ54: DA | AK54: DA | AL54: DA | AM54: DA | AN54: DA | AO54: =COUNTIF(AC54:AM54,"NE") -> 0 | AP54: DA | AQ54: DA | AR54: DA | AS54: DA | AT54: DA | AU54: DA | AV54: DA | AW54: DA | AX54: DA | AY54: DA | AZ54: DA | BA54: DA | BB54: =COUNTIF(AP54:AZ54,"NE") -> 0 | BC54: DA | BD54: DA | BE54: DA | BF54: DA | BG54: DA | BH54: DA | BI54: DA | BJ54: DA | BK54: DA | BL54: DA | BM54: DA | BN54: DA | BO54: =COUNTIF(BC54:BM54,"NE") -> 0 | BP54: DA | BQ54: DA | BR54: DA | BS54: DA | BT54: DA | BU54: DA | BV54: DA | BW54: DA | BX54: DA | BY54: DA | BZ54: NE | CA54: DA
A55: 54 | B55: 1 | C55: 01007-102 | D55: ISTOK | E55: 01007-10206 | F55: I6 Varaždin | G55: S280 | H55: S280 | J55: 714101S | K55: 0100/714101S | M55: Varaždinske Toplice | O55: =COUNTIF(P55:AA55,"NE") -> 0 | P55: DA | Q55: DA | R55: DA | S55: DA | T55: DA | U55: DA | V55: DA | W55: DA | X55: DA | Y55: DA | Z55: DA | AA55: DA | AB55: =COUNTIF(AC55:AN55,"NE") -> 0 | AC55: DA | AD55: DA | AE55: DA | AF55: DA | AG55: DA | AH55: DA | AI55: DA | AJ55: DA | AK55: DA | AL55: DA | AM55: DA | AN55: DA | AO55: =COUNTIF(AC55:AM55,"NE") -> 0 | AP55: DA | AQ55: DA | AR55: DA | AS55: DA | AT55: DA | AU55: DA | AV55: DA | AW55: DA | AX55: DA | AY55: DA | AZ55: DA | BA55: DA | BB55: =COUNTIF(AP55:AZ55,"NE") -> 0 | BC55: DA | BD55: DA | BE55: DA | BF55: DA | BG55: DA | BH55: DA | BI55: DA | BJ55: DA | BK55: DA | BL55: DA | BM55: DA | BN55: DA | BO55: =COUNTIF(BC55:BM55,"NE") -> 0 | BP55: DA | BQ55: DA | BR55: DA | BS55: DA | BT55: DA | BU55: DA | BV55: DA | BW55: DA | BX55: DA | BY55: DA | BZ55: DA | CA55: DA
A56: 55 | B56: 1 | C56: 01007-102 | D56: ISTOK | E56: 01007-10206 | F56: I6 Varaždin | G56: S293 | H56: S293 | J56: 714114S | K56: 0100/714114S | M56: Vidovec | O56: =COUNTIF(P56:AA56,"NE") -> 0 | P56: DA | Q56: DA | R56: DA | S56: DA | T56: DA | U56: DA | V56: DA | W56: DA | X56: DA | Y56: DA | Z56: DA | AA56: DA | AB56: =COUNTIF(AC56:AN56,"NE") -> 0 | AC56: DA | AD56: DA | AE56: DA | AF56: DA | AG56: DA | AH56: DA | AI56: DA | AJ56: DA | AK56: DA | AL56: DA | AM56: DA | AN56: DA | AO56: =COUNTIF(AC56:AM56,"NE") -> 0 | AP56: DA | AQ56: DA | AR56: DA | AS56: DA | AT56: DA | AU56: DA | AV56: DA | AW56: DA | AX56: DA | AY56: DA | AZ56: DA | BA56: DA | BB56: =COUNTIF(AP56:AZ56,"NE") -> 0 | BC56: DA | BD56: DA | BE56: DA | BF56: DA | BG56: DA | BH56: DA | BI56: DA | BJ56: DA | BK56: DA | BL56: DA | BM56: DA | BN56: DA | BO56: =COUNTIF(BC56:BM56,"NE") -> 0 | BP56: DA | BQ56: DA | BR56: DA | BS56: DA | BT56: DA | BU56: DA | BV56: DA | BW56: DA | BX56: DA | BY56: DA | BZ56: DA | CA56: DA
A57: 56 | B57: 1 | C57: 01007-102 | D57: ISTOK | E57: 01007-10206 | F57: I6 Varaždin | G57: S283 | H57: S283 | J57: 714104S | K57: 0100/714104S | M57: Vratno | O57: =COUNTIF(P57:AA57,"NE") -> 0 | P57: DA | Q57: DA | R57: DA | S57: DA | T57: DA | U57: DA | V57: DA | W57: DA | X57: DA | Y57: DA | Z57: DA | AA57: DA | AB57: =COUNTIF(AC57:AN57,"NE") -> 0 | AC57: DA | AD57: DA | AE57: DA | AF57: DA | AG57: DA | AH57: DA | AI57: DA | AJ57: DA | AK57: DA | AL57: DA | AM57: DA | AN57: DA | AO57: =COUNTIF(AC57:AM57,"NE") -> 0 | AP57: DA | AQ57: DA | AR57: DA | AS57: DA | AT57: DA | AU57: DA | AV57: DA | AW57: DA | AX57: DA | AY57: DA | AZ57: DA | BA57: DA | BB57: =COUNTIF(AP57:AZ57,"NE") -> 0 | BC57: DA | BD57: DA | BE57: DA | BF57: DA | BG57: DA | BH57: DA | BI57: DA | BJ57: DA | BK57: DA | BL57: DA | BM57: DA | BN57: DA | BO57: =COUNTIF(BC57:BM57,"NE") -> 0 | BP57: DA | BQ57: DA | BR57: DA | BS57: DA | BT57: DA | BU57: DA | BV57: DA | BW57: DA | BX57: DA | BY57: DA | BZ57: DA | CA57: DA
A58: 57 | B58: 1 | C58: 01007-103 | D58: ZAPAD | E58: 01007-10304 | F58: Z4 Krapina | G58: S376 | H58: S376 | J58: 712110S | K58: 0100/712110S | L58: PSUM | M58: Bedekovčina | N58: 19.03.2015. primopredaja BP u ruke partnera - PSUM | O58: =COUNTIF(P58:AA58,"NE") -> 0 | P58: DA | Q58: DA | R58: DA | S58: DA | T58: DA | U58: DA | V58: DA | W58: DA | X58: DA | Y58: DA | Z58: DA | AA58: DA | AB58: =COUNTIF(AC58:AN58,"NE") -> 0 | AC58: DA | AD58: DA | AE58: DA | AF58: DA | AG58: DA | AH58: DA | AI58: DA | AJ58: DA | AK58: DA | AL58: DA | AM58: DA | AN58: DA | AO58: =COUNTIF(AC58:AM58,"NE") -> 0 | AP58: DA | AQ58: DA | AR58: DA | AS58: DA | AT58: DA | AU58: DA | AV58: DA | AW58: DA | AX58: DA | AY58: DA | AZ58: DA | BA58: DA | BB58: =COUNTIF(AP58:AZ58,"NE") -> 0 | BC58: DA | BD58: DA | BE58: DA | BF58: DA | BG58: DA | BH58: DA | BI58: DA | BJ58: DA | BK58: DA | BL58: DA | BM58: DA | BN58: DA | BO58: =COUNTIF(BC58:BM58,"NE") -> 0 | BP58: DA | BQ58: DA | BR58: DA | BS58: DA | BT58: DA | BU58: DA | BV58: DA | BW58: DA | BX58: DA | BY58: DA | BZ58: DA | CA58: DA
A59: 58 | B59: 1 | C59: 01007-103 | D59: ZAPAD | E59: 01007-10304 | F59: Z4 Krapina | G59: S377 | H59: S377 | J59: 712111S | K59: 0100/712111S | L59: PSUM | M59: Donja Stubica | N59: 29.04.2014. primopredaja BP u ruke partnera - PSUM | O59: =COUNTIF(P59:AA59,"NE") -> 0 | P59: DA | Q59: DA | R59: DA | S59: DA | T59: DA | U59: DA | V59: DA | W59: DA | X59: DA | Y59: DA | Z59: DA | AA59: DA | AB59: =COUNTIF(AC59:AN59,"NE") -> 0 | AC59: DA | AD59: DA | AE59: DA | AF59: DA | AG59: DA | AH59: DA | AI59: DA | AJ59: DA | AK59: DA | AL59: DA | AM59: DA | AN59: DA | AO59: =COUNTIF(AC59:AM59,"NE") -> 0 | AP59: DA | AQ59: DA | AR59: DA | AS59: DA | AT59: DA | AU59: DA | AV59: DA | AW59: DA | AX59: DA | AY59: DA | AZ59: DA | BA59: DA | BB59: =COUNTIF(AP59:AZ59,"NE") -> 0 | BC59: DA | BD59: DA | BE59: DA | BF59: DA | BG59: DA | BH59: DA | BI59: DA | BJ59: DA | BK59: DA | BL59: DA | BM59: DA | BN59: DA | BO59: =COUNTIF(BC59:BM59,"NE") -> 0 | BP59: DA | BQ59: DA | BR59: DA | BS59: DA | BT59: DA | BU59: DA | BV59: DA | BW59: DA | BX59: DA | BY59: DA | BZ59: DA | CA59: DA
A60: 59 | B60: 1 | C60: 01007-103 | D60: ZAPAD | E60: 01007-10304 | F60: Z4 Krapina | G60: S386 | H60: S386 | J60: 712121S | K60: 0100/712121S | M60: Jakovlje-istok | N60: 14.10.2019. do ? 2019. modernizacija, implementacija FC (cca 70 dana, rad iz kontejnera) | O60: =COUNTIF(P60:AA60,"NE") -> 0 | P60: DA | Q60: DA | R60: DA | S60: DA | T60: DA | U60: DA | V60: DA | W60: DA | X60: DA | Y60: DA | Z60: DA | AA60: DA | AB60: =COUNTIF(AC60:AN60,"NE") -> 0 | AC60: DA | AD60: DA | AE60: DA | AF60: DA | AG60: DA | AH60: DA | AI60: DA | AJ60: DA | AK60: DA | AL60: DA | AM60: DA | AN60: DA | AO60: =COUNTIF(AC60:AM60,"NE") -> 0 | AP60: DA | AQ60: DA | AR60: DA | AS60: DA | AT60: DA | AU60: DA | AV60: DA | AW60: DA | AX60: DA | AY60: DA | AZ60: DA | BA60: DA | BB60: =COUNTIF(AP60:AZ60,"NE") -> 0 | BC60: DA | BD60: DA | BE60: DA | BF60: DA | BG60: DA | BH60: DA | BI60: DA | BJ60: DA | BK60: DA | BL60: DA | BM60: DA | BN60: DA | BO60: =COUNTIF(BC60:BM60,"NE") -> 0 | BP60: DA | BQ60: DA | BR60: DA | BS60: DA | BT60: DA | BU60: DA | BV60: DA | BW60: DA | BX60: DA | BY60: DA | BZ60: DA | CA60: DA
A61: 60 | C61: 01007-103 | D61: ZAPAD | E61: 01007-10304 | F61: Z4 Krapina | G61: S386 | H61: C386 | I61: C386 | J61: 712121S | K61: 0100/712121S | M61: Jakovlje-istok AB | N61: Z. trajno 27.03.2019. (C+S); 31.01.2016.-brisana OJ 50001473 | O61: =COUNTIF(P61:AA61,"NE") -> 1 | P61: DA | Q61: NE | AB61: =COUNTIF(AC61:AN61,"NE") -> 0 | AC61: DA | AD61: DA | AE61: DA | AF61: DA | AG61: DA | AH61: DA | AI61: DA | AJ61: DA | AK61: DA | AL61: DA | AM61: DA | AN61: DA | AO61: =COUNTIF(AC61:AM61,"NE") -> 0 | AP61: DA | AQ61: DA | AR61: DA | AS61: DA | AT61: DA | AU61: DA | AV61: DA | AW61: DA | AX61: DA | AY61: DA | AZ61: DA | BA61: DA | BB61: =COUNTIF(AP61:AZ61,"NE") -> 0 | BC61: DA | BD61: DA | BE61: DA | BF61: DA | BG61: DA | BH61: DA | BI61: DA | BJ61: DA | BK61: DA | BL61: DA | BM61: DA | BN61: DA | BO61: =COUNTIF(BC61:BM61,"NE") -> 0 | BP61: DA | BQ61: DA | BR61: DA | BS61: DA | BT61: DA | BU61: DA | BV61: DA | BW61: DA | BX61: DA | BY61: DA | BZ61: DA | CA61: DA
A62: 61 | B62: 1 | C62: 01007-103 | D62: ZAPAD | E62: 01007-10304 | F62: Z4 Krapina | G62: S387 | H62: S387 | J62: 712122S | K62: 0100/712122S | M62: Jakovlje-zapad | N62: Zamjena glavnog razvodnog uređaja - RV 05.03.2019. (00-08), 06.03.2019. (12-24); Z. 04.09.-31.10.2017. (radovi na autocesti – nemogućnost pristupa); (modernizacija od 27.01. do 05.05.2016. - kontejner) | O62: =COUNTIF(P62:AA62,"NE") -> 0 | P62: DA | Q62: DA | R62: DA | S62: DA | T62: DA | U62: DA | V62: DA | W62: DA | X62: DA | Y62: DA | Z62: DA | AA62: DA | AB62: =COUNTIF(AC62:AN62,"NE") -> 0 | AC62: DA | AD62: DA | AE62: DA | AF62: DA | AG62: DA | AH62: DA | AI62: DA | AJ62: DA | AK62: DA | AL62: DA | AM62: DA | AN62: DA | AO62: =COUNTIF(AC62:AM62,"NE") -> 0 | AP62: DA | AQ62: DA | AR62: DA | AS62: DA | AT62: DA | AU62: DA | AV62: DA | AW62: DA | AX62: NE | AY62: NE | AZ62: DA | BA62: DA | BB62: =COUNTIF(AP62:AZ62,"NE") -> 2 | BC62: DA | BD62: DA | BE62: DA | BF62: DA | BG62: DA | BH62: DA | BI62: DA | BJ62: DA | BK62: DA | BL62: DA | BM62: DA | BN62: DA | BO62: =COUNTIF(BC62:BM62,"NE") -> 0 | BP62: DA | BQ62: DA | BR62: DA | BS62: DA | BT62: DA | BU62: DA | BV62: DA | BW62: DA | BX62: DA | BY62: DA | BZ62: DA | CA62: DA
A63: 62 | C63: 01007-103 | D63: ZAPAD | E63: 01007-10304 | F63: Z4 Krapina | G63: S387 | H63: C387 | I63: C387 | J63: 712122S | K63: 0100/712122S | M63: Jakovlje-zapad AB | N63: Z. trajno 15.10.2018.(C+S); 31.01.2016.-brisana OJ 50001474 | O63: =COUNTIF(P63:AA63,"NE") -> 0 | AB63: =COUNTIF(AC63:AN63,"NE") -> 1 | AC63: DA | AD63: DA | AE63: DA | AF63: DA | AG63: DA | AH63: DA | AI63: DA | AJ63: DA | AK63: NE | AO63: =COUNTIF(AC63:AM63,"NE") -> 1 | AP63: DA | AQ63: DA | AR63: DA | AS63: DA | AT63: DA | AU63: DA | AV63: DA | AW63: DA | AX63: NE | AY63: NE | AZ63: DA | BA63: DA | BB63: =COUNTIF(AP63:AZ63,"NE") -> 2 | BC63: NE | BD63: NE | BE63: NE | BF63: NE | BG63: NE | BH63: DA | BI63: DA | BJ63: DA | BK63: DA | BL63: DA | BM63: DA | BN63: DA | BO63: =COUNTIF(BC63:BM63,"NE") -> 5 | BP63: DA | BQ63: DA | BR63: DA | BS63: DA | BT63: DA | BU63: DA | BV63: DA | BW63: DA | BX63: DA | BY63: DA | BZ63: DA | CA63: DA
A64: 63 | B64: 1 | C64: 01007-103 | D64: ZAPAD | E64: 01007-10304 | F64: Z4 Krapina | G64: S390 | H64: S390 | J64: 712135S | K64: 0100/712135S | L64: PSUM | M64: Krapina-jug | N64: 29.04.2014. primopredaja BP u ruke partnera - PSUM | O64: =COUNTIF(P64:AA64,"NE") -> 0 | P64: DA | Q64: DA | R64: DA | S64: DA | T64: DA | U64: DA | V64: DA | W64: DA | X64: DA | Y64: DA | Z64: DA | AA64: DA | AB64: =COUNTIF(AC64:AN64,"NE") -> 0 | AC64: DA | AD64: DA | AE64: DA | AF64: DA | AG64: DA | AH64: DA | AI64: DA | AJ64: DA | AK64: DA | AL64: DA | AM64: DA | AN64: DA | AO64: =COUNTIF(AC64:AM64,"NE") -> 0 | AP64: DA | AQ64: DA | AR64: DA | AS64: DA | AT64: DA | AU64: DA | AV64: DA | AW64: DA | AX64: DA | AY64: DA | AZ64: DA | BA64: DA | BB64: =COUNTIF(AP64:AZ64,"NE") -> 0 | BC64: DA | BD64: DA | BE64: DA | BF64: DA | BG64: DA | BH64: DA | BI64: DA | BJ64: DA | BK64: DA | BL64: DA | BM64: DA | BN64: DA | BO64: =COUNTIF(BC64:BM64,"NE") -> 0 | BP64: DA | BQ64: DA | BR64: DA | BS64: DA | BT64: DA | BU64: DA | BV64: DA | BW64: DA | BX64: DA | BY64: DA | BZ64: DA | CA64: DA
A65: 64 | B65: 1 | C65: 01007-103 | D65: ZAPAD | E65: 01007-10304 | F65: Z4 Krapina | G65: S400 | H65: S400 | J65: 712156S | K65: 0100/712156S | L65: PSUM | M65: Krapina-sjever | N65: Z. 16.10. do 28.12.2017. (projekt modernizacije cca 35 dana); 27.03.2015. primopredaja BP u ruke partnera - PSUM | O65: =COUNTIF(P65:AA65,"NE") -> 0 | P65: DA | Q65: DA | R65: DA | S65: DA | T65: DA | U65: DA | V65: DA | W65: DA | X65: DA | Y65: DA | Z65: DA | AA65: DA | AB65: =COUNTIF(AC65:AN65,"NE") -> 0 | AC65: DA | AD65: DA | AE65: DA | AF65: DA | AG65: DA | AH65: DA | AI65: DA | AJ65: DA | AK65: DA | AL65: DA | AM65: DA | AN65: DA | AO65: =COUNTIF(AC65:AM65,"NE") -> 0 | AP65: DA | AQ65: DA | AR65: DA | AS65: DA | AT65: DA | AU65: DA | AV65: DA | AW65: DA | AX65: DA | AY65: NE | AZ65: NE | BA65: NE | BB65: =COUNTIF(AP65:AZ65,"NE") -> 2 | BC65: DA | BD65: DA | BE65: DA | BF65: DA | BG65: DA | BH65: DA | BI65: DA | BJ65: DA | BK65: DA | BL65: DA | BM65: DA | BN65: DA | BO65: =COUNTIF(BC65:BM65,"NE") -> 0 | BP65: DA | BQ65: DA | BR65: DA | BS65: DA | BT65: DA | BU65: DA | BV65: DA | BW65: DA | BX65: DA | BY65: DA | BZ65: DA | CA65: DA
A66: 65 | B66: 1 | C66: 01007-103 | D66: ZAPAD | E66: 01007-10304 | F66: Z4 Krapina | G66: S378 | H66: S378 | J66: 712112S | K66: 0100/712112S | M66: Krapinske Toplice | O66: =COUNTIF(P66:AA66,"NE") -> 0 | P66: DA | Q66: DA | R66: DA | S66: DA | T66: DA | U66: DA | V66: DA | W66: DA | X66: DA | Y66: DA | Z66: DA | AA66: DA | AB66: =COUNTIF(AC66:AN66,"NE") -> 0 | AC66: DA | AD66: DA | AE66: DA | AF66: DA | AG66: DA | AH66: DA | AI66: DA | AJ66: DA | AK66: DA | AL66: DA | AM66: DA | AN66: DA | AO66: =COUNTIF(AC66:AM66,"NE") -> 0 | AP66: DA | AQ66: DA | AR66: DA | AS66: DA | AT66: DA | AU66: DA | AV66: DA | AW66: DA | AX66: DA | AY66: DA | AZ66: DA | BA66: DA | BB66: =COUNTIF(AP66:AZ66,"NE") -> 0 | BC66: DA | BD66: DA | BE66: DA | BF66: DA | BG66: DA | BH66: DA | BI66: DA | BJ66: DA | BK66: DA | BL66: DA | BM66: DA | BN66: DA | BO66: =COUNTIF(BC66:BM66,"NE") -> 0 | BP66: DA | BQ66: DA | BR66: DA | BS66: DA | BT66: DA | BU66: DA | BV66: DA | BW66: DA | BX66: DA | BY66: DA | BZ66: DA | CA66: DA
A67: 66 | B67: 1 | C67: 01007-103 | D67: ZAPAD | E67: 01007-10304 | F67: Z4 Krapina | G67: S389 | H67: S389 | J67: 712134S | K67: 0100/712134S | M67: Kumrovec | O67: =COUNTIF(P67:AA67,"NE") -> 0 | P67: DA | Q67: DA | R67: DA | S67: DA | T67: DA | U67: DA | V67: DA | W67: DA | X67: DA | Y67: DA | Z67: DA | AA67: DA | AB67: =COUNTIF(AC67:AN67,"NE") -> 0 | AC67: DA | AD67: DA | AE67: DA | AF67: DA | AG67: DA | AH67: DA | AI67: DA | AJ67: DA | AK67: DA | AL67: DA | AM67: DA | AN67: DA | AO67: =COUNTIF(AC67:AM67,"NE") -> 0 | AP67: DA | AQ67: DA | AR67: DA | AS67: DA | AT67: DA | AU67: DA | AV67: DA | AW67: DA | AX67: DA | AY67: DA | AZ67: DA | BA67: DA | BB67: =COUNTIF(AP67:AZ67,"NE") -> 0 | BC67: DA | BD67: DA | BE67: DA | BF67: DA | BG67: DA | BH67: DA | BI67: DA | BJ67: DA | BK67: DA | BL67: DA | BM67: DA | BN67: DA | BO67: =COUNTIF(BC67:BM67,"NE") -> 0 | BP67: DA | BQ67: DA | BR67: DA | BS67: DA | BT67: DA | BU67: DA | BV67: DA | BW67: DA | BX67: DA | BY67: DA | BZ67: DA | CA67: DA
A68: 67 | B68: 1 | C68: 01007-103 | D68: ZAPAD | E68: 01007-10304 | F68: Z4 Krapina | G68: S434 | H68: S434 | J68: 711102S | K68: 0100/711102S | M68: Lepa Bukva | N68: Z. 20.09.2019. do 06.10.2019. (AZM - sanacija u tunelu Frukov Krč - nemogućnost pristupa); Z. 02.10. do 08.12.2017. (projekt modernizacije FC cca 35 dana) | O68: =COUNTIF(P68:AA68,"NE") -> 2 | P68: DA | Q68: DA | R68: DA | S68: DA | T68: DA | U68: DA | V68: DA | W68: DA | X68: NE | Y68: NE | Z68: DA | AA68: DA | AB68: =COUNTIF(AC68:AN68,"NE") -> 0 | AC68: DA | AD68: DA | AE68: DA | AF68: DA | AG68: DA | AH68: DA | AI68: DA | AJ68: DA | AK68: DA | AL68: DA | AM68: DA | AN68: DA | AO68: =COUNTIF(AC68:AM68,"NE") -> 0 | AP68: DA | AQ68: DA | AR68: DA | AS68: DA | AT68: DA | AU68: DA | AV68: DA | AW68: DA | AX68: DA | AY68: NE | AZ68: NE | BA68: NE | BB68: =COUNTIF(AP68:AZ68,"NE") -> 2 | BC68: DA | BD68: DA | BE68: DA | BF68: DA | BG68: DA | BH68: DA | BI68: DA | BJ68: DA | BK68: DA | BL68: DA | BM68: DA | BN68: DA | BO68: =COUNTIF(BC68:BM68,"NE") -> 0 | BP68: DA | BQ68: DA | BR68: DA | BS68: DA | BT68: DA | BU68: DA | BV68: DA | BW68: DA | BX68: DA | BY68: DA | BZ68: DA | CA68: DA
A69: 68 | C69: 01007-103 | D69: ZAPAD | E69: 01007-10304 | F69: Z4 Krapina | G69: S434 | H69: C434 | I69: C434 | J69: 711102S | K69: 0100/711102S | M69: Lepa Bukva AB | N69: Z. trajno 15.10.2018.(C+S); 31.01.2016.-brisana OJ 50163492 | O69: =COUNTIF(P69:AA69,"NE") -> 0 | AB69: =COUNTIF(AC69:AN69,"NE") -> 1 | AC69: DA | AD69: DA | AE69: DA | AF69: DA | AG69: DA | AH69: DA | AI69: DA | AJ69: DA | AK69: NE | AO69: =COUNTIF(AC69:AM69,"NE") -> 1 | AP69: DA | AQ69: DA | AR69: DA | AS69: DA | AT69: DA | AU69: DA | AV69: DA | AW69: DA | AX69: DA | AY69: NE | AZ69: NE | BA69: NE | BB69: =COUNTIF(AP69:AZ69,"NE") -> 2 | BC69: DA | BD69: DA | BE69: DA | BF69: DA | BG69: DA | BH69: DA | BI69: DA | BJ69: DA | BK69: DA | BL69: DA | BM69: DA | BN69: DA | BO69: =COUNTIF(BC69:BM69,"NE") -> 0 | BP69: DA | BQ69: DA | BR69: DA | BS69: DA | BT69: DA | BU69: DA | BV69: DA | BW69: DA | BX69: DA | BY69: DA | BZ69: DA | CA69: DA
A70: 69 | B70: 1 | C70: 01007-103 | D70: ZAPAD | E70: 01007-10304 | F70: Z4 Krapina | G70: S383 | H70: S383 | J70: 712118S | K70: 0100/712118S | M70: Lučko-jug | O70: =COUNTIF(P70:AA70,"NE") -> 0 | P70: DA | Q70: DA | R70: DA | S70: DA | T70: DA | U70: DA | V70: DA | W70: DA | X70: DA | Y70: DA | Z70: DA | AA70: DA | AB70: =COUNTIF(AC70:AN70,"NE") -> 0 | AC70: DA | AD70: DA | AE70: DA | AF70: DA | AG70: DA | AH70: DA | AI70: DA | AJ70: DA | AK70: DA | AL70: DA | AM70: DA | AN70: DA | AO70: =COUNTIF(AC70:AM70,"NE") -> 0 | AP70: DA | AQ70: DA | AR70: DA | AS70: DA | AT70: DA | AU70: DA | AV70: DA | AW70: DA | AX70: DA | AY70: DA | AZ70: DA | BA70: DA | BB70: =COUNTIF(AP70:AZ70,"NE") -> 0 | BC70: DA | BD70: DA | BE70: DA | BF70: DA | BG70: DA | BH70: DA | BI70: DA | BJ70: DA | BK70: DA | BL70: DA | BM70: DA | BN70: DA | BO70: =COUNTIF(BC70:BM70,"NE") -> 0 | BP70: DA | BQ70: DA | BR70: DA | BS70: DA | BT70: DA | BU70: DA | BV70: DA | BW70: DA | BX70: DA | BY70: DA | BZ70: DA | CA70: DA
A71: 70 | B71: 1 | C71: 01007-103 | D71: ZAPAD | E71: 01007-10304 | F71: Z4 Krapina | G71: S384 | H71: S384 | J71: 712119S | K71: 0100/712119S | M71: Lučko-sjever | O71: =COUNTIF(P71:AA71,"NE") -> 0 | P71: DA | Q71: DA | R71: DA | S71: DA | T71: DA | U71: DA | V71: DA | W71: DA | X71: DA | Y71: DA | Z71: DA | AA71: DA | AB71: =COUNTIF(AC71:AN71,"NE") -> 0 | AC71: DA | AD71: DA | AE71: DA | AF71: DA | AG71: DA | AH71: DA | AI71: DA | AJ71: DA | AK71: DA | AL71: DA | AM71: DA | AN71: DA | AO71: =COUNTIF(AC71:AM71,"NE") -> 0 | AP71: DA | AQ71: DA | AR71: DA | AS71: DA | AT71: DA | AU71: DA | AV71: DA | AW71: DA | AX71: DA | AY71: DA | AZ71: DA | BA71: DA | BB71: =COUNTIF(AP71:AZ71,"NE") -> 0 | BC71: DA | BD71: DA | BE71: DA | BF71: DA | BG71: DA | BH71: DA | BI71: DA | BJ71: DA | BK71: DA | BL71: DA | BM71: DA | BN71: DA | BO71: =COUNTIF(BC71:BM71,"NE") -> 0 | BP71: DA | BQ71: DA | BR71: DA | BS71: DA | BT71: DA | BU71: DA | BV71: DA | BW71: DA | BX71: DA | BY71: DA | BZ71: DA | CA71: DA
A72: 71 | B72: 1 | C72: 01007-103 | D72: ZAPAD | E72: 01007-10304 | F72: Z4 Krapina | G72: S407 | H72: S407 | J72: 712167S | K72: 0100/712167S | M72: Marija Bistrica | O72: =COUNTIF(P72:AA72,"NE") -> 0 | P72: DA | Q72: DA | R72: DA | S72: DA | T72: DA | U72: DA | V72: DA | W72: DA | X72: DA | Y72: DA | Z72: DA | AA72: DA | AB72: =COUNTIF(AC72:AN72,"NE") -> 0 | AC72: DA | AD72: DA | AE72: DA | AF72: DA | AG72: DA | AH72: DA | AI72: DA | AJ72: DA | AK72: DA | AL72: DA | AM72: DA | AN72: DA | AO72: =COUNTIF(AC72:AM72,"NE") -> 0 | AP72: DA | AQ72: DA | AR72: DA | AS72: DA | AT72: DA | AU72: DA | AV72: DA | AW72: DA | AX72: DA | AY72: DA | AZ72: DA | BA72: DA | BB72: =COUNTIF(AP72:AZ72,"NE") -> 0 | BC72: DA | BD72: DA | BE72: DA | BF72: DA | BG72: DA | BH72: DA | BI72: DA | BJ72: DA | BK72: DA | BL72: DA | BM72: DA | BN72: DA | BO72: =COUNTIF(BC72:BM72,"NE") -> 0 | BP72: DA | BQ72: DA | BR72: DA | BS72: DA | BT72: DA | BU72: DA | BV72: DA | BW72: DA | BX72: DA | BY72: DA | BZ72: DA | CA72: DA
A73: 72 | B73: 1 | C73: 01007-103 | D73: ZAPAD | E73: 01007-10304 | F73: Z4 Krapina | G73: S395 | H73: S395 | J73: 712140S | K73: 0100/712140S | M73: Mokrice-Oroslavje | O73: =COUNTIF(P73:AA73,"NE") -> 0 | P73: DA | Q73: DA | R73: DA | S73: DA | T73: DA | U73: DA | V73: DA | W73: DA | X73: DA | Y73: DA | Z73: DA | AA73: DA | AB73: =COUNTIF(AC73:AN73,"NE") -> 0 | AC73: DA | AD73: DA | AE73: DA | AF73: DA | AG73: DA | AH73: DA | AI73: DA | AJ73: DA | AK73: DA | AL73: DA | AM73: DA | AN73: DA | AO73: =COUNTIF(AC73:AM73,"NE") -> 0 | AP73: DA | AQ73: DA | AR73: DA | AS73: DA | AT73: DA | AU73: DA | AV73: DA | AW73: DA | AX73: DA | AY73: DA | AZ73: DA | BA73: DA | BB73: =COUNTIF(AP73:AZ73,"NE") -> 0 | BC73: DA | BD73: DA | BE73: DA | BF73: DA | BG73: DA | BH73: DA | BI73: DA | BJ73: DA | BK73: DA | BL73: DA | BM73: DA | BN73: DA | BO73: =COUNTIF(BC73:BM73,"NE") -> 0 | BP73: DA | BQ73: DA | BR73: DA | BS73: DA | BT73: DA | BU73: DA | BV73: DA | BW73: DA | BX73: DA | BY73: DA | BZ73: DA | CA73: DA
A74: 73 | B74: 1 | C74: 01007-103 | D74: ZAPAD | E74: 01007-10304 | F74: Z4 Krapina | G74: S394 | H74: S394 | J74: 712139S | K74: 0100/712139S | M74: Oroslavje | O74: =COUNTIF(P74:AA74,"NE") -> 0 | P74: DA | Q74: DA | R74: DA | S74: DA | T74: DA | U74: DA | V74: DA | W74: DA | X74: DA | Y74: DA | Z74: DA | AA74: DA | AB74: =COUNTIF(AC74:AN74,"NE") -> 0 | AC74: DA | AD74: DA | AE74: DA | AF74: DA | AG74: DA | AH74: DA | AI74: DA | AJ74: DA | AK74: DA | AL74: DA | AM74: DA | AN74: DA | AO74: =COUNTIF(AC74:AM74,"NE") -> 0 | AP74: DA | AQ74: DA | AR74: DA | AS74: DA | AT74: DA | AU74: DA | AV74: DA | AW74: DA | AX74: DA | AY74: DA | AZ74: DA | BA74: DA | BB74: =COUNTIF(AP74:AZ74,"NE") -> 0 | BC74: DA | BD74: DA | BE74: DA | BF74: DA | BG74: DA | BH74: DA | BI74: DA | BJ74: DA | BK74: DA | BL74: DA | BM74: DA | BN74: DA | BO74: =COUNTIF(BC74:BM74,"NE") -> 0 | BP74: DA | BQ74: DA | BR74: DA | BS74: DA | BT74: DA | BU74: DA | BV74: DA | BW74: DA | BX74: DA | BY74: DA | BZ74: DA | CA74: DA
A75: 74 | B75: 1 | C75: 01007-103 | D75: ZAPAD | E75: 01007-10304 | F75: Z4 Krapina | G75: S399 | H75: S399 | J75: 712155S | K75: 0100/712155S | L75: PSUM | M75: Zabok | N75: 21.05.2015. primopredaja BP u ruke partnera - PSUM | O75: =COUNTIF(P75:AA75,"NE") -> 0 | P75: DA | Q75: DA | R75: DA | S75: DA | T75: DA | U75: DA | V75: DA | W75: DA | X75: DA | Y75: DA | Z75: DA | AA75: DA | AB75: =COUNTIF(AC75:AN75,"NE") -> 0 | AC75: DA | AD75: DA | AE75: DA | AF75: DA | AG75: DA | AH75: DA | AI75: DA | AJ75: DA | AK75: DA | AL75: DA | AM75: DA | AN75: DA | AO75: =COUNTIF(AC75:AM75,"NE") -> 0 | AP75: DA | AQ75: DA | AR75: DA | AS75: DA | AT75: DA | AU75: DA | AV75: DA | AW75: DA | AX75: DA | AY75: DA | AZ75: DA | BA75: DA | BB75: =COUNTIF(AP75:AZ75,"NE") -> 0 | BC75: DA | BD75: DA | BE75: DA | BF75: DA | BG75: DA | BH75: DA | BI75: DA | BJ75: DA | BK75: DA | BL75: DA | BM75: DA | BN75: DA | BO75: =COUNTIF(BC75:BM75,"NE") -> 0 | BP75: DA | BQ75: DA | BR75: DA | BS75: DA | BT75: DA | BU75: DA | BV75: DA | BW75: DA | BX75: DA | BY75: DA | BZ75: DA | CA75: DA
A76: 75 | B76: 1 | C76: 01007-103 | D76: ZAPAD | E76: 01007-10304 | F76: Z4 Krapina | G76: S403 | H76: S403 | J76: 712160S | K76: 0100/712160S | L76: PSUM | M76: Zaprešić | N76: 22.07.2014. primopredaja BP u ruke partnera - PSUM | O76: =COUNTIF(P76:AA76,"NE") -> 0 | P76: DA | Q76: DA | R76: DA | S76: DA | T76: DA | U76: DA | V76: DA | W76: DA | X76: DA | Y76: DA | Z76: DA | AA76: DA | AB76: =COUNTIF(AC76:AN76,"NE") -> 0 | AC76: DA | AD76: DA | AE76: DA | AF76: DA | AG76: DA | AH76: DA | AI76: DA | AJ76: DA | AK76: DA | AL76: DA | AM76: DA | AN76: DA | AO76: =COUNTIF(AC76:AM76,"NE") -> 0 | AP76: DA | AQ76: DA | AR76: DA | AS76: DA | AT76: DA | AU76: DA | AV76: DA | AW76: DA | AX76: DA | AY76: DA | AZ76: DA | BA76: DA | BB76: =COUNTIF(AP76:AZ76,"NE") -> 0 | BC76: DA | BD76: DA | BE76: DA | BF76: DA | BG76: DA | BH76: DA | BI76: DA | BJ76: DA | BK76: DA | BL76: DA | BM76: DA | BN76: DA | BO76: =COUNTIF(BC76:BM76,"NE") -> 0 | BP76: DA | BQ76: DA | BR76: DA | BS76: DA | BT76: DA | BU76: DA | BV76: DA | BW76: DA | BX76: DA | BY76: DA | BZ76: DA | CA76: DA
A77: 76 | B77: 1 | C77: 01007-103 | D77: ZAPAD | E77: 01007-10304 | F77: Z4 Krapina | G77: S382 | H77: S382 | J77: 712117S | K77: 0100/712117S | M77: Zlatar | N77: Z. 29.01. do 22.03.2016. (modernizacija cca 40 dana) | O77: =COUNTIF(P77:AA77,"NE") -> 0 | P77: DA | Q77: DA | R77: DA | S77: DA | T77: DA | U77: DA | V77: DA | W77: DA | X77: DA | Y77: DA | Z77: DA | AA77: DA | AB77: =COUNTIF(AC77:AN77,"NE") -> 0 | AC77: DA | AD77: DA | AE77: DA | AF77: DA | AG77: DA | AH77: DA | AI77: DA | AJ77: DA | AK77: DA | AL77: DA | AM77: DA | AN77: DA | AO77: =COUNTIF(AC77:AM77,"NE") -> 0 | AP77: DA | AQ77: DA | AR77: DA | AS77: DA | AT77: DA | AU77: DA | AV77: DA | AW77: DA | AX77: DA | AY77: DA | AZ77: DA | BA77: DA | BB77: =COUNTIF(AP77:AZ77,"NE") -> 0 | BC77: NE | BD77: NE | BE77: NE | BF77: DA | BG77: DA | BH77: DA | BI77: DA | BJ77: DA | BK77: DA | BL77: DA | BM77: DA | BN77: DA | BO77: =COUNTIF(BC77:BM77,"NE") -> 3 | BP77: DA | BQ77: DA | BR77: DA | BS77: DA | BT77: DA | BU77: DA | BV77: DA | BW77: DA | BX77: DA | BY77: DA | BZ77: DA | CA77: DA
A78: 77 | B78: 1 | C78: 01007-102 | D78: ISTOK | E78: 01007-10209 | F78: I9 Zagreb-istok | G78: S392 | H78: S392 | J78: 712137S | K78: 0100/712137S | M78: Božjakovina | O78: =COUNTIF(P78:AA78,"NE") -> 0 | P78: DA | Q78: DA | R78: DA | S78: DA | T78: DA | U78: DA | V78: DA | W78: DA | X78: DA | Y78: DA | Z78: DA | AA78: DA | AB78: =COUNTIF(AC78:AN78,"NE") -> 0 | AC78: DA | AD78: DA | AE78: DA | AF78: DA | AG78: DA | AH78: DA | AI78: DA | AJ78: DA | AK78: DA | AL78: DA | AM78: DA | AN78: DA | AO78: =COUNTIF(AC78:AM78,"NE") -> 0 | AP78: DA | AQ78: DA | AR78: DA | AS78: DA | AT78: DA | AU78: DA | AV78: DA | AW78: DA | AX78: DA | AY78: DA | AZ78: DA | BA78: DA | BB78: =COUNTIF(AP78:AZ78,"NE") -> 0 | BC78: DA | BD78: DA | BE78: DA | BF78: DA | BG78: DA | BH78: DA | BI78: DA | BJ78: DA | BK78: DA | BL78: DA | BM78: DA | BN78: DA | BO78: =COUNTIF(BC78:BM78,"NE") -> 0 | BP78: DA | BQ78: DA | BR78: DA | BS78: DA | BT78: DA | BU78: DA | BV78: DA | BW78: DA | BX78: DA | BY78: DA | BZ78: DA | CA78: DA
A79: 78 | B79: 1 | C79: 01007-102 | D79: ISTOK | E79: 01007-10209 | F79: I9 Zagreb-istok | G79: S404 | H79: S404 | J79: 712163S | K79: 0100/712163S | M79: Dugo Selo | O79: =COUNTIF(P79:AA79,"NE") -> 0 | P79: DA | Q79: DA | R79: DA | S79: DA | T79: DA | U79: DA | V79: DA | W79: DA | X79: DA | Y79: DA | Z79: DA | AA79: DA | AB79: =COUNTIF(AC79:AN79,"NE") -> 0 | AC79: DA | AD79: DA | AE79: DA | AF79: DA | AG79: DA | AH79: DA | AI79: DA | AJ79: DA | AK79: DA | AL79: DA | AM79: DA | AN79: DA | AO79: =COUNTIF(AC79:AM79,"NE") -> 0 | AP79: DA | AQ79: DA | AR79: DA | AS79: DA | AT79: DA | AU79: DA | AV79: DA | AW79: DA | AX79: DA | AY79: DA | AZ79: DA | BA79: DA | BB79: =COUNTIF(AP79:AZ79,"NE") -> 0 | BC79: DA | BD79: DA | BE79: DA | BF79: DA | BG79: DA | BH79: DA | BI79: DA | BJ79: DA | BK79: DA | BL79: DA | BM79: DA | BN79: DA | BO79: =COUNTIF(BC79:BM79,"NE") -> 0 | BP79: DA | BQ79: DA | BR79: DA | BS79: DA | BT79: DA | BU79: DA | BV79: DA | BW79: DA | BX79: DA | BY79: DA | BZ79: DA | CA79: DA
A80: 79 | B80: 1 | C80: 01007-102 | D80: ISTOK | E80: 01007-10209 | F80: I9 Zagreb-istok | G80: S011 | H80: S011 | J80: 714211S | K80: 0100/714211S | M80: Đelekovec | O80: =COUNTIF(P80:AA80,"NE") -> 0 | P80: DA | Q80: DA | R80: DA | S80: DA | T80: DA | U80: DA | V80: DA | W80: DA | X80: DA | Y80: DA | Z80: DA | AA80: DA | AB80: =COUNTIF(AC80:AN80,"NE") -> 0 | AC80: DA | AD80: DA | AE80: DA | AF80: DA | AG80: DA | AH80: DA | AI80: DA | AJ80: DA | AK80: DA | AL80: DA | AM80: DA | AN80: DA | AO80: =COUNTIF(AC80:AM80,"NE") -> 0 | AP80: DA | AQ80: DA | AR80: DA | AS80: DA | AT80: DA | AU80: DA | AV80: DA | AW80: DA | AX80: DA | AY80: DA | AZ80: DA | BA80: DA | BB80: =COUNTIF(AP80:AZ80,"NE") -> 0 | BC80: DA | BD80: DA | BE80: DA | BF80: DA | BG80: DA | BH80: DA | BI80: DA | BJ80: DA | BK80: DA | BL80: DA | BM80: DA | BN80: DA | BO80: =COUNTIF(BC80:BM80,"NE") -> 0 | BP80: DA | BQ80: DA | BR80: DA | BS80: DA | BT80: DA | BU80: DA | BV80: DA | BW80: DA | BX80: DA | BY80: DA | BZ80: DA | CA80: DA
A81: 80 | B81: 1 | C81: 01007-102 | D81: ISTOK | E81: 01007-10209 | F81: I9 Zagreb-istok | G81: S012 | H81: S012 | J81: 714212S | K81: 0100/714212S | L81: PSUM | M81: Koprivnica-Bjelovarska | N81: Z. 16.05. do 26.06.2017. (projekt održavanja cca 35 dana); 16.12.2015. primopredaja BP u ruke partnera - PSUM | O81: =COUNTIF(P81:AA81,"NE") -> 0 | P81: DA | Q81: DA | R81: DA | S81: DA | T81: DA | U81: DA | V81: DA | W81: DA | X81: DA | Y81: DA | Z81: DA | AA81: DA | AB81: =COUNTIF(AC81:AN81,"NE") -> 0 | AC81: DA | AD81: DA | AE81: DA | AF81: DA | AG81: DA | AH81: DA | AI81: DA | AJ81: DA | AK81: DA | AL81: DA | AM81: DA | AN81: DA | AO81: =COUNTIF(AC81:AM81,"NE") -> 0 | AP81: DA | AQ81: DA | AR81: DA | AS81: DA | AT81: NE | AU81: NE | AV81: DA | AW81: DA | AX81: DA | AY81: DA | AZ81: DA | BA81: DA | BB81: =COUNTIF(AP81:AZ81,"NE") -> 2 | BC81: DA | BD81: DA | BE81: DA | BF81: DA | BG81: DA | BH81: DA | BI81: DA | BJ81: DA | BK81: DA | BL81: DA | BM81: DA | BN81: DA | BO81: =COUNTIF(BC81:BM81,"NE") -> 0 | BP81: DA | BQ81: DA | BR81: DA | BS81: DA | BT81: DA | BU81: DA | BV81: DA | BW81: DA | BX81: DA | BY81: DA | BZ81: DA | CA81: NE
A82: 81 | B82: 1 | C82: 01007-102 | D82: ISTOK | E82: 01007-10209 | F82: I9 Zagreb-istok | G82: S006 | H82: S006 | J82: 714206S | K82: 0100/714206S | L82: PSUM | M82: Koprivnica-Kolodvorska | N82: Z. 16.04. do 12.06.2018. (implementacija FC - cca 37 dana); 16.04.2018. promjena PSUM partnera (21.12.2015. primopredaja BP u ruke partnera - PSUM) | O82: =COUNTIF(P82:AA82,"NE") -> 0 | P82: DA | Q82: DA | R82: DA | S82: DA | T82: DA | U82: DA | V82: DA | W82: DA | X82: DA | Y82: DA | Z82: DA | AA82: DA | AB82: =COUNTIF(AC82:AN82,"NE") -> 4 | AC82: DA | AD82: DA | AE82: DA | AF82: NE | AG82: NE | AH82: NE | AI82: NE | AJ82: DA | AK82: DA | AL82: DA | AM82: DA | AN82: DA | AO82: =COUNTIF(AC82:AM82,"NE") -> 4 | AP82: DA | AQ82: DA | AR82: DA | AS82: DA | AT82: DA | AU82: DA | AV82: DA | AW82: DA | AX82: DA | AY82: DA | AZ82: DA | BA82: DA | BB82: =COUNTIF(AP82:AZ82,"NE") -> 0 | BC82: DA | BD82: DA | BE82: DA | BF82: DA | BG82: DA | BH82: DA | BI82: DA | BJ82: DA | BK82: DA | BL82: DA | BM82: DA | BN82: DA | BO82: =COUNTIF(BC82:BM82,"NE") -> 0 | BP82: DA | BQ82: DA | BR82: DA | BS82: DA | BT82: DA | BU82: DA | BV82: DA | BW82: DA | BX82: DA | BY82: DA | BZ82: DA | CA82: NE
A83: 82 | C83: 01007-102 | D83: ISTOK | E83: 01007-10209 | F83: I9 Zagreb-istok | G83: S006 | H83: C006 | I83: C006 | J83: 714206S | K83: 0100/714206S | L83: PSUM | M83: Koprivnica-Kolodvorska AB | N83: Z. trajno 15.10.2018.(C+S); Z. 16.04. do 18.06.2018. (implementacija FC - cca 37 dana); 16.04.2018. promjena PSUM partnera (21.12.2015. primopredaja BP u ruke partnera - PSUM); 31.01.2016.-brisana OJ 50001667 | O83: =COUNTIF(P83:AA83,"NE") -> 0 | AB83: =COUNTIF(AC83:AN83,"NE") -> 4 | AC83: DA | AD83: DA | AE83: DA | AF83: NE | AG83: NE | AH83: NE | AI83: DA | AJ83: DA | AK83: NE | AO83: =COUNTIF(AC83:AM83,"NE") -> 4 | AP83: DA | AQ83: DA | AR83: DA | AS83: DA | AT83: DA | AU83: DA | AV83: DA | AW83: DA | AX83: DA | AY83: DA | AZ83: DA | BA83: DA | BB83: =COUNTIF(AP83:AZ83,"NE") -> 0 | BC83: NE | BD83: NE | BE83: NE | BF83: NE | BG83: NE | BH83: NE | BI83: DA | BJ83: DA | BK83: DA | BL83: DA | BM83: DA | BN83: DA | BO83: =COUNTIF(BC83:BM83,"NE") -> 6 | BP83: DA | BQ83: DA | BR83: NE | BS83: NE | BT83: NE | BU83: NE | BV83: NE | BW83: NE | BX83: NE | BY83: NE | BZ83: NE | CA83: NE
A84: 83 | C84: 01007-102 | D84: ISTOK | E84: 01007-10209 | F84: I9 Zagreb-istok | G84: S006 | H84: S425 | I84: S425 | J84: 714206L | K84: 0100/714206S | L84: PSUM | M84: Koprivnica-Kolodvorska AP | N84: Z. trajno 31.01.2016.-brisana OJ 50001668; 21.12.2015. primopredaja BP u ruke partnera - PSUM | O84: =COUNTIF(P84:AA84,"NE") -> 0 | AB84: =COUNTIF(AC84:AN84,"NE") -> 0 | AO84: =COUNTIF(AC84:AM84,"NE") -> 0 | BB84: =COUNTIF(AP84:AZ84,"NE") -> 0 | BO84: =COUNTIF(BC84:BM84,"NE") -> 0 | BP84: DA | BQ84: DA | BR84: DA | BS84: DA | BT84: DA | BU84: DA | BV84: DA | BW84: DA | BX84: DA | BY84: DA | BZ84: DA | CA84: NE
A85: 84 | B85: 1 | C85: 01007-102 | D85: ISTOK | E85: 01007-10209 | F85: I9 Zagreb-istok | G85: S008 | H85: S008 | J85: 714208S | K85: 0100/714208S | M85: Križevci-Tomislavova | N85: Z. 29.08.2017. do 15.02.2018. (kapitalna rekonstrukcija - KDR - cca 120 dana) | O85: =COUNTIF(P85:AA85,"NE") -> 0 | P85: DA | Q85: DA | R85: DA | S85: DA | T85: DA | U85: DA | V85: DA | W85: DA | X85: DA | Y85: DA | Z85: DA | AA85: DA | AB85: =COUNTIF(AC85:AN85,"NE") -> 2 | AC85: NE | AD85: NE | AE85: DA | AF85: DA | AG85: DA | AH85: DA | AI85: DA | AJ85: DA | AK85: DA | AL85: DA | AM85: DA | AN85: DA | AO85: =COUNTIF(AC85:AM85,"NE") -> 2 | AP85: DA | AQ85: DA | AR85: DA | AS85: DA | AT85: DA | AU85: DA | AV85: DA | AW85: NE | AX85: NE | AY85: NE | AZ85: NE | BA85: NE | BB85: =COUNTIF(AP85:AZ85,"NE") -> 4 | BC85: DA | BD85: DA | BE85: DA | BF85: DA | BG85: DA | BH85: DA | BI85: DA | BJ85: DA | BK85: DA | BL85: DA | BM85: DA | BN85: DA | BO85: =COUNTIF(BC85:BM85,"NE") -> 0 | BP85: DA | BQ85: DA | BR85: DA | BS85: DA | BT85: DA | BU85: DA | BV85: DA | BW85: DA | BX85: DA | BY85: DA | BZ85: DA | CA85: DA
A86: 85 | B86: 1 | C86: 01007-102 | D86: ISTOK | E86: 01007-10209 | F86: I9 Zagreb-istok | G86: S014 | H86: S014 | J86: 714214S | K86: 0100/714214S | M86: Križevci-Zagrebačka | N86: Z. 18.07.2019. do 26.12.2019. (kapitalna rekonstrukcija - KDR - cca 140 dana) | O86: =COUNTIF(P86:AA86,"NE") -> 6 | P86: DA | Q86: DA | R86: DA | S86: DA | T86: DA | U86: DA | V86: NE | W86: NE | X86: NE | Y86: NE | Z86: NE | AA86: NE | AB86: =COUNTIF(AC86:AN86,"NE") -> 0 | AC86: DA | AD86: DA | AE86: DA | AF86: DA | AG86: DA | AH86: DA | AI86: DA | AJ86: DA | AK86: DA | AL86: DA | AM86: DA | AN86: DA | AO86: =COUNTIF(AC86:AM86,"NE") -> 0 | AP86: DA | AQ86: DA | AR86: DA | AS86: DA | AT86: DA | AU86: DA | AV86: DA | AW86: DA | AX86: DA | AY86: DA | AZ86: DA | BA86: DA | BB86: =COUNTIF(AP86:AZ86,"NE") -> 0 | BC86: DA | BD86: DA | BE86: DA | BF86: DA | BG86: DA | BH86: DA | BI86: DA | BJ86: DA | BK86: DA | BL86: DA | BM86: DA | BN86: DA | BO86: =COUNTIF(BC86:BM86,"NE") -> 0 | BP86: DA | BQ86: DA | BR86: DA | BS86: DA | BT86: DA | BU86: DA | BV86: DA | BW86: DA | BX86: DA | BY86: DA | BZ86: DA | CA86: DA
A87: 86 | B87: 1 | C87: 01007-102 | D87: ISTOK | E87: 01007-10209 | F87: I9 Zagreb-istok | G87: S405 | H87: S405 | J87: 712165S | K87: 0100/712165S | M87: Sesvete-jug | N87: Z. 14.03. do 20.05.2016. (zamjena spremnika cca. 45 dana) | O87: =COUNTIF(P87:AA87,"NE") -> 0 | P87: DA | Q87: DA | R87: DA | S87: DA | T87: DA | U87: DA | V87: DA | W87: DA | X87: DA | Y87: DA | Z87: DA | AA87: DA | AB87: =COUNTIF(AC87:AN87,"NE") -> 0 | AC87: DA | AD87: DA | AE87: DA | AF87: DA | AG87: DA | AH87: DA | AI87: DA | AJ87: DA | AK87: DA | AL87: DA | AM87: DA | AN87: DA | AO87: =COUNTIF(AC87:AM87,"NE") -> 0 | AP87: DA | AQ87: DA | AR87: DA | AS87: DA | AT87: DA | AU87: DA | AV87: DA | AW87: DA | AX87: DA | AY87: DA | AZ87: DA | BA87: DA | BB87: =COUNTIF(AP87:AZ87,"NE") -> 0 | BC87: DA | BD87: DA | BE87: NE | BF87: NE | BG87: NE | BH87: DA | BI87: DA | BJ87: DA | BK87: DA | BL87: DA | BM87: DA | BN87: DA | BO87: =COUNTIF(BC87:BM87,"NE") -> 3 | BP87: DA | BQ87: DA | BR87: DA | BS87: DA | BT87: DA | BU87: DA | BV87: DA | BW87: DA | BX87: DA | BY87: DA | BZ87: DA | CA87: DA
A88: 87 | B88: 1 | C88: 01007-102 | D88: ISTOK | E88: 01007-10209 | F88: I9 Zagreb-istok | G88: S397 | H88: S397 | J88: 712142S | K88: 0100/712142S | M88: Sesvete-sjever | O88: =COUNTIF(P88:AA88,"NE") -> 0 | P88: DA | Q88: DA | R88: DA | S88: DA | T88: DA | U88: DA | V88: DA | W88: DA | X88: DA | Y88: DA | Z88: DA | AA88: DA | AB88: =COUNTIF(AC88:AN88,"NE") -> 0 | AC88: DA | AD88: DA | AE88: DA | AF88: DA | AG88: DA | AH88: DA | AI88: DA | AJ88: DA | AK88: DA | AL88: DA | AM88: DA | AN88: DA | AO88: =COUNTIF(AC88:AM88,"NE") -> 0 | AP88: DA | AQ88: DA | AR88: DA | AS88: DA | AT88: DA | AU88: DA | AV88: DA | AW88: DA | AX88: DA | AY88: DA | AZ88: DA | BA88: DA | BB88: =COUNTIF(AP88:AZ88,"NE") -> 0 | BC88: DA | BD88: DA | BE88: DA | BF88: DA | BG88: DA | BH88: DA | BI88: DA | BJ88: DA | BK88: DA | BL88: DA | BM88: DA | BN88: DA | BO88: =COUNTIF(BC88:BM88,"NE") -> 0 | BP88: DA | BQ88: DA | BR88: DA | BS88: DA | BT88: DA | BU88: DA | BV88: DA | BW88: DA | BX88: DA | BY88: DA | BZ88: DA | CA88: DA
A89: 88 | B89: 1 | C89: 01007-102 | D89: ISTOK | E89: 01007-10209 | F89: I9 Zagreb-istok | G89: S415 | H89: S415 | J89: 711101S | K89: 0100/711101S | L89: PSUM | M89: Sesvetski Kraljevec | N89: 04.11.2019. do 23.12.2019. implementacija FC (cca 28 dana, rad iz kontejnera); 28.02.2017. promjena PSUM partnera (05.05.2014. primopredaja BP u ruke partnera - PSUM) | O89: =COUNTIF(P89:AA89,"NE") -> 0 | P89: DA | Q89: DA | R89: DA | S89: DA | T89: DA | U89: DA | V89: DA | W89: DA | X89: DA | Y89: DA | Z89: DA | AA89: DA | AB89: =COUNTIF(AC89:AN89,"NE") -> 0 | AC89: DA | AD89: DA | AE89: DA | AF89: DA | AG89: DA | AH89: DA | AI89: DA | AJ89: DA | AK89: DA | AL89: DA | AM89: DA | AN89: DA | AO89: =COUNTIF(AC89:AM89,"NE") -> 0 | AP89: DA | AQ89: NE | AR89: DA | AS89: DA | AT89: DA | AU89: DA | AV89: DA | AW89: DA | AX89: DA | AY89: DA | AZ89: DA | BA89: DA | BB89: =COUNTIF(AP89:AZ89,"NE") -> 1 | BC89: DA | BD89: DA | BE89: DA | BF89: DA | BG89: DA | BH89: DA | BI89: DA | BJ89: DA | BK89: DA | BL89: DA | BM89: DA | BN89: DA | BO89: =COUNTIF(BC89:BM89,"NE") -> 0 | BP89: DA | BQ89: DA | BR89: DA | BS89: DA | BT89: DA | BU89: DA | BV89: DA | BW89: DA | BX89: DA | BY89: DA | BZ89: DA | CA89: DA
A90: 89 | C90: 01007-102 | D90: ISTOK | E90: 01007-10209 | F90: I9 Zagreb-istok | G90: S415 | H90: C415 | I90: C415 | J90: 711101C | K90: 0100/711101S | M90: Sesvetski Kraljevec AB | N90: Z. 30.08.2012.-brisana OJ 50006003 (Z. 18.08.2012 modernizacija BP) | O90: =COUNTIF(P90:AA90,"NE") -> 0 | AB90: =COUNTIF(AC90:AN90,"NE") -> 0 | AO90: =COUNTIF(AC90:AM90,"NE") -> 0 | BB90: =COUNTIF(AP90:AZ90,"NE") -> 0 | BO90: =COUNTIF(BC90:BM90,"NE") -> 0
A91: 90 | B91: 1 | C91: 01007-102 | D91: ISTOK | E91: 01007-10209 | F91: I9 Zagreb-istok | G91: S393 | H91: S393 | J91: 712138S | K91: 0100/712138S | L91: PSUM | M91: Sv. Ivan Zelina | N91: 11.03.2015. primopredaja BP u ruke partnera - PSUM | O91: =COUNTIF(P91:AA91,"NE") -> 0 | P91: DA | Q91: DA | R91: DA | S91: DA | T91: DA | U91: DA | V91: DA | W91: DA | X91: DA | Y91: DA | Z91: DA | AA91: DA | AB91: =COUNTIF(AC91:AN91,"NE") -> 0 | AC91: DA | AD91: DA | AE91: DA | AF91: DA | AG91: DA | AH91: DA | AI91: DA | AJ91: DA | AK91: DA | AL91: DA | AM91: DA | AN91: DA | AO91: =COUNTIF(AC91:AM91,"NE") -> 0 | AP91: DA | AQ91: DA | AR91: DA | AS91: DA | AT91: DA | AU91: DA | AV91: DA | AW91: DA | AX91: DA | AY91: DA | AZ91: DA | BA91: DA | BB91: =COUNTIF(AP91:AZ91,"NE") -> 0 | BC91: DA | BD91: DA | BE91: DA | BF91: DA | BG91: DA | BH91: DA | BI91: DA | BJ91: DA | BK91: DA | BL91: DA | BM91: DA | BN91: DA | BO91: =COUNTIF(BC91:BM91,"NE") -> 0 | BP91: DA | BQ91: DA | BR91: DA | BS91: DA | BT91: DA | BU91: DA | BV91: DA | BW91: DA | BX91: DA | BY91: DA | BZ91: DA | CA91: DA
A92: 91 | B92: 1 | C92: 01007-102 | D92: ISTOK | E92: 01007-10209 | F92: I9 Zagreb-istok | G92: S018 | H92: S018 | J92: 714218S | K92: 0100/714218S | M92: Sveti Ivan Žabno | O92: =COUNTIF(P92:AA92,"NE") -> 0 | P92: DA | Q92: DA | R92: DA | S92: DA | T92: DA | U92: DA | V92: DA | W92: DA | X92: DA | Y92: DA | Z92: DA | AA92: DA | AB92: =COUNTIF(AC92:AN92,"NE") -> 0 | AC92: DA | AD92: DA | AE92: DA | AF92: DA | AG92: DA | AH92: DA | AI92: DA | AJ92: DA | AK92: DA | AL92: DA | AM92: DA | AN92: DA | AO92: =COUNTIF(AC92:AM92,"NE") -> 0 | AP92: DA | AQ92: DA | AR92: DA | AS92: DA | AT92: DA | AU92: DA | AV92: DA | AW92: DA | AX92: DA | AY92: DA | AZ92: DA | BA92: DA | BB92: =COUNTIF(AP92:AZ92,"NE") -> 0 | BC92: DA | BD92: DA | BE92: DA | BF92: DA | BG92: DA | BH92: DA | BI92: DA | BJ92: DA | BK92: DA | BL92: DA | BM92: DA | BN92: DA | BO92: =COUNTIF(BC92:BM92,"NE") -> 0 | BP92: DA | BQ92: DA | BR92: DA | BS92: DA | BT92: DA | BU92: DA | BV92: DA | BW92: DA | BX92: DA | BY92: DA | BZ92: DA | CA92: DA
A93: 92 | B93: 1 | C93: 01007-102 | D93: ISTOK | E93: 01007-10209 | F93: I9 Zagreb-istok | G93: S401 | H93: S401 | J93: 712157S | K93: 0100/712157S | M93: Vrbovec | O93: =COUNTIF(P93:AA93,"NE") -> 0 | P93: DA | Q93: DA | R93: DA | S93: DA | T93: DA | U93: DA | V93: DA | W93: DA | X93: DA | Y93: DA | Z93: DA | AA93: DA | AB93: =COUNTIF(AC93:AN93,"NE") -> 0 | AC93: DA | AD93: DA | AE93: DA | AF93: DA | AG93: DA | AH93: DA | AI93: DA | AJ93: DA | AK93: DA | AL93: DA | AM93: DA | AN93: DA | AO93: =COUNTIF(AC93:AM93,"NE") -> 0 | AP93: DA | AQ93: DA | AR93: DA | AS93: DA | AT93: DA | AU93: DA | AV93: DA | AW93: DA | AX93: DA | AY93: DA | AZ93: DA | BA93: DA | BB93: =COUNTIF(AP93:AZ93,"NE") -> 0 | BC93: DA | BD93: DA | BE93: DA | BF93: DA | BG93: DA | BH93: DA | BI93: DA | BJ93: DA | BK93: DA | BL93: DA | BM93: DA | BN93: DA | BO93: =COUNTIF(BC93:BM93,"NE") -> 0 | BP93: DA | BQ93: DA | BR93: DA | BS93: DA | BT93: DA | BU93: DA | BV93: DA | BW93: DA | BX93: DA | BY93: DA | BZ93: DA | CA93: DA
A94: 93 | B94: 1 | C94: 01007-102 | D94: ISTOK | E94: 01007-10209 | F94: I9 Zagreb-istok | G94: S406 | H94: S406 | J94: 712166S | K94: 0100/712166S | M94: Vrbovec-Dubrava | N94: Z. 22.10. do 05.11.2018. (zamjena spremnika); (27.08.) 05.09. do 25.09.2018. (nadogradnja spremnika) | O94: =COUNTIF(P94:AA94,"NE") -> 0 | P94: DA | Q94: DA | R94: DA | S94: DA | T94: DA | U94: DA | V94: DA | W94: DA | X94: DA | Y94: DA | Z94: DA | AA94: DA | AB94: =COUNTIF(AC94:AN94,"NE") -> 3 | AC94: DA | AD94: DA | AE94: DA | AF94: DA | AG94: DA | AH94: DA | AI94: DA | AJ94: DA | AK94: NE | AL94: NE | AM94: NE | AN94: DA | AO94: =COUNTIF(AC94:AM94,"NE") -> 3 | AP94: DA | AQ94: DA | AR94: DA | AS94: DA | AT94: DA | AU94: DA | AV94: DA | AW94: DA | AX94: DA | AY94: DA | AZ94: DA | BA94: DA | BB94: =COUNTIF(AP94:AZ94,"NE") -> 0 | BC94: DA | BD94: DA | BE94: DA | BF94: DA | BG94: DA | BH94: DA | BI94: DA | BJ94: DA | BK94: DA | BL94: DA | BM94: DA | BN94: DA | BO94: =COUNTIF(BC94:BM94,"NE") -> 0 | BP94: DA | BQ94: DA | BR94: DA | BS94: DA | BT94: DA | BU94: DA | BV94: DA | BW94: DA | BX94: DA | BY94: DA | BZ94: DA | CA94: DA
A95: 94 | B95: 1 | C95: 01007-102 | D95: ISTOK | E95: 01007-10207 | F95: I7 Kutina | G95: S183 | H95: S183 | J95: 712201S | K95: 0100/712201S | M95: Banova Jaruga | N95: Z. 21.11. do 11.12.2016. (projekt održavanja cca. 20 dana) | O95: =COUNTIF(P95:AA95,"NE") -> 0 | P95: DA | Q95: DA | R95: DA | S95: DA | T95: DA | U95: DA | V95: DA | W95: DA | X95: DA | Y95: DA | Z95: DA | AA95: DA | AB95: =COUNTIF(AC95:AN95,"NE") -> 0 | AC95: DA | AD95: DA | AE95: DA | AF95: DA | AG95: DA | AH95: DA | AI95: DA | AJ95: DA | AK95: DA | AL95: DA | AM95: DA | AN95: DA | AO95: =COUNTIF(AC95:AM95,"NE") -> 0 | AP95: DA | AQ95: DA | AR95: DA | AS95: DA | AT95: DA | AU95: DA | AV95: DA | AW95: DA | AX95: DA | AY95: DA | AZ95: DA | BA95: DA | BB95: =COUNTIF(AP95:AZ95,"NE") -> 0 | BC95: DA | BD95: DA | BE95: DA | BF95: DA | BG95: DA | BH95: DA | BI95: DA | BJ95: DA | BK95: DA | BL95: DA | BM95: NE | BN95: NE | BO95: =COUNTIF(BC95:BM95,"NE") -> 1 | BP95: DA | BQ95: DA | BR95: DA | BS95: DA | BT95: DA | BU95: DA | BV95: DA | BW95: DA | BX95: DA | BY95: DA | BZ95: DA | CA95: DA
A96: 95 | B96: 1 | C96: 01007-102 | D96: ISTOK | E96: 01007-10207 | F96: I7 Kutina | G96: S010 | H96: S010 | J96: 714210S | K96: 0100/714210S | M96: Čazma | O96: =COUNTIF(P96:AA96,"NE") -> 0 | P96: DA | Q96: DA | R96: DA | S96: DA | T96: DA | U96: DA | V96: DA | W96: DA | X96: DA | Y96: DA | Z96: DA | AA96: DA | AB96: =COUNTIF(AC96:AN96,"NE") -> 0 | AC96: DA | AD96: DA | AE96: DA | AF96: DA | AG96: DA | AH96: DA | AI96: DA | AJ96: DA | AK96: DA | AL96: DA | AM96: DA | AN96: DA | AO96: =COUNTIF(AC96:AM96,"NE") -> 0 | AP96: DA | AQ96: DA | AR96: DA | AS96: DA | AT96: DA | AU96: DA | AV96: DA | AW96: DA | AX96: DA | AY96: DA | AZ96: DA | BA96: DA | BB96: =COUNTIF(AP96:AZ96,"NE") -> 0 | BC96: DA | BD96: DA | BE96: DA | BF96: DA | BG96: DA | BH96: DA | BI96: DA | BJ96: DA | BK96: DA | BL96: DA | BM96: DA | BN96: DA | BO96: =COUNTIF(BC96:BM96,"NE") -> 0 | BP96: DA | BQ96: DA | BR96: DA | BS96: DA | BT96: DA | BU96: DA | BV96: DA | BW96: DA | BX96: DA | BY96: DA | BZ96: DA | CA96: DA
A97: 96 | B97: 1 | C97: 01007-102 | D97: ISTOK | E97: 01007-10207 | F97: I7 Kutina | G97: S398 | H97: S398 | J97: 712144S | K97: 0100/712144S | M97: Ivanić Grad | O97: =COUNTIF(P97:AA97,"NE") -> 0 | P97: DA | Q97: DA | R97: DA | S97: DA | T97: DA | U97: DA | V97: DA | W97: DA | X97: DA | Y97: DA | Z97: DA | AA97: DA | AB97: =COUNTIF(AC97:AN97,"NE") -> 0 | AC97: DA | AD97: DA | AE97: DA | AF97: DA | AG97: DA | AH97: DA | AI97: DA | AJ97: DA | AK97: DA | AL97: DA | AM97: DA | AN97: DA | AO97: =COUNTIF(AC97:AM97,"NE") -> 0 | AP97: DA | AQ97: DA | AR97: DA | AS97: DA | AT97: DA | AU97: DA | AV97: DA | AW97: DA | AX97: DA | AY97: DA | AZ97: DA | BA97: DA | BB97: =COUNTIF(AP97:AZ97,"NE") -> 0 | BC97: DA | BD97: DA | BE97: DA | BF97: DA | BG97: DA | BH97: DA | BI97: DA | BJ97: DA | BK97: DA | BL97: DA | BM97: DA | BN97: DA | BO97: =COUNTIF(BC97:BM97,"NE") -> 0 | BP97: DA | BQ97: DA | BR97: DA | BS97: DA | BT97: DA | BU97: DA | BV97: DA | BW97: DA | BX97: DA | BY97: DA | BZ97: DA | CA97: DA
A98: 97 | B98: 1 | C98: 01007-102 | D98: ISTOK | E98: 01007-10207 | F98: I7 Kutina | G98: S373 | H98: S373 | J98: 712104S | K98: 0100/712104S | M98: Ježevo-jug | O98: =COUNTIF(P98:AA98,"NE") -> 0 | P98: DA | Q98: DA | R98: DA | S98: DA | T98: DA | U98: DA | V98: DA | W98: DA | X98: DA | Y98: DA | Z98: DA | AA98: DA | AB98: =COUNTIF(AC98:AN98,"NE") -> 0 | AC98: DA | AD98: DA | AE98: DA | AF98: DA | AG98: DA | AH98: DA | AI98: DA | AJ98: DA | AK98: DA | AL98: DA | AM98: DA | AN98: DA | AO98: =COUNTIF(AC98:AM98,"NE") -> 0 | AP98: DA | AQ98: DA | AR98: DA | AS98: DA | AT98: DA | AU98: DA | AV98: DA | AW98: DA | AX98: DA | AY98: DA | AZ98: DA | BA98: DA | BB98: =COUNTIF(AP98:AZ98,"NE") -> 0 | BC98: DA | BD98: DA | BE98: DA | BF98: DA | BG98: DA | BH98: DA | BI98: DA | BJ98: DA | BK98: DA | BL98: DA | BM98: DA | BN98: DA | BO98: =COUNTIF(BC98:BM98,"NE") -> 0 | BP98: DA | BQ98: DA | BR98: DA | BS98: DA | BT98: DA | BU98: DA | BV98: DA | BW98: DA | BX98: DA | BY98: DA | BZ98: DA | CA98: DA
A99: 98 | C99: 01007-102 | D99: ISTOK | E99: 01007-10207 | F99: I7 Kutina | G99: S373 | H99: C373 | I99: C373 | J99: 712104S | K99: 0100/712104S | M99: Ježevo-jug AB | N99: Z. trajno 27.03.2019. (C+S); Z. 12.02. do 16.05.2018. (implementacija FC - cca 35 dana); 31.01.2016.-brisana OJ 50001471; 01.12.2014. promjena naziva (restoran=AB) | O99: =COUNTIF(P99:AA99,"NE") -> 1 | P99: DA | Q99: NE | AB99: =COUNTIF(AC99:AN99,"NE") -> 4 | AC99: DA | AD99: NE | AE99: NE | AF99: NE | AG99: NE | AH99: DA | AI99: DA | AJ99: DA | AK99: DA | AL99: DA | AM99: DA | AN99: DA | AO99: =COUNTIF(AC99:AM99,"NE") -> 4 | AP99: DA | AQ99: DA | AR99: DA | AS99: DA | AT99: DA | AU99: DA | AV99: DA | AW99: DA | AX99: DA | AY99: DA | AZ99: DA | BA99: DA | BB99: =COUNTIF(AP99:AZ99,"NE") -> 0 | BC99: DA | BD99: DA | BE99: DA | BF99: DA | BG99: DA | BH99: DA | BI99: DA | BJ99: DA | BK99: DA | BL99: DA | BM99: DA | BN99: DA | BO99: =COUNTIF(BC99:BM99,"NE") -> 0 | BP99: DA | BQ99: DA | BR99: DA | BS99: DA | BT99: DA | BU99: DA | BV99: DA | BW99: DA | BX99: DA | BY99: DA | BZ99: DA | CA99: DA
A100: 99 | B100: 1 | C100: 01007-102 | D100: ISTOK | E100: 01007-10207 | F100: I7 Kutina | G100: S374 | H100: S374 | J100: 712105S | K100: 0100/712105S | M100: Ježevo-sjever | O100: =COUNTIF(P100:AA100,"NE") -> 0 | P100: DA | Q100: DA | R100: DA | S100: DA | T100: DA | U100: DA | V100: DA | W100: DA | X100: DA | Y100: DA | Z100: DA | AA100: DA | AB100: =COUNTIF(AC100:AN100,"NE") -> 0 | AC100: DA | AD100: DA | AE100: DA | AF100: DA | AG100: DA | AH100: DA | AI100: DA | AJ100: DA | AK100: DA | AL100: DA | AM100: DA | AN100: DA | AO100: =COUNTIF(AC100:AM100,"NE") -> 0 | AP100: DA | AQ100: DA | AR100: DA | AS100: DA | AT100: DA | AU100: DA | AV100: DA | AW100: DA | AX100: DA | AY100: DA | AZ100: DA | BA100: DA | BB100: =COUNTIF(AP100:AZ100,"NE") -> 0 | BC100: DA | BD100: DA | BE100: DA | BF100: DA | BG100: DA | BH100: DA | BI100: DA | BJ100: DA | BK100: DA | BL100: DA | BM100: DA | BN100: DA | BO100: =COUNTIF(BC100:BM100,"NE") -> 0 | BP100: DA | BQ100: DA | BR100: DA | BS100: DA | BT100: DA | BU100: DA | BV100: DA | BW100: DA | BX100: DA | BY100: DA | BZ100: DA | CA100: DA
...
